Workbook

Sheet LEASE_MASTER
A1: lease_id | B1: lease_reference | C1: property_id | D1: property_name | E1: property_address | F1: customer_id | G1: customer_name | H1: start_date | I1: end_date | J1: monthly_rent | K1: frequency | L1: frequency_months
A2: 1 | B2: LEASE-BH-F1-2025 | C2: 22 | D2: Flat 1 - 3 West Gate | E2: Flat 1 - 3 West Gate, Long Eaton NG10 1EG | F2: 79 | G2: Achal (Delegated for Udayan) | H2: 45715 | J2: 795 | K2: monthly | L2: 1
A3: 2 | B3: LEASE-BH-F2-2025 | C3: 23 | D3: Flat 2 - 3 West Gate | E3: Flat 2 - 3 West Gate, Long Eaton NG10 1EG | F3: 79 | G3: Achal (Delegated for Udayan) | H3: 45715 | J3: 740 | K3: monthly | L3: 1
A4: 3 | B4: LEASE-BH-F3-2025 | C4: 42 | D4: Flat 3 - 3 West Gate | E4: Flat 3 - 3 West Gate, Long Eaton NG10 1EG | F4: 79 | G4: Achal (Delegated for Udayan) | H4: 45727 | J4: 740 | K4: monthly | L4: 1
A5: 4 | B5: LEASE-BH-F4-2025 | C5: 30 | D5: Flat 4 - 3 West Gate | E5: Flat 4 - 3 West Gate, Long Eaton NG10 1EG | F5: 79 | G5: Achal (Delegated for Udayan) | H5: 45713 | J5: 855 | K5: monthly | L5: 1
A6: 5 | B6: LEASE-BH-F5-2025 | C6: 21 | D6: Flat 5 - 3 West Gate | E6: Flat 5 - 3 West Gate, Long Eaton NG10 1EG | F6: 79 | G6: Achal (Delegated for Udayan) | H6: 45698 | J6: 740 | K6: monthly | L6: 1
A7: 6 | B7: LEASE-BH-F6-2025 | C7: 1 | D7: Flat 6 - 3 West Gate | E7: Flat 6 - 3 West Gate, Long Eaton NG10 1EG | F7: 79 | G7: Achal (Delegated for Udayan) | H7: 45744 | J7: 740 | K7: monthly | L7: 1
A8: 7 | B8: LEASE-BH-F7-2025 | C8: 20 | D8: Flat 7 - 3 West Gate | E8: Flat 7 - 3 West Gate, Long Eaton NG10 1EG | F8: 79 | G8: Achal (Delegated for Udayan) | H8: 45707 | I8: 45887 | J8: 700 | K8: monthly | L8: 1
A9: 8 | B9: LEASE-BH-F8-2025 | C9: 40 | D9: Flat 8 - 3 West Gate | E9: Flat 8 - 3 West Gate, Long Eaton NG10 1EG | F9: 79 | G9: Achal (Delegated for Udayan) | H9: 45712 | J9: 675 | K9: monthly | L9: 1
A10: 9 | B10: LEASE-BH-F9-2025 | C10: 6 | D10: Flat 9 - 3 West Gate | E10: Flat 9 - 3 West Gate, Long Eaton NG10 1EG | F10: 79 | G10: Achal (Delegated for Udayan) | H10: 45736 | J10: 700 | K10: monthly | L10: 1
A11: 10 | B11: LEASE-BH-F10-2025 | C11: 7 | D11: Flat 10 - 3 West Gate | E11: Flat 10 - 3 West Gate, Long Eaton NG10 1EG | F11: 79 | G11: Achal (Delegated for Udayan) | H11: 45722 | I11: 45894 | J11: 735 | K11: monthly | L11: 1
A12: 11 | B12: LEASE-BH-F10-2025B | C12: 7 | D12: Flat 10 - 3 West Gate | E12: Flat 10 - 3 West Gate, Long Eaton NG10 1EG | F12: 79 | G12: Achal (Delegated for Udayan) | H12: 45903 | J12: 795 | K12: monthly | L12: 1
A13: 12 | B13: LEASE-BH-F11-2025 | C13: 17 | D13: Flat 11 - 3 West Gate | E13: Flat 11 - 3 West Gate, Long Eaton NG10 1EG | F13: 79 | G13: Achal (Delegated for Udayan) | H13: 45722 | J13: 795 | K13: monthly | L13: 1
A14: 13 | B14: LEASE-BH-F12-2025 | C14: 41 | D14: Flat 12 - 3 West Gate | E14: Flat 12 - 3 West Gate, Long Eaton NG10 1EG | F14: 79 | G14: Achal (Delegated for Udayan) | H14: 45754 | I14: 45814 | J14: 675 | K14: monthly | L14: 1
A15: 14 | B15: LEASE-BH-F12-2025B | C15: 41 | D15: Flat 12 - 3 West Gate | E15: Flat 12 - 3 West Gate, Long Eaton NG10 1EG | F15: 79 | G15: Achal (Delegated for Udayan) | H15: 45860 | I15: 45951 | J15: 5687 | K15: quarterly | L15: 3
A16: 15 | B16: LEASE-BH-F13-2025 | C16: 25 | D16: Flat 13 - 3 West Gate | E16: Flat 13 - 3 West Gate, Long Eaton NG10 1EG | F16: 79 | G16: Achal (Delegated for Udayan) | H16: 45719 | I16: 45963 | J16: 800 | K16: monthly | L16: 1
A17: 16 | B17: LEASE-BH-F14-2025 | C17: 24 | D17: Flat 14 - 3 West Gate | E17: Flat 14 - 3 West Gate, Long Eaton NG10 1EG | F17: 79 | G17: Achal (Delegated for Udayan) | H17: 45744 | J17: 795 | K17: monthly | L17: 1
A18: 17 | B18: LEASE-BH-F15-2025 | C18: 44 | D18: Flat 15 - 3 West Gate | E18: Flat 15 - 3 West Gate, Long Eaton NG10 1EG | F18: 79 | G18: Achal (Delegated for Udayan) | H18: 45703 | J18: 740 | K18: monthly | L18: 1
A19: 18 | B19: LEASE-BH-F16-2025 | C19: 2 | D19: Flat 16 - 3 West Gate | E19: Flat 16 - 3 West Gate, Long Eaton NG10 1EG | F19: 79 | G19: Achal (Delegated for Udayan) | H19: 45726 | I19: 45902 | J19: 740 | K19: monthly | L19: 1
A20: 19 | B20: LEASE-BH-F17-2025 | C20: 5 | D20: Flat 17 - 3 West Gate | E20: Flat 17 - 3 West Gate, Long Eaton NG10 1EG | F20: 79 | G20: Achal (Delegated for Udayan) | H20: 45705 | J20: 700 | K20: monthly | L20: 1
A21: 20 | B21: LEASE-BH-F18-2025 | C21: 33 | D21: Flat 18 - 3 West Gate | E21: Flat 18 - 3 West Gate, Long Eaton NG10 1EG | F21: 79 | G21: Achal (Delegated for Udayan) | H21: 45687 | I21: 45783 | J21: 740 | K21: monthly | L21: 1
A22: 21 | B22: LEASE-BH-F18-2025B | C22: 33 | D22: Flat 18 - 3 West Gate | E22: Flat 18 - 3 West Gate, Long Eaton NG10 1EG | F22: 79 | G22: Achal (Delegated for Udayan) | H22: 45818 | J22: 795 | K22: monthly | L22: 1
A23: 22 | B23: LEASE-BH-F19-2025 | C23: 43 | D23: Flat 19 - 3 West Gate | E23: Flat 19 - 3 West Gate, Long Eaton NG10 1EG | F23: 79 | G23: Achal (Delegated for Udayan) | H23: 45730 | I23: 45869 | J23: 740 | K23: monthly | L23: 1
A24: 23 | B24: LEASE-BH-F19-2025B | C24: 43 | D24: Flat 19 - 3 West Gate | E24: Flat 19 - 3 West Gate, Long Eaton NG10 1EG | F24: 79 | G24: Achal (Delegated for Udayan) | H24: 45901 | J24: 795 | K24: monthly | L24: 1
A25: 24 | B25: LEASE-BH-F20-2025 | C25: 39 | D25: Flat 20 - 3 West Gate | E25: Flat 20 - 3 West Gate, Long Eaton NG10 1EG | F25: 79 | G25: Achal (Delegated for Udayan) | H25: 45732 | J25: 700 | K25: monthly | L25: 1
A26: 25 | B26: LEASE-BH-F21-2025 | C26: 31 | D26: Flat 21 - 3 West Gate | E26: Flat 21 - 3 West Gate, Long Eaton NG10 1EG | F26: 79 | G26: Achal (Delegated for Udayan) | H26: 45687 | J26: 795 | K26: monthly | L26: 1
A27: 26 | B27: LEASE-BH-F22-2025 | C27: 14 | D27: Flat 22 - 3 West Gate | E27: Flat 22 - 3 West Gate, Long Eaton NG10 1EG | F27: 79 | G27: Achal (Delegated for Udayan) | H27: 45717 | J27: 740 | K27: monthly | L27: 1
A28: 27 | B28: LEASE-BH-F23-2025 | C28: 29 | D28: Flat 23 - 3 West Gate | E28: Flat 23 - 3 West Gate, Long Eaton NG10 1EG | F28: 79 | G28: Achal (Delegated for Udayan) | H28: 45830 | J28: 795 | K28: monthly | L28: 1
A29: 28 | B29: LEASE-BH-F24-2025 | C29: 37 | D29: Flat 24 - 3 West Gate | E29: Flat 24 - 3 West Gate, Long Eaton NG10 1EG | F29: 79 | G29: Achal (Delegated for Udayan) | H29: 45700 | J29: 810 | K29: monthly | L29: 1
A30: 29 | B30: LEASE-BH-F26-2025 | C30: 32 | D30: Flat 26 - 3 West Gate | E30: Flat 26 - 3 West Gate, Long Eaton NG10 1EG | F30: 79 | G30: Achal (Delegated for Udayan) | H30: 45730 | J30: 675 | K30: monthly | L30: 1
A31: 30 | B31: LEASE-BH-F27-2025 | C31: 27 | D31: Flat 27 - 3 West Gate | E31: Flat 27 - 3 West Gate, Long Eaton NG10 1EG | F31: 79 | G31: Achal (Delegated for Udayan) | H31: 45716 | J31: 700 | K31: monthly | L31: 1
A32: 31 | B32: LEASE-BH-F28-2025 | C32: 15 | D32: Flat 28 - 3 West Gate | E32: Flat 28 - 3 West Gate, Long Eaton NG10 1EG | F32: 79 | G32: Achal (Delegated for Udayan) | H32: 45744 | I32: 45927 | J32: 740 | K32: monthly | L32: 1
A33: 32 | B33: LEASE-BH-F29-2025 | C33: 11 | D33: Flat 29 - 3 West Gate | E33: Flat 29 - 3 West Gate, Long Eaton NG10 1EG | F33: 79 | G33: Achal (Delegated for Udayan) | H33: 45715 | J33: 740 | K33: monthly | L33: 1
A34: 33 | B34: LEASE-BH-F30-2025 | C34: 10 | D34: Flat 30 - 3 West Gate | E34: Flat 30 - 3 West Gate, Long Eaton NG10 1EG | F34: 79 | G34: Achal (Delegated for Udayan) | H34: 45722 | I34: 45966 | J34: 740 | K34: monthly | L34: 1
A35: 34 | B35: LEASE-BH-PS1-2025 | C35: 38 | D35: Parking Space 1 - 3 West Gate | E35: Parking Space 1, 3 West Gate, Long Eaton NG10 1EG | F35: 79 | G35: Achal (Delegated for Udayan) | H35: 45842 | J35: 60 | K35: monthly | L35: 1
A36: 35 | B36: LEASE-BH-PS2-2025 | C36: 36 | D36: Parking Space 2 - 3 West Gate | E36: Parking Space 2 - 3 West Gate, Long Eaton NG10 1EG | F36: 79 | G36: Achal (Delegated for Udayan) | H36: 45852 | J36: 60 | K36: monthly | L36: 1
A37: 36 | B37: LEASE-KH-F-2024 | C37: 16 | D37: Apartment F - Knighton Hayes Manor | E37: Apartment F - Knighton Hayes Manor, 6A Ratcliffe Road, Leicester LE2 3TB | F37: 79 | G37: Achal (Delegated for Udayan) | H37: 45648 | J37: 1125 | K37: monthly | L37: 1
A38: 78 | B38: LEASE-BH-F12-2025C | C38: 41 | D38: Flat 12 - 3 West Gate | E38: Flat 12 - 3 West Gate, Long Eaton NG10 1EG | F38: 79 | G38: Achal (Delegated for Udayan) | H38: 45940 | J38: 795 | K38: monthly | L38: 1
A39: 79 | B39: LEASE-BH-F25-2025 | C39: 28 | D39: Flat 25 - 3 West Gate | E39: Flat 25 - 3 West Gate, Long Eaton NG10 1EG | F39: 79 | G39: Achal (Delegated for Udayan) | H39: 45922 | J39: 765 | K39: monthly | L39: 1
A40: 86 | B40: BODEN-BLOCK-2025 | C40: 69 | D40: Boden House Block - Block Property | E40: Boden House Block - Block Property, 3 West Gate, Long Eaton NG10 1EG | F40: 79 | G40: Achal (Delegated for Udayan) | H40: 45717 | J40: 0.01 | K40: yearly | L40: 12
A41: 88 | B41: LEASE-88 | C41: 15 | D41: Flat 28 - 3 West Gate | E41: Flat 28 - 3 West Gate, Long Eaton NG10 1EG | F41: 79 | G41: Achal (Delegated for Udayan) | H41: 45956 | J41: 750 | K41: monthly | L41: 1
A42: 131 | B42: LEASE-131 | C42: 10 | D42: Flat 30 - 3 West Gate | E42: Flat 30 - 3 West Gate, Long Eaton NG10 1EG | F42: 79 | G42: Achal (Delegated for Udayan) | H42: 45996 | J42: 775 | K42: monthly | L42: 1

Sheet TRANSACTIONS
A1: transaction_id | B1: transaction_date | C1: invoice_id | D1: property_id | E1: property_name | F1: customer_id | G1: category | H1: transaction_type | I1: amount | J1: description | K1: lease_reference
A2: 8 | B2: 45685 | C2: 36 | D2: 16 | E2: Apartment F - Knighton Hayes Manor | F2: 13 | G2: rent | H2: rent_received | I2: 2250 | J2: Rent for flat apt f kh
A3: 5 | B3: 45703 | C3: 20 | D3: 33 | E3: Flat 18 - 3 West Gate | F3: 76 | G3: rent | H3: rent_received | I3: 740 | J3: Rent for flat 18 boden
A4: 6 | B4: 45703 | C4: 25 | D4: 31 | E4: Flat 21 - 3 West Gate | F4: 12 | G4: rent | H4: rent_received | I4: 795 | J4: Rent for flat 21 boden
A5: 1 | B5: 45705 | C5: 5 | D5: 21 | E5: Flat 5 - 3 West Gate | F5: 28 | G5: rent | H5: rent_received | I5: 740 | J5: Rent for flat 5 boden
A6: 2 | B6: 45707 | C6: 7 | D6: 20 | E6: Flat 7 - 3 West Gate | F6: 8 | G6: rent | H6: rent_received | I6: 700 | J6: Rent for flat 7 boden
A7: 3 | B7: 45707 | C7: 17 | D7: 44 | E7: Flat 15 - 3 West Gate | F7: 36 | G7: rent | H7: rent_received | I7: 740 | J7: Rent for flat 15 boden
A8: 4 | B8: 45708 | C8: 19 | D8: 5 | E8: Flat 17 - 3 West Gate | F8: 3 | G8: rent | H8: rent_received | I8: 700 | J8: Rent for flat 17 boden
A9: 7 | B9: 45708 | C9: 28 | D9: 37 | E9: Flat 24 - 3 West Gate | F9: 16 | G9: rent | H9: rent_received | I9: 810 | J9: Rent for flat 24 boden
A10: 38 | B10: 45712 | C10: 36 | D10: 16 | E10: Apartment F - Knighton Hayes Manor | F10: 13 | G10: rent | H10: rent_received | I10: 2250 | J10: rent for apartment F KH for 2 months
A11: 32 | B11: 45716 | C11: 26 | D11: 14 | E11: Flat 22 - 3 West Gate | F11: 9 | G11: rent | H11: rent_received | I11: 740 | J11: rent for flat 22 boden
A12: 34 | B12: 45716 | C12: 29 | D12: 32 | E12: Flat 26 - 3 West Gate | F12: 2 | G12: rent | H12: rent_received | I12: 675 | J12: rent for flat 26 boden
A13: 23 | B13: 45718 | C13: 12 | D13: 17 | E13: Flat 11 - 3 West Gate | F13: 17 | G13: rent | H13: rent_received | I13: 795 | J13: rent for flat 11 boden
... A273: 806 | B273: 45993 | C273: 86 | D273: 69 | E273: Boden House Block - Block Property | F273: 0 | G273: Rent | H273: incoming_payment | I273: 1000 | J273: Tenant Payment - property account - Boden House Block - Block Property (Tenant ID: , Deposit: N/A)

Sheet RENT_DUE
A1: lease_id | B1: lease_reference | C1: property_name | D1: period_start | E1: period_end | F1: period_days | G1: lease_start | H1: lease_end | I1: monthly_rent | J1: rent_due_day | K1: lease_days_in_period | L1: prorated_rent_due | M1: management_fee | N1: service_fee | O1: total_commission | P1: net_to_owner
A2: 1 | B2: LEASE-BH-F1-2025 | C2: Flat 1 - 3 West Gate | D2: 45715 | E2: 45742 | F2: 28 | G2: 45715 | I2: 795 | J2: 27 | K2: 28 | L2: =IF(F2 < 28, ROUND(F2 / DAY(EOMONTH(D2, 0)) * I2, 2), I2) -> 0 | M2: =L2 * 0.10 -> 0 | N2: =L2 * 0.05 -> 0 | O2: =M2 + N2 -> 0 | P2: =L2 - O2 -> 0
A3: 1 | B3: LEASE-BH-F1-2025 | C3: Flat 1 - 3 West Gate | D3: 45743 | E3: 45773 | F3: 31 | G3: 45715 | I3: 795 | J3: 27 | K3: 31 | L3: =IF(F3 < 28, ROUND(F3 / DAY(EOMONTH(D3, 0)) * I3, 2), I3) -> 0 | M3: =L3 * 0.10 -> 0 | N3: =L3 * 0.05 -> 0 | O3: =M3 + N3 -> 0 | P3: =L3 - O3 -> 0
A4: 1 | B4: LEASE-BH-F1-2025 | C4: Flat 1 - 3 West Gate | D4: 45774 | E4: 45803 | F4: 30 | G4: 45715 | I4: 795 | J4: 27 | K4: 30 | L4: =IF(F4 < 28, ROUND(F4 / DAY(EOMONTH(D4, 0)) * I4, 2), I4) -> 0 | M4: =L4 * 0.10 -> 0 | N4: =L4 * 0.05 -> 0 | O4: =M4 + N4 -> 0 | P4: =L4 - O4 -> 0
A5: 1 | B5: LEASE-BH-F1-2025 | C5: Flat 1 - 3 West Gate | D5: 45804 | E5: 45834 | F5: 31 | G5: 45715 | I5: 795 | J5: 27 | K5: 31 | L5: =IF(F5 < 28, ROUND(F5 / DAY(EOMONTH(D5, 0)) * I5, 2), I5) -> 0 | M5: =L5 * 0.10 -> 0 | N5: =L5 * 0.05 -> 0 | O5: =M5 + N5 -> 0 | P5: =L5 - O5 -> 0
A6: 1 | B6: LEASE-BH-F1-2025 | C6: Flat 1 - 3 West Gate | D6: 45835 | E6: 45864 | F6: 30 | G6: 45715 | I6: 795 | J6: 27 | K6: 30 | L6: =IF(F6 < 28, ROUND(F6 / DAY(EOMONTH(D6, 0)) * I6, 2), I6) -> 0 | M6: =L6 * 0.10 -> 0 | N6: =L6 * 0.05 -> 0 | O6: =M6 + N6 -> 0 | P6: =L6 - O6 -> 0
A7: 1 | B7: LEASE-BH-F1-2025 | C7: Flat 1 - 3 West Gate | D7: 45865 | E7: 45895 | F7: 31 | G7: 45715 | I7: 795 | J7: 27 | K7: 31 | L7: =IF(F7 < 28, ROUND(F7 / DAY(EOMONTH(D7, 0)) * I7, 2), I7) -> 0 | M7: =L7 * 0.10 -> 0 | N7: =L7 * 0.05 -> 0 | O7: =M7 + N7 -> 0 | P7: =L7 - O7 -> 0
A8: 1 | B8: LEASE-BH-F1-2025 | C8: Flat 1 - 3 West Gate | D8: 45896 | E8: 45926 | F8: 31 | G8: 45715 | I8: 795 | J8: 27 | K8: 31 | L8: =IF(F8 < 28, ROUND(F8 / DAY(EOMONTH(D8, 0)) * I8, 2), I8) -> 0 | M8: =L8 * 0.10 -> 0 | N8: =L8 * 0.05 -> 0 | O8: =M8 + N8 -> 0 | P8: =L8 - O8 -> 0
A9: 1 | B9: LEASE-BH-F1-2025 | C9: Flat 1 - 3 West Gate | D9: 45927 | E9: 45956 | F9: 30 | G9: 45715 | I9: 795 | J9: 27 | K9: 30 | L9: =IF(F9 < 28, ROUND(F9 / DAY(EOMONTH(D9, 0)) * I9, 2), I9) -> 0 | M9: =L9 * 0.10 -> 0 | N9: =L9 * 0.05 -> 0 | O9: =M9 + N9 -> 0 | P9: =L9 - O9 -> 0
A10: 1 | B10: LEASE-BH-F1-2025 | C10: Flat 1 - 3 West Gate | D10: 45957 | E10: 45987 | F10: 31 | G10: 45715 | I10: 795 | J10: 27 | K10: 31 | L10: =IF(F10 < 28, ROUND(F10 / DAY(EOMONTH(D10, 0)) * I10, 2), I10) -> 0 | M10: =L10 * 0.10 -> 0 | N10: =L10 * 0.05 -> 0 | O10: =M10 + N10 -> 0 | P10: =L10 - O10 -> 0
A11: 2 | B11: LEASE-BH-F2-2025 | C11: Flat 2 - 3 West Gate | D11: 45715 | E11: 45742 | F11: 28 | G11: 45715 | I11: 740 | J11: 27 | K11: 28 | L11: =IF(F11 < 28, ROUND(F11 / DAY(EOMONTH(D11, 0)) * I11, 2), I11) -> 0 | M11: =L11 * 0.10 -> 0 | N11: =L11 * 0.05 -> 0 | O11: =M11 + N11 -> 0 | P11: =L11 - O11 -> 0
A12: 2 | B12: LEASE-BH-F2-2025 | C12: Flat 2 - 3 West Gate | D12: 45743 | E12: 45773 | F12: 31 | G12: 45715 | I12: 740 | J12: 27 | K12: 31 | L12: =IF(F12 < 28, ROUND(F12 / DAY(EOMONTH(D12, 0)) * I12, 2), I12) -> 0 | M12: =L12 * 0.10 -> 0 | N12: =L12 * 0.05 -> 0 | O12: =M12 + N12 -> 0 | P12: =L12 - O12 -> 0
A13: 2 | B13: LEASE-BH-F2-2025 | C13: Flat 2 - 3 West Gate | D13: 45774 | E13: 45803 | F13: 30 | G13: 45715 | I13: 740 | J13: 27 | K13: 30 | L13: =IF(F13 < 28, ROUND(F13 / DAY(EOMONTH(D13, 0)) * I13, 2), I13) -> 0 | M13: =L13 * 0.10 -> 0 | N13: =L13 * 0.05 -> 0 | O13: =M13 + N13 -> 0 | P13: =L13 - O13 -> 0
... A55: 6 | B55: LEASE-BH-F6-2025 | C55: Flat 6 - 3 West Gate | D55: 45958 | E55: 45988 | F55: 31 | G55: 45744 | I55: 740 | J55: 28 | K55: 31 | L55: =IF(F55 < 28, ROUND(F55 / DAY(EOMONTH(D55, 0)) * I55, 2), I55) -> 0 | M55: =L55 * 0.10 -> 0 | N55: =L55 * 0.05 -> 0 | O55: =M55 + N55 -> 0 | P55: =L55 - O55 -> 0
A56: 7 | B56: LEASE-BH-F7-2025 | C56: Flat 7 - 3 West Gate | D56: 45707 | E56: 45734 | F56: 28 | G56: 45707 | H56: 45887 | I56: 700 | J56: 19 | K56: 28 | L56: =IF(F56 < 28, ROUND(F56 / DAY(EOMONTH(D56, 0)) * I56, 2), I56) -> 0 | M56: =L56 * 0.10 -> 0 | N56: =L56 * 0.05 -> 0 | O56: =M56 + N56 -> 0 | P56: =L56 - O56 -> 0
A57: 7 | B57: LEASE-BH-F7-2025 | C57: Flat 7 - 3 West Gate | D57: 45735 | E57: 45765 | F57: 31 | G57: 45707 | H57: 45887 | I57: 700 | J57: 19 | K57: 31 | L57: =IF(F57 < 28, ROUND(F57 / DAY(EOMONTH(D57, 0)) * I57, 2), I57) -> 0 | M57: =L57 * 0.10 -> 0 | N57: =L57 * 0.05 -> 0 | O57: =M57 + N57 -> 0 | P57: =L57 - O57 -> 0
A58: 7 | B58: LEASE-BH-F7-2025 | C58: Flat 7 - 3 West Gate | D58: 45766 | E58: 45795 | F58: 30 | G58: 45707 | H58: 45887 | I58: 700 | J58: 19 | K58: 30 | L58: =IF(F58 < 28, ROUND(F58 / DAY(EOMONTH(D58, 0)) * I58, 2), I58) -> 0 | M58: =L58 * 0.10 -> 0 | N58: =L58 * 0.05 -> 0 | O58: =M58 + N58 -> 0 | P58: =L58 - O58 -> 0
A59: 7 | B59: LEASE-BH-F7-2025 | C59: Flat 7 - 3 West Gate | D59: 45796 | E59: 45826 | F59: 31 | G59: 45707 | H59: 45887 | I59: 700 | J59: 19 | K59: 31 | L59: =IF(F59 < 28, ROUND(F59 / DAY(EOMONTH(D59, 0)) * I59, 2), I59) -> 0 | M59: =L59 * 0.10 -> 0 | N59: =L59 * 0.05 -> 0 | O59: =M59 + N59 -> 0 | P59: =L59 - O59 -> 0
A60: 7 | B60: LEASE-BH-F7-2025 | C60: Flat 7 - 3 West Gate | D60: 45827 | E60: 45856 | F60: 30 | G60: 45707 | H60: 45887 | I60: 700 | J60: 19 | K60: 30 | L60: =IF(F60 < 28, ROUND(F60 / DAY(EOMONTH(D60, 0)) * I60, 2), I60) -> 0 | M60: =L60 * 0.10 -> 0 | N60: =L60 * 0.05 -> 0 | O60: =M60 + N60 -> 0 | P60: =L60 - O60 -> 0
A61: 7 | B61: LEASE-BH-F7-2025 | C61: Flat 7 - 3 West Gate | D61: 45857 | E61: 45887 | F61: 31 | G61: 45707 | H61: 45887 | I61: 700 | J61: 19 | K61: 31 | L61: =IF(F61 < 28, ROUND(F61 / DAY(EOMONTH(D61, 0)) * I61, 2), I61) -> 0 | M61: =L61 * 0.10 -> 0 | N61: =L61 * 0.05 -> 0 | O61: =M61 + N61 -> 0 | P61: =L61 - O61 -> 0
A62: 8 | B62: LEASE-BH-F8-2025 | C62: Flat 8 - 3 West Gate | D62: 45712 | E62: 45739 | F62: 28 | G62: 45712 | I62: 675 | J62: 24 | K62: 28 | L62: =IF(F62 < 28, ROUND(F62 / DAY(EOMONTH(D62, 0)) * I62, 2), I62) -> 0 | M62: =L62 * 0.10 -> 0 | N62: =L62 * 0.05 -> 0 | O62: =M62 + N62 -> 0 | P62: =L62 - O62 -> 0
A63: 8 | B63: LEASE-BH-F8-2025 | C63: Flat 8 - 3 West Gate | D63: 45740 | E63: 45770 | F63: 31 | G63: 45712 | I63: 675 | J63: 24 | K63: 31 | L63: =IF(F63 < 28, ROUND(F63 / DAY(EOMONTH(D63, 0)) * I63, 2), I63) -> 0 | M63: =L63 * 0.10 -> 0 | N63: =L63 * 0.05 -> 0 | O63: =M63 + N63 -> 0 | P63: =L63 - O63 -> 0
A64: 8 | B64: LEASE-BH-F8-2025 | C64: Flat 8 - 3 West Gate | D64: 45771 | E64: 45800 | F64: 30 | G64: 45712 | I64: 675 | J64: 24 | K64: 30 | L64: =IF(F64 < 28, ROUND(F64 / DAY(EOMONTH(D64, 0)) * I64, 2), I64) -> 0 | M64: =L64 * 0.10 -> 0 | N64: =L64 * 0.05 -> 0 | O64: =M64 + N64 -> 0 | P64: =L64 - O64 -> 0
A65: 8 | B65: LEASE-BH-F8-2025 | C65: Flat 8 - 3 West Gate | D65: 45801 | E65: 45831 | F65: 31 | G65: 45712 | I65: 675 | J65: 24 | K65: 31 | L65: =IF(F65 < 28, ROUND(F65 / DAY(EOMONTH(D65, 0)) * I65, 2), I65) -> 0 | M65: =L65 * 0.10 -> 0 | N65: =L65 * 0.05 -> 0 | O65: =M65 + N65 -> 0 | P65: =L65 - O65 -> 0
A66: 8 | B66: LEASE-BH-F8-2025 | C66: Flat 8 - 3 West Gate | D66: 45832 | E66: 45861 | F66: 30 | G66: 45712 | I66: 675 | J66: 24 | K66: 30 | L66: =IF(F66 < 28, ROUND(F66 / DAY(EOMONTH(D66, 0)) * I66, 2), I66) -> 0 | M66: =L66 * 0.10 -> 0 | N66: =L66 * 0.05 -> 0 | O66: =M66 + N66 -> 0 | P66: =L66 - O66 -> 0
A67: 8 | B67: LEASE-BH-F8-2025 | C67: Flat 8 - 3 West Gate | D67: 45862 | E67: 45892 | F67: 31 | G67: 45712 | I67: 675 | J67: 24 | K67: 31 | L67: =IF(F67 < 28, ROUND(F67 / DAY(EOMONTH(D67, 0)) * I67, 2), I67) -> 0 | M67: =L67 * 0.10 -> 0 | N67: =L67 * 0.05 -> 0 | O67: =M67 + N67 -> 0 | P67: =L67 - O67 -> 0
A68: 8 | B68: LEASE-BH-F8-2025 | C68: Flat 8 - 3 West Gate | D68: 45893 | E68: 45923 | F68: 31 | G68: 45712 | I68: 675 | J68: 24 | K68: 31 | L68: =IF(F68 < 28, ROUND(F68 / DAY(EOMONTH(D68, 0)) * I68, 2), I68) -> 0 | M68: =L68 * 0.10 -> 0 | N68: =L68 * 0.05 -> 0 | O68: =M68 + N68 -> 0 | P68: =L68 - O68 -> 0
A69: 8 | B69: LEASE-BH-F8-2025 | C69: Flat 8 - 3 West Gate | D69: 45924 | E69: 45953 | F69: 30 | G69: 45712 | I69: 675 | J69: 24 | K69: 30 | L69: =IF(F69 < 28, ROUND(F69 / DAY(EOMONTH(D69, 0)) * I69, 2), I69) -> 0 | M69: =L69 * 0.10 -> 0 | N69: =L69 * 0.05 -> 0 | O69: =M69 + N69 -> 0 | P69: =L69 - O69 -> 0
A70: 8 | B70: LEASE-BH-F8-2025 | C70: Flat 8 - 3 West Gate | D70: 45954 | E70: 45984 | F70: 31 | G70: 45712 | I70: 675 | J70: 24 | K70: 31 | L70: =IF(F70 < 28, ROUND(F70 / DAY(EOMONTH(D70, 0)) * I70, 2), I70) -> 0 | M70: =L70 * 0.10 -> 0 | N70: =L70 * 0.05 -> 0 | O70: =M70 + N70 -> 0 | P70: =L70 - O70 -> 0
A71: 9 | B71: LEASE-BH-F9-2025 | C71: Flat 9 - 3 West Gate | D71: 45736 | E71: 45766 | F71: 31 | G71: 45736 | I71: 700 | J71: 20 | K71: 31 | L71: =IF(F71 < 28, ROUND(F71 / DAY(EOMONTH(D71, 0)) * I71, 2), I71) -> 0 | M71: =L71 * 0.10 -> 0 | N71: =L71 * 0.05 -> 0 | O71: =M71 + N71 -> 0 | P71: =L71 - O71 -> 0
A72: 9 | B72: LEASE-BH-F9-2025 | C72: Flat 9 - 3 West Gate | D72: 45767 | E72: 45796 | F72: 30 | G72: 45736 | I72: 700 | J72: 20 | K72: 30 | L72: =IF(F72 < 28, ROUND(F72 / DAY(EOMONTH(D72, 0)) * I72, 2), I72) -> 0 | M72: =L72 * 0.10 -> 0 | N72: =L72 * 0.05 -> 0 | O72: =M72 + N72 -> 0 | P72: =L72 - O72 -> 0
A73: 9 | B73: LEASE-BH-F9-2025 | C73: Flat 9 - 3 West Gate | D73: 45797 | E73: 45827 | F73: 31 | G73: 45736 | I73: 700 | J73: 20 | K73: 31 | L73: =IF(F73 < 28, ROUND(F73 / DAY(EOMONTH(D73, 0)) * I73, 2), I73) -> 0 | M73: =L73 * 0.10 -> 0 | N73: =L73 * 0.05 -> 0 | O73: =M73 + N73 -> 0 | P73: =L73 - O73 -> 0
... A79: 9 | B79: LEASE-BH-F9-2025 | C79: Flat 9 - 3 West Gate | D79: 45981 | E79: 46010 | F79: 30 | G79: 45736 | I79: 700 | J79: 20 | K79: 30 | L79: =IF(F79 < 28, ROUND(F79 / DAY(EOMONTH(D79, 0)) * I79, 2), I79) -> 0 | M79: =L79 * 0.10 -> 0 | N79: =L79 * 0.05 -> 0 | O79: =M79 + N79 -> 0 | P79: =L79 - O79 -> 0
A80: 10 | B80: LEASE-BH-F10-2025 | C80: Flat 10 - 3 West Gate | D80: 45722 | E80: 45752 | F80: 31 | G80: 45722 | H80: 45894 | I80: 735 | J80: 6 | K80: 31 | L80: =IF(F80 < 28, ROUND(F80 / DAY(EOMONTH(D80, 0)) * I80, 2), I80) -> 0 | M80: =L80 * 0.10 -> 0 | N80: =L80 * 0.05 -> 0 | O80: =M80 + N80 -> 0 | P80: =L80 - O80 -> 0
A81: 10 | B81: LEASE-BH-F10-2025 | C81: Flat 10 - 3 West Gate | D81: 45753 | E81: 45782 | F81: 30 | G81: 45722 | H81: 45894 | I81: 735 | J81: 6 | K81: 30 | L81: =IF(F81 < 28, ROUND(F81 / DAY(EOMONTH(D81, 0)) * I81, 2), I81) -> 0 | M81: =L81 * 0.10 -> 0 | N81: =L81 * 0.05 -> 0 | O81: =M81 + N81 -> 0 | P81: =L81 - O81 -> 0
A82: 10 | B82: LEASE-BH-F10-2025 | C82: Flat 10 - 3 West Gate | D82: 45783 | E82: 45813 | F82: 31 | G82: 45722 | H82: 45894 | I82: 735 | J82: 6 | K82: 31 | L82: =IF(F82 < 28, ROUND(F82 / DAY(EOMONTH(D82, 0)) * I82, 2), I82) -> 0 | M82: =L82 * 0.10 -> 0 | N82: =L82 * 0.05 -> 0 | O82: =M82 + N82 -> 0 | P82: =L82 - O82 -> 0
A83: 10 | B83: LEASE-BH-F10-2025 | C83: Flat 10 - 3 West Gate | D83: 45814 | E83: 45843 | F83: 30 | G83: 45722 | H83: 45894 | I83: 735 | J83: 6 | K83: 30 | L83: =IF(F83 < 28, ROUND(F83 / DAY(EOMONTH(D83, 0)) * I83, 2), I83) -> 0 | M83: =L83 * 0.10 -> 0 | N83: =L83 * 0.05 -> 0 | O83: =M83 + N83 -> 0 | P83: =L83 - O83 -> 0
A84: 10 | B84: LEASE-BH-F10-2025 | C84: Flat 10 - 3 West Gate | D84: 45844 | E84: 45874 | F84: 31 | G84: 45722 | H84: 45894 | I84: 735 | J84: 6 | K84: 31 | L84: =IF(F84 < 28, ROUND(F84 / DAY(EOMONTH(D84, 0)) * I84, 2), I84) -> 0 | M84: =L84 * 0.10 -> 0 | N84: =L84 * 0.05 -> 0 | O84: =M84 + N84 -> 0 | P84: =L84 - O84 -> 0
A85: 10 | B85: LEASE-BH-F10-2025 | C85: Flat 10 - 3 West Gate | D85: 45875 | E85: 45894 | F85: 20 | G85: 45722 | H85: 45894 | I85: 735 | J85: 6 | K85: 20 | L85: =IF(F85 < 28, ROUND(F85 / DAY(EOMONTH(D85, 0)) * I85, 2), I85) -> 0 | M85: =L85 * 0.10 -> 0 | N85: =L85 * 0.05 -> 0 | O85: =M85 + N85 -> 0 | P85: =L85 - O85 -> 0
A86: 11 | B86: LEASE-BH-F10-2025B | C86: Flat 10 - 3 West Gate | D86: 45903 | E86: 45932 | F86: 30 | G86: 45903 | I86: 795 | J86: 3 | K86: 30 | L86: =IF(F86 < 28, ROUND(F86 / DAY(EOMONTH(D86, 0)) * I86, 2), I86) -> 0 | M86: =L86 * 0.10 -> 0 | N86: =L86 * 0.05 -> 0 | O86: =M86 + N86 -> 0 | P86: =L86 - O86 -> 0
A87: 11 | B87: LEASE-BH-F10-2025B | C87: Flat 10 - 3 West Gate | D87: 45933 | E87: 45963 | F87: 31 | G87: 45903 | I87: 795 | J87: 3 | K87: 31 | L87: =IF(F87 < 28, ROUND(F87 / DAY(EOMONTH(D87, 0)) * I87, 2), I87) -> 0 | M87: =L87 * 0.10 -> 0 | N87: =L87 * 0.05 -> 0 | O87: =M87 + N87 -> 0 | P87: =L87 - O87 -> 0
A88: 11 | B88: LEASE-BH-F10-2025B | C88: Flat 10 - 3 West Gate | D88: 45964 | E88: 45993 | F88: 30 | G88: 45903 | I88: 795 | J88: 3 | K88: 30 | L88: =IF(F88 < 28, ROUND(F88 / DAY(EOMONTH(D88, 0)) * I88, 2), I88) -> 0 | M88: =L88 * 0.10 -> 0 | N88: =L88 * 0.05 -> 0 | O88: =M88 + N88 -> 0 | P88: =L88 - O88 -> 0
A89: 12 | B89: LEASE-BH-F11-2025 | C89: Flat 11 - 3 West Gate | D89: 45722 | E89: 45752 | F89: 31 | G89: 45722 | I89: 795 | J89: 6 | K89: 31 | L89: =IF(F89 < 28, ROUND(F89 / DAY(EOMONTH(D89, 0)) * I89, 2), I89) -> 0 | M89: =L89 * 0.10 -> 0 | N89: =L89 * 0.05 -> 0 | O89: =M89 + N89 -> 0 | P89: =L89 - O89 -> 0
A90: 12 | B90: LEASE-BH-F11-2025 | C90: Flat 11 - 3 West Gate | D90: 45753 | E90: 45782 | F90: 30 | G90: 45722 | I90: 795 | J90: 6 | K90: 30 | L90: =IF(F90 < 28, ROUND(F90 / DAY(EOMONTH(D90, 0)) * I90, 2), I90) -> 0 | M90: =L90 * 0.10 -> 0 | N90: =L90 * 0.05 -> 0 | O90: =M90 + N90 -> 0 | P90: =L90 - O90 -> 0
A91: 12 | B91: LEASE-BH-F11-2025 | C91: Flat 11 - 3 West Gate | D91: 45783 | E91: 45813 | F91: 31 | G91: 45722 | I91: 795 | J91: 6 | K91: 31 | L91: =IF(F91 < 28, ROUND(F91 / DAY(EOMONTH(D91, 0)) * I91, 2), I91) -> 0 | M91: =L91 * 0.10 -> 0 | N91: =L91 * 0.05 -> 0 | O91: =M91 + N91 -> 0 | P91: =L91 - O91 -> 0
A92: 12 | B92: LEASE-BH-F11-2025 | C92: Flat 11 - 3 West Gate | D92: 45814 | E92: 45843 | F92: 30 | G92: 45722 | I92: 795 | J92: 6 | K92: 30 | L92: =IF(F92 < 28, ROUND(F92 / DAY(EOMONTH(D92, 0)) * I92, 2), I92) -> 0 | M92: =L92 * 0.10 -> 0 | N92: =L92 * 0.05 -> 0 | O92: =M92 + N92 -> 0 | P92: =L92 - O92 -> 0
A93: 12 | B93: LEASE-BH-F11-2025 | C93: Flat 11 - 3 West Gate | D93: 45844 | E93: 45874 | F93: 31 | G93: 45722 | I93: 795 | J93: 6 | K93: 31 | L93: =IF(F93 < 28, ROUND(F93 / DAY(EOMONTH(D93, 0)) * I93, 2), I93) -> 0 | M93: =L93 * 0.10 -> 0 | N93: =L93 * 0.05 -> 0 | O93: =M93 + N93 -> 0 | P93: =L93 - O93 -> 0
A94: 12 | B94: LEASE-BH-F11-2025 | C94: Flat 11 - 3 West Gate | D94: 45875 | E94: 45905 | F94: 31 | G94: 45722 | I94: 795 | J94: 6 | K94: 31 | L94: =IF(F94 < 28, ROUND(F94 / DAY(EOMONTH(D94, 0)) * I94, 2), I94) -> 0 | M94: =L94 * 0.10 -> 0 | N94: =L94 * 0.05 -> 0 | O94: =M94 + N94 -> 0 | P94: =L94 - O94 -> 0
A95: 12 | B95: LEASE-BH-F11-2025 | C95: Flat 11 - 3 West Gate | D95: 45906 | E95: 45935 | F95: 30 | G95: 45722 | I95: 795 | J95: 6 | K95: 30 | L95: =IF(F95 < 28, ROUND(F95 / DAY(EOMONTH(D95, 0)) * I95, 2), I95) -> 0 | M95: =L95 * 0.10 -> 0 | N95: =L95 * 0.05 -> 0 | O95: =M95 + N95 -> 0 | P95: =L95 - O95 -> 0
A96: 12 | B96: LEASE-BH-F11-2025 | C96: Flat 11 - 3 West Gate | D96: 45936 | E96: 45966 | F96: 31 | G96: 45722 | I96: 795 | J96: 6 | K96: 31 | L96: =IF(F96 < 28, ROUND(F96 / DAY(EOMONTH(D96, 0)) * I96, 2), I96) -> 0 | M96: =L96 * 0.10 -> 0 | N96: =L96 * 0.05 -> 0 | O96: =M96 + N96 -> 0 | P96: =L96 - O96 -> 0
A97: 12 | B97: LEASE-BH-F11-2025 | C97: Flat 11 - 3 West Gate | D97: 45967 | E97: 45996 | F97: 30 | G97: 45722 | I97: 795 | J97: 6 | K97: 30 | L97: =IF(F97 < 28, ROUND(F97 / DAY(EOMONTH(D97, 0)) * I97, 2), I97) -> 0 | M97: =L97 * 0.10 -> 0 | N97: =L97 * 0.05 -> 0 | O97: =M97 + N97 -> 0 | P97: =L97 - O97 -> 0
A98: 13 | B98: LEASE-BH-F12-2025 | C98: Flat 12 - 3 West Gate | D98: 45754 | E98: 45783 | F98: 30 | G98: 45754 | H98: 45814 | I98: 675 | J98: 7 | K98: 30 | L98: =IF(F98 < 28, ROUND(F98 / DAY(EOMONTH(D98, 0)) * I98, 2), I98) -> 0 | M98: =L98 * 0.10 -> 0 | N98: =L98 * 0.05 -> 0 | O98: =M98 + N98 -> 0 | P98: =L98 - O98 -> 0
A99: 13 | B99: LEASE-BH-F12-2025 | C99: Flat 12 - 3 West Gate | D99: 45784 | E99: 45814 | F99: 31 | G99: 45754 | H99: 45814 | I99: 675 | J99: 7 | K99: 31 | L99: =IF(F99 < 28, ROUND(F99 / DAY(EOMONTH(D99, 0)) * I99, 2), I99) -> 0 | M99: =L99 * 0.10 -> 0 | N99: =L99 * 0.05 -> 0 | O99: =M99 + N99 -> 0 | P99: =L99 - O99 -> 0
A100: 14 | B100: LEASE-BH-F12-2025B | C100: Flat 12 - 3 West Gate | D100: 45860 | E100: 45890 | F100: 31 | G100: 45860 | H100: 45951 | I100: 5687 | J100: 22 | K100: 31 | L100: =IF(F100 < 28, ROUND(F100 / DAY(EOMONTH(D100, 0)) * I100, 2), I100) -> 0 | M100: =L100 * 0.10 -> 0 | N100: =L100 * 0.05 -> 0 | O100: =M100 + N100 -> 0 | P100: =L100 - O100 -> 0
A101: 14 | B101: LEASE-BH-F12-2025B | C101: Flat 12 - 3 West Gate | D101: 45891 | E101: 45921 | F101: 31 | G101: 45860 | H101: 45951 | I101: 5687 | J101: 22 | K101: 31 | L101: 0 | M101: =L101 * 0.10 -> 0 | N101: =L101 * 0.05 -> 0 | O101: =M101 + N101 -> 0 | P101: =L101 - O101 -> 0
A102: 14 | B102: LEASE-BH-F12-2025B | C102: Flat 12 - 3 West Gate | D102: 45922 | E102: 45951 | F102: 30 | G102: 45860 | H102: 45951 | I102: 5687 | J102: 22 | K102: 30 | L102: 0 | M102: =L102 * 0.10 -> 0 | N102: =L102 * 0.05 -> 0 | O102: =M102 + N102 -> 0 | P102: =L102 - O102 -> 0
A103: 15 | B103: LEASE-BH-F13-2025 | C103: Flat 13 - 3 West Gate | D103: 45719 | E103: 45749 | F103: 31 | G103: 45719 | H103: 45963 | I103: 800 | J103: 3 | K103: 31 | L103: =IF(F103 < 28, ROUND(F103 / DAY(EOMONTH(D103, 0)) * I103, 2), I103) -> 0 | M103: =L103 * 0.10 -> 0 | N103: =L103 * 0.05 -> 0 | O103: =M103 + N103 -> 0 | P103: =L103 - O103 -> 0
A104: 15 | B104: LEASE-BH-F13-2025 | C104: Flat 13 - 3 West Gate | D104: 45750 | E104: 45779 | F104: 30 | G104: 45719 | H104: 45963 | I104: 800 | J104: 3 | K104: 30 | L104: =IF(F104 < 28, ROUND(F104 / DAY(EOMONTH(D104, 0)) * I104, 2), I104) -> 0 | M104: =L104 * 0.10 -> 0 | N104: =L104 * 0.05 -> 0 | O104: =M104 + N104 -> 0 | P104: =L104 - O104 -> 0
A105: 15 | B105: LEASE-BH-F13-2025 | C105: Flat 13 - 3 West Gate | D105: 45780 | E105: 45810 | F105: 31 | G105: 45719 | H105: 45963 | I105: 800 | J105: 3 | K105: 31 | L105: =IF(F105 < 28, ROUND(F105 / DAY(EOMONTH(D105, 0)) * I105, 2), I105) -> 0 | M105: =L105 * 0.10 -> 0 | N105: =L105 * 0.05 -> 0 | O105: =M105 + N105 -> 0 | P105: =L105 - O105 -> 0
A106: 15 | B106: LEASE-BH-F13-2025 | C106: Flat 13 - 3 West Gate | D106: 45811 | E106: 45840 | F106: 30 | G106: 45719 | H106: 45963 | I106: 800 | J106: 3 | K106: 30 | L106: =IF(F106 < 28, ROUND(F106 / DAY(EOMONTH(D106, 0)) * I106, 2), I106) -> 0 | M106: =L106 * 0.10 -> 0 | N106: =L106 * 0.05 -> 0 | O106: =M106 + N106 -> 0 | P106: =L106 - O106 -> 0
A107: 15 | B107: LEASE-BH-F13-2025 | C107: Flat 13 - 3 West Gate | D107: 45841 | E107: 45871 | F107: 31 | G107: 45719 | H107: 45963 | I107: 800 | J107: 3 | K107: 31 | L107: =IF(F107 < 28, ROUND(F107 / DAY(EOMONTH(D107, 0)) * I107, 2), I107) -> 0 | M107: =L107 * 0.10 -> 0 | N107: =L107 * 0.05 -> 0 | O107: =M107 + N107 -> 0 | P107: =L107 - O107 -> 0
A108: 15 | B108: LEASE-BH-F13-2025 | C108: Flat 13 - 3 West Gate | D108: 45872 | E108: 45902 | F108: 31 | G108: 45719 | H108: 45963 | I108: 800 | J108: 3 | K108: 31 | L108: =IF(F108 < 28, ROUND(F108 / DAY(EOMONTH(D108, 0)) * I108, 2), I108) -> 0 | M108: =L108 * 0.10 -> 0 | N108: =L108 * 0.05 -> 0 | O108: =M108 + N108 -> 0 | P108: =L108 - O108 -> 0
A109: 15 | B109: LEASE-BH-F13-2025 | C109: Flat 13 - 3 West Gate | D109: 45903 | E109: 45932 | F109: 30 | G109: 45719 | H109: 45963 | I109: 800 | J109: 3 | K109: 30 | L109: =IF(F109 < 28, ROUND(F109 / DAY(EOMONTH(D109, 0)) * I109, 2), I109) -> 0 | M109: =L109 * 0.10 -> 0 | N109: =L109 * 0.05 -> 0 | O109: =M109 + N109 -> 0 | P109: =L109 - O109 -> 0
A110: 15 | B110: LEASE-BH-F13-2025 | C110: Flat 13 - 3 West Gate | D110: 45933 | E110: 45963 | F110: 31 | G110: 45719 | H110: 45963 | I110: 800 | J110: 3 | K110: 31 | L110: =IF(F110 < 28, ROUND(F110 / DAY(EOMONTH(D110, 0)) * I110, 2), I110) -> 0 | M110: =L110 * 0.10 -> 0 | N110: =L110 * 0.05 -> 0 | O110: =M110 + N110 -> 0 | P110: =L110 - O110 -> 0
A111: 16 | B111: LEASE-BH-F14-2025 | C111: Flat 14 - 3 West Gate | D111: 45744 | E111: 45774 | F111: 31 | G111: 45744 | I111: 795 | J111: 28 | K111: 31 | L111: =IF(F111 < 28, ROUND(F111 / DAY(EOMONTH(D111, 0)) * I111, 2), I111) -> 0 | M111: =L111 * 0.10 -> 0 | N111: =L111 * 0.05 -> 0 | O111: =M111 + N111 -> 0 | P111: =L111 - O111 -> 0
A112: 16 | B112: LEASE-BH-F14-2025 | C112: Flat 14 - 3 West Gate | D112: 45775 | E112: 45804 | F112: 30 | G112: 45744 | I112: 795 | J112: 28 | K112: 30 | L112: =IF(F112 < 28, ROUND(F112 / DAY(EOMONTH(D112, 0)) * I112, 2), I112) -> 0 | M112: =L112 * 0.10 -> 0 | N112: =L112 * 0.05 -> 0 | O112: =M112 + N112 -> 0 | P112: =L112 - O112 -> 0
A113: 16 | B113: LEASE-BH-F14-2025 | C113: Flat 14 - 3 West Gate | D113: 45805 | E113: 45835 | F113: 31 | G113: 45744 | I113: 795 | J113: 28 | K113: 31 | L113: =IF(F113 < 28, ROUND(F113 / DAY(EOMONTH(D113, 0)) * I113, 2), I113) -> 0 | M113: =L113 * 0.10 -> 0 | N113: =L113 * 0.05 -> 0 | O113: =M113 + N113 -> 0 | P113: =L113 - O113 -> 0
A114: 16 | B114: LEASE-BH-F14-2025 | C114: Flat 14 - 3 West Gate | D114: 45836 | E114: 45865 | F114: 30 | G114: 45744 | I114: 795 | J114: 28 | K114: 30 | L114: =IF(F114 < 28, ROUND(F114 / DAY(EOMONTH(D114, 0)) * I114, 2), I114) -> 0 | M114: =L114 * 0.10 -> 0 | N114: =L114 * 0.05 -> 0 | O114: =M114 + N114 -> 0 | P114: =L114 - O114 -> 0
A115: 16 | B115: LEASE-BH-F14-2025 | C115: Flat 14 - 3 West Gate | D115: 45866 | E115: 45896 | F115: 31 | G115: 45744 | I115: 795 | J115: 28 | K115: 31 | L115: =IF(F115 < 28, ROUND(F115 / DAY(EOMONTH(D115, 0)) * I115, 2), I115) -> 0 | M115: =L115 * 0.10 -> 0 | N115: =L115 * 0.05 -> 0 | O115: =M115 + N115 -> 0 | P115: =L115 - O115 -> 0
A116: 16 | B116: LEASE-BH-F14-2025 | C116: Flat 14 - 3 West Gate | D116: 45897 | E116: 45927 | F116: 31 | G116: 45744 | I116: 795 | J116: 28 | K116: 31 | L116: =IF(F116 < 28, ROUND(F116 / DAY(EOMONTH(D116, 0)) * I116, 2), I116) -> 0 | M116: =L116 * 0.10 -> 0 | N116: =L116 * 0.05 -> 0 | O116: =M116 + N116 -> 0 | P116: =L116 - O116 -> 0
A117: 16 | B117: LEASE-BH-F14-2025 | C117: Flat 14 - 3 West Gate | D117: 45928 | E117: 45957 | F117: 30 | G117: 45744 | I117: 795 | J117: 28 | K117: 30 | L117: =IF(F117 < 28, ROUND(F117 / DAY(EOMONTH(D117, 0)) * I117, 2), I117) -> 0 | M117: =L117 * 0.10 -> 0 | N117: =L117 * 0.05 -> 0 | O117: =M117 + N117 -> 0 | P117: =L117 - O117 -> 0
A118: 16 | B118: LEASE-BH-F14-2025 | C118: Flat 14 - 3 West Gate | D118: 45958 | E118: 45988 | F118: 31 | G118: 45744 | I118: 795 | J118: 28 | K118: 31 | L118: =IF(F118 < 28, ROUND(F118 / DAY(EOMONTH(D118, 0)) * I118, 2), I118) -> 0 | M118: =L118 * 0.10 -> 0 | N118: =L118 * 0.05 -> 0 | O118: =M118 + N118 -> 0 | P118: =L118 - O118 -> 0
A119: 17 | B119: LEASE-BH-F15-2025 | C119: Flat 15 - 3 West Gate | D119: 45703 | E119: 45730 | F119: 28 | G119: 45703 | I119: 740 | J119: 15 | K119: 28 | L119: =IF(F119 < 28, ROUND(F119 / DAY(EOMONTH(D119, 0)) * I119, 2), I119) -> 0 | M119: =L119 * 0.10 -> 0 | N119: =L119 * 0.05 -> 0 | O119: =M119 + N119 -> 0 | P119: =L119 - O119 -> 0
A120: 17 | B120: LEASE-BH-F15-2025 | C120: Flat 15 - 3 West Gate | D120: 45731 | E120: 45761 | F120: 31 | G120: 45703 | I120: 740 | J120: 15 | K120: 31 | L120: =IF(F120 < 28, ROUND(F120 / DAY(EOMONTH(D120, 0)) * I120, 2), I120) -> 0 | M120: =L120 * 0.10 -> 0 | N120: =L120 * 0.05 -> 0 | O120: =M120 + N120 -> 0 | P120: =L120 - O120 -> 0
A121: 17 | B121: LEASE-BH-F15-2025 | C121: Flat 15 - 3 West Gate | D121: 45762 | E121: 45791 | F121: 30 | G121: 45703 | I121: 740 | J121: 15 | K121: 30 | L121: =IF(F121 < 28, ROUND(F121 / DAY(EOMONTH(D121, 0)) * I121, 2), I121) -> 0 | M121: =L121 * 0.10 -> 0 | N121: =L121 * 0.05 -> 0 | O121: =M121 + N121 -> 0 | P121: =L121 - O121 -> 0
A122: 17 | B122: LEASE-BH-F15-2025 | C122: Flat 15 - 3 West Gate | D122: 45792 | E122: 45822 | F122: 31 | G122: 45703 | I122: 740 | J122: 15 | K122: 31 | L122: =IF(F122 < 28, ROUND(F122 / DAY(EOMONTH(D122, 0)) * I122, 2), I122) -> 0 | M122: =L122 * 0.10 -> 0 | N122: =L122 * 0.05 -> 0 | O122: =M122 + N122 -> 0 | P122: =L122 - O122 -> 0
... A128: 17 | B128: LEASE-BH-F15-2025 | C128: Flat 15 - 3 West Gate | D128: 45976 | E128: 46005 | F128: 30 | G128: 45703 | I128: 740 | J128: 15 | K128: 30 | L128: =IF(F128 < 28, ROUND(F128 / DAY(EOMONTH(D128, 0)) * I128, 2), I128) -> 0 | M128: =L128 * 0.10 -> 0 | N128: =L128 * 0.05 -> 0 | O128: =M128 + N128 -> 0 | P128: =L128 - O128 -> 0
A129: 18 | B129: LEASE-BH-F16-2025 | C129: Flat 16 - 3 West Gate | D129: 45726 | E129: 45756 | F129: 31 | G129: 45726 | H129: 45902 | I129: 740 | J129: 10 | K129: 31 | L129: =IF(F129 < 28, ROUND(F129 / DAY(EOMONTH(D129, 0)) * I129, 2), I129) -> 0 | M129: =L129 * 0.10 -> 0 | N129: =L129 * 0.05 -> 0 | O129: =M129 + N129 -> 0 | P129: =L129 - O129 -> 0
A130: 18 | B130: LEASE-BH-F16-2025 | C130: Flat 16 - 3 West Gate | D130: 45757 | E130: 45786 | F130: 30 | G130: 45726 | H130: 45902 | I130: 740 | J130: 10 | K130: 30 | L130: =IF(F130 < 28, ROUND(F130 / DAY(EOMONTH(D130, 0)) * I130, 2), I130) -> 0 | M130: =L130 * 0.10 -> 0 | N130: =L130 * 0.05 -> 0 | O130: =M130 + N130 -> 0 | P130: =L130 - O130 -> 0
A131: 18 | B131: LEASE-BH-F16-2025 | C131: Flat 16 - 3 West Gate | D131: 45787 | E131: 45817 | F131: 31 | G131: 45726 | H131: 45902 | I131: 740 | J131: 10 | K131: 31 | L131: =IF(F131 < 28, ROUND(F131 / DAY(EOMONTH(D131, 0)) * I131, 2), I131) -> 0 | M131: =L131 * 0.10 -> 0 | N131: =L131 * 0.05 -> 0 | O131: =M131 + N131 -> 0 | P131: =L131 - O131 -> 0
A132: 18 | B132: LEASE-BH-F16-2025 | C132: Flat 16 - 3 West Gate | D132: 45818 | E132: 45847 | F132: 30 | G132: 45726 | H132: 45902 | I132: 740 | J132: 10 | K132: 30 | L132: =IF(F132 < 28, ROUND(F132 / DAY(EOMONTH(D132, 0)) * I132, 2), I132) -> 0 | M132: =L132 * 0.10 -> 0 | N132: =L132 * 0.05 -> 0 | O132: =M132 + N132 -> 0 | P132: =L132 - O132 -> 0
A133: 18 | B133: LEASE-BH-F16-2025 | C133: Flat 16 - 3 West Gate | D133: 45848 | E133: 45878 | F133: 31 | G133: 45726 | H133: 45902 | I133: 740 | J133: 10 | K133: 31 | L133: =IF(F133 < 28, ROUND(F133 / DAY(EOMONTH(D133, 0)) * I133, 2), I133) -> 0 | M133: =L133 * 0.10 -> 0 | N133: =L133 * 0.05 -> 0 | O133: =M133 + N133 -> 0 | P133: =L133 - O133 -> 0
A134: 18 | B134: LEASE-BH-F16-2025 | C134: Flat 16 - 3 West Gate | D134: 45879 | E134: 45902 | F134: 24 | G134: 45726 | H134: 45902 | I134: 740 | J134: 10 | K134: 24 | L134: =IF(F134 < 28, ROUND(F134 / DAY(EOMONTH(D134, 0)) * I134, 2), I134) -> 0 | M134: =L134 * 0.10 -> 0 | N134: =L134 * 0.05 -> 0 | O134: =M134 + N134 -> 0 | P134: =L134 - O134 -> 0
A135: 19 | B135: LEASE-BH-F17-2025 | C135: Flat 17 - 3 West Gate | D135: 45705 | E135: 45732 | F135: 28 | G135: 45705 | I135: 700 | J135: 17 | K135: 28 | L135: =IF(F135 < 28, ROUND(F135 / DAY(EOMONTH(D135, 0)) * I135, 2), I135) -> 0 | M135: =L135 * 0.10 -> 0 | N135: =L135 * 0.05 -> 0 | O135: =M135 + N135 -> 0 | P135: =L135 - O135 -> 0
A136: 19 | B136: LEASE-BH-F17-2025 | C136: Flat 17 - 3 West Gate | D136: 45733 | E136: 45763 | F136: 31 | G136: 45705 | I136: 700 | J136: 17 | K136: 31 | L136: =IF(F136 < 28, ROUND(F136 / DAY(EOMONTH(D136, 0)) * I136, 2), I136) -> 0 | M136: =L136 * 0.10 -> 0 | N136: =L136 * 0.05 -> 0 | O136: =M136 + N136 -> 0 | P136: =L136 - O136 -> 0
A137: 19 | B137: LEASE-BH-F17-2025 | C137: Flat 17 - 3 West Gate | D137: 45764 | E137: 45793 | F137: 30 | G137: 45705 | I137: 700 | J137: 17 | K137: 30 | L137: =IF(F137 < 28, ROUND(F137 / DAY(EOMONTH(D137, 0)) * I137, 2), I137) -> 0 | M137: =L137 * 0.10 -> 0 | N137: =L137 * 0.05 -> 0 | O137: =M137 + N137 -> 0 | P137: =L137 - O137 -> 0
A138: 19 | B138: LEASE-BH-F17-2025 | C138: Flat 17 - 3 West Gate | D138: 45794 | E138: 45824 | F138: 31 | G138: 45705 | I138: 700 | J138: 17 | K138: 31 | L138: =IF(F138 < 28, ROUND(F138 / DAY(EOMONTH(D138, 0)) * I138, 2), I138) -> 0 | M138: =L138 * 0.10 -> 0 | N138: =L138 * 0.05 -> 0 | O138: =M138 + N138 -> 0 | P138: =L138 - O138 -> 0
A139: 19 | B139: LEASE-BH-F17-2025 | C139: Flat 17 - 3 West Gate | D139: 45825 | E139: 45854 | F139: 30 | G139: 45705 | I139: 700 | J139: 17 | K139: 30 | L139: =IF(F139 < 28, ROUND(F139 / DAY(EOMONTH(D139, 0)) * I139, 2), I139) -> 0 | M139: =L139 * 0.10 -> 0 | N139: =L139 * 0.05 -> 0 | O139: =M139 + N139 -> 0 | P139: =L139 - O139 -> 0
A140: 19 | B140: LEASE-BH-F17-2025 | C140: Flat 17 - 3 West Gate | D140: 45855 | E140: 45885 | F140: 31 | G140: 45705 | I140: 700 | J140: 17 | K140: 31 | L140: =IF(F140 < 28, ROUND(F140 / DAY(EOMONTH(D140, 0)) * I140, 2), I140) -> 0 | M140: =L140 * 0.10 -> 0 | N140: =L140 * 0.05 -> 0 | O140: =M140 + N140 -> 0 | P140: =L140 - O140 -> 0
A141: 19 | B141: LEASE-BH-F17-2025 | C141: Flat 17 - 3 West Gate | D141: 45886 | E141: 45916 | F141: 31 | G141: 45705 | I141: 700 | J141: 17 | K141: 31 | L141: =IF(F141 < 28, ROUND(F141 / DAY(EOMONTH(D141, 0)) * I141, 2), I141) -> 0 | M141: =L141 * 0.10 -> 0 | N141: =L141 * 0.05 -> 0 | O141: =M141 + N141 -> 0 | P141: =L141 - O141 -> 0
A142: 19 | B142: LEASE-BH-F17-2025 | C142: Flat 17 - 3 West Gate | D142: 45917 | E142: 45946 | F142: 30 | G142: 45705 | I142: 700 | J142: 17 | K142: 30 | L142: =IF(F142 < 28, ROUND(F142 / DAY(EOMONTH(D142, 0)) * I142, 2), I142) -> 0 | M142: =L142 * 0.10 -> 0 | N142: =L142 * 0.05 -> 0 | O142: =M142 + N142 -> 0 | P142: =L142 - O142 -> 0
A143: 19 | B143: LEASE-BH-F17-2025 | C143: Flat 17 - 3 West Gate | D143: 45947 | E143: 45977 | F143: 31 | G143: 45705 | I143: 700 | J143: 17 | K143: 31 | L143: =IF(F143 < 28, ROUND(F143 / DAY(EOMONTH(D143, 0)) * I143, 2), I143) -> 0 | M143: =L143 * 0.10 -> 0 | N143: =L143 * 0.05 -> 0 | O143: =M143 + N143 -> 0 | P143: =L143 - O143 -> 0
A144: 19 | B144: LEASE-BH-F17-2025 | C144: Flat 17 - 3 West Gate | D144: 45978 | E144: 46007 | F144: 30 | G144: 45705 | I144: 700 | J144: 17 | K144: 30 | L144: =IF(F144 < 28, ROUND(F144 / DAY(EOMONTH(D144, 0)) * I144, 2), I144) -> 0 | M144: =L144 * 0.10 -> 0 | N144: =L144 * 0.05 -> 0 | O144: =M144 + N144 -> 0 | P144: =L144 - O144 -> 0
A145: 20 | B145: LEASE-BH-F18-2025 | C145: Flat 18 - 3 West Gate | D145: 45687 | E145: 45715 | F145: 29 | G145: 45687 | H145: 45783 | I145: 740 | J145: 30 | K145: 29 | L145: =IF(F145 < 28, ROUND(F145 / DAY(EOMONTH(D145, 0)) * I145, 2), I145) -> 0 | M145: =L145 * 0.10 -> 0 | N145: =L145 * 0.05 -> 0 | O145: =M145 + N145 -> 0 | P145: =L145 - O145 -> 0
A146: 20 | B146: LEASE-BH-F18-2025 | C146: Flat 18 - 3 West Gate | D146: 45716 | E146: 45745 | F146: 30 | G146: 45687 | H146: 45783 | I146: 740 | J146: 30 | K146: 30 | L146: =IF(F146 < 28, ROUND(F146 / DAY(EOMONTH(D146, 0)) * I146, 2), I146) -> 0 | M146: =L146 * 0.10 -> 0 | N146: =L146 * 0.05 -> 0 | O146: =M146 + N146 -> 0 | P146: =L146 - O146 -> 0
A147: 20 | B147: LEASE-BH-F18-2025 | C147: Flat 18 - 3 West Gate | D147: 45746 | E147: 45776 | F147: 31 | G147: 45687 | H147: 45783 | I147: 740 | J147: 30 | K147: 31 | L147: =IF(F147 < 28, ROUND(F147 / DAY(EOMONTH(D147, 0)) * I147, 2), I147) -> 0 | M147: =L147 * 0.10 -> 0 | N147: =L147 * 0.05 -> 0 | O147: =M147 + N147 -> 0 | P147: =L147 - O147 -> 0
A148: 20 | B148: LEASE-BH-F18-2025 | C148: Flat 18 - 3 West Gate | D148: 45777 | E148: 45783 | F148: 7 | G148: 45687 | H148: 45783 | I148: 740 | J148: 30 | K148: 7 | L148: =IF(F148 < 28, ROUND(F148 / DAY(EOMONTH(D148, 0)) * I148, 2), I148) -> 0 | M148: =L148 * 0.10 -> 0 | N148: =L148 * 0.05 -> 0 | O148: =M148 + N148 -> 0 | P148: =L148 - O148 -> 0
A149: 21 | B149: LEASE-BH-F18-2025B | C149: Flat 18 - 3 West Gate | D149: 45818 | E149: 45847 | F149: 30 | G149: 45818 | I149: 795 | J149: 10 | K149: 30 | L149: =IF(F149 < 28, ROUND(F149 / DAY(EOMONTH(D149, 0)) * I149, 2), I149) -> 0 | M149: =L149 * 0.10 -> 0 | N149: =L149 * 0.05 -> 0 | O149: =M149 + N149 -> 0 | P149: =L149 - O149 -> 0
A150: 21 | B150: LEASE-BH-F18-2025B | C150: Flat 18 - 3 West Gate | D150: 45848 | E150: 45878 | F150: 31 | G150: 45818 | I150: 795 | J150: 10 | K150: 31 | L150: =IF(F150 < 28, ROUND(F150 / DAY(EOMONTH(D150, 0)) * I150, 2), I150) -> 0 | M150: =L150 * 0.10 -> 0 | N150: =L150 * 0.05 -> 0 | O150: =M150 + N150 -> 0 | P150: =L150 - O150 -> 0
A151: 21 | B151: LEASE-BH-F18-2025B | C151: Flat 18 - 3 West Gate | D151: 45879 | E151: 45909 | F151: 31 | G151: 45818 | I151: 795 | J151: 10 | K151: 31 | L151: =IF(F151 < 28, ROUND(F151 / DAY(EOMONTH(D151, 0)) * I151, 2), I151) -> 0 | M151: =L151 * 0.10 -> 0 | N151: =L151 * 0.05 -> 0 | O151: =M151 + N151 -> 0 | P151: =L151 - O151 -> 0
...

Sheet RENT_RECEIVED
A1: lease_id | B1: lease_reference | C1: property_name | D1: rent_due_date | E1: period_start | F1: period_end | G1: payment_1_date | H1: payment_1_amount | I1: payment_2_date | J1: payment_2_amount | K1: payment_3_date | L1: payment_3_amount | M1: payment_4_date | N1: payment_4_amount | O1: total_received
A2: 1 | B2: LEASE-BH-F1-2025 | C2: Flat 1 - 3 West Gate | D2: 45715 | E2: 45715 | F2: 45742 | G2: 45720 | H2: 795 | O2: 795
A3: 1 | B3: LEASE-BH-F1-2025 | C3: Flat 1 - 3 West Gate | D3: 45743 | E3: 45743 | F3: 45773 | G3: 45751 | H3: 795 | O3: 795
A4: 1 | B4: LEASE-BH-F1-2025 | C4: Flat 1 - 3 West Gate | D4: 45774 | E4: 45774 | F4: 45803 | G4: 45783 | H4: 795 | O4: 795
A5: 1 | B5: LEASE-BH-F1-2025 | C5: Flat 1 - 3 West Gate | D5: 45804 | E5: 45804 | F5: 45834 | G5: 45812 | H5: 795 | O5: 795
A6: 1 | B6: LEASE-BH-F1-2025 | C6: Flat 1 - 3 West Gate | D6: 45835 | E6: 45835 | F6: 45864 | G6: 45842 | H6: 795 | O6: 795
A7: 1 | B7: LEASE-BH-F1-2025 | C7: Flat 1 - 3 West Gate | D7: 45865 | E7: 45865 | F7: 45895 | G7: 45873 | H7: 795 | O7: 795
A8: 1 | B8: LEASE-BH-F1-2025 | C8: Flat 1 - 3 West Gate | D8: 45896 | E8: 45896 | F8: 45926 | G8: 45904 | H8: 795 | O8: 795
A9: 1 | B9: LEASE-BH-F1-2025 | C9: Flat 1 - 3 West Gate | D9: 45927 | E9: 45927 | F9: 45956 | G9: 45936 | H9: 795 | O9: 795
A10: 1 | B10: LEASE-BH-F1-2025 | C10: Flat 1 - 3 West Gate | D10: 45957 | E10: 45957 | F10: 45987 | G10: 45965 | H10: 795 | O10: 795
A11: 2 | B11: LEASE-BH-F2-2025 | C11: Flat 2 - 3 West Gate | D11: 45715 | E11: 45715 | F11: 45742 | G11: 45719 | H11: 740 | O11: 740
A12: 2 | B12: LEASE-BH-F2-2025 | C12: Flat 2 - 3 West Gate | D12: 45743 | E12: 45743 | F12: 45773 | G12: 45749 | H12: 740 | O12: 740
A13: 2 | B13: LEASE-BH-F2-2025 | C13: Flat 2 - 3 West Gate | D13: 45774 | E13: 45774 | F13: 45803 | G13: 45779 | H13: 740 | O13: 740
... A57: 7 | B57: LEASE-BH-F7-2025 | C57: Flat 7 - 3 West Gate | D57: 45735 | E57: 45735 | F57: 45765 | G57: 45735 | H57: 700 | O57: 700
A58: 7 | B58: LEASE-BH-F7-2025 | C58: Flat 7 - 3 West Gate | D58: 45766 | E58: 45766 | F58: 45795 | O58: 0
A59: 7 | B59: LEASE-BH-F7-2025 | C59: Flat 7 - 3 West Gate | D59: 45796 | E59: 45796 | F59: 45826 | G59: 45796 | H59: 1400 | O59: 1400
A60: 7 | B60: LEASE-BH-F7-2025 | C60: Flat 7 - 3 West Gate | D60: 45827 | E60: 45827 | F60: 45856 | G60: 45831 | H60: 700 | O60: 700
A61: 7 | B61: LEASE-BH-F7-2025 | C61: Flat 7 - 3 West Gate | D61: 45857 | E61: 45857 | F61: 45887 | G61: 45860 | H61: 700 | O61: 700
A62: 8 | B62: LEASE-BH-F8-2025 | C62: Flat 8 - 3 West Gate | D62: 45712 | E62: 45712 | F62: 45739 | G62: 45720 | H62: 675 | O62: 675
A63: 8 | B63: LEASE-BH-F8-2025 | C63: Flat 8 - 3 West Gate | D63: 45740 | E63: 45740 | F63: 45770 | G63: 45751 | H63: 675 | O63: 675
A64: 8 | B64: LEASE-BH-F8-2025 | C64: Flat 8 - 3 West Gate | D64: 45771 | E64: 45771 | F64: 45800 | G64: 45783 | H64: 675 | O64: 675
A65: 8 | B65: LEASE-BH-F8-2025 | C65: Flat 8 - 3 West Gate | D65: 45801 | E65: 45801 | F65: 45831 | G65: 45812 | H65: 675 | O65: 675
A66: 8 | B66: LEASE-BH-F8-2025 | C66: Flat 8 - 3 West Gate | D66: 45832 | E66: 45832 | F66: 45861 | G66: 45861 | H66: 735 | O66: 735
A67: 8 | B67: LEASE-BH-F8-2025 | C67: Flat 8 - 3 West Gate | D67: 45862 | E67: 45862 | F67: 45892 | G67: 45877 | H67: 735 | O67: 735
A68: 8 | B68: LEASE-BH-F8-2025 | C68: Flat 8 - 3 West Gate | D68: 45893 | E68: 45893 | F68: 45923 | G68: 45909 | H68: 735 | O68: 735
A69: 8 | B69: LEASE-BH-F8-2025 | C69: Flat 8 - 3 West Gate | D69: 45924 | E69: 45924 | F69: 45953 | G69: 45936 | H69: 735 | O69: 735
A70: 8 | B70: LEASE-BH-F8-2025 | C70: Flat 8 - 3 West Gate | D70: 45954 | E70: 45954 | F70: 45984 | G70: 45982 | H70: 735 | O70: 735
... A74: 9 | B74: LEASE-BH-F9-2025 | C74: Flat 9 - 3 West Gate | D74: 45797 | E74: 45797 | F74: 45827 | G74: 45810 | H74: 700 | O74: 700
A75: 9 | B75: LEASE-BH-F9-2025 | C75: Flat 9 - 3 West Gate | D75: 45828 | E75: 45828 | F75: 45857 | O75: 0
A76: 9 | B76: LEASE-BH-F9-2025 | C76: Flat 9 - 3 West Gate | D76: 45858 | E76: 45858 | F76: 45888 | G76: 45860 | H76: 700 | I76: 45877 | J76: 700 | O76: 1400
A77: 9 | B77: LEASE-BH-F9-2025 | C77: Flat 9 - 3 West Gate | D77: 45889 | E77: 45889 | F77: 45919 | G77: 45902 | H77: 700 | O77: 700
A78: 9 | B78: LEASE-BH-F9-2025 | C78: Flat 9 - 3 West Gate | D78: 45920 | E78: 45920 | F78: 45949 | G78: 45936 | H78: 700 | O78: 700
A79: 9 | B79: LEASE-BH-F9-2025 | C79: Flat 9 - 3 West Gate | D79: 45950 | E79: 45950 | F79: 45980 | O79: 0
A80: 9 | B80: LEASE-BH-F9-2025 | C80: Flat 9 - 3 West Gate | D80: 45981 | E80: 45981 | F80: 46010 | G80: 45982 | H80: 700 | O80: 700
A81: 10 | B81: LEASE-BH-F10-2025 | C81: Flat 10 - 3 West Gate | D81: 45357 | E81: 45357 | F81: 45721 | G81: 45721 | H81: 735 | O81: 735
A82: 10 | B82: LEASE-BH-F10-2025 | C82: Flat 10 - 3 West Gate | D82: 45722 | E82: 45722 | F82: 45752 | O82: 0
A83: 10 | B83: LEASE-BH-F10-2025 | C83: Flat 10 - 3 West Gate | D83: 45753 | E83: 45753 | F83: 45782 | G83: 45754 | H83: 735 | O83: 735
A84: 10 | B84: LEASE-BH-F10-2025 | C84: Flat 10 - 3 West Gate | D84: 45783 | E84: 45783 | F84: 45813 | G84: 45783 | H84: 735 | I84: 45813 | J84: 735 | O84: 1470
A85: 10 | B85: LEASE-BH-F10-2025 | C85: Flat 10 - 3 West Gate | D85: 45814 | E85: 45814 | F85: 45843 | O85: 0
A86: 10 | B86: LEASE-BH-F10-2025 | C86: Flat 10 - 3 West Gate | D86: 45844 | E86: 45844 | F86: 45874 | G86: 45860 | H86: 735 | O86: 735
A87: 10 | B87: LEASE-BH-F10-2025 | C87: Flat 10 - 3 West Gate | D87: 45875 | E87: 45875 | F87: 45894 | O87: 0
A88: 10 | B88: LEASE-BH-F10-2025 | C88: Flat 10 - 3 West Gate | D88: 45895 | E88: 45895 | F88: 45982 | G88: 45911 | H88: 483.2 | O88: 483.2
A89: 11 | B89: LEASE-BH-F10-2025B | C89: Flat 10 - 3 West Gate | D89: 45903 | E89: 45903 | F89: 45932 | G89: 45911 | H89: 795 | O89: 795
A90: 11 | B90: LEASE-BH-F10-2025B | C90: Flat 10 - 3 West Gate | D90: 45933 | E90: 45933 | F90: 45963 | G90: 45953 | H90: 785 | O90: 785
A91: 11 | B91: LEASE-BH-F10-2025B | C91: Flat 10 - 3 West Gate | D91: 45964 | E91: 45964 | F91: 45993 | G91: 45982 | H91: 785 | O91: 785
A92: 12 | B92: LEASE-BH-F11-2025 | C92: Flat 11 - 3 West Gate | D92: 45357 | E92: 45357 | F92: 45721 | G92: 45718 | H92: 795 | O92: 795
A93: 12 | B93: LEASE-BH-F11-2025 | C93: Flat 11 - 3 West Gate | D93: 45722 | E93: 45722 | F93: 45752 | G93: 45748 | H93: 795 | O93: 795
A94: 12 | B94: LEASE-BH-F11-2025 | C94: Flat 11 - 3 West Gate | D94: 45753 | E94: 45753 | F94: 45782 | G94: 45779 | H94: 795 | O94: 795
A95: 12 | B95: LEASE-BH-F11-2025 | C95: Flat 11 - 3 West Gate | D95: 45783 | E95: 45783 | F95: 45813 | G95: 45809 | H95: 795 | O95: 795
A96: 12 | B96: LEASE-BH-F11-2025 | C96: Flat 11 - 3 West Gate | D96: 45814 | E96: 45814 | F96: 45843 | O96: 0
A97: 12 | B97: LEASE-BH-F11-2025 | C97: Flat 11 - 3 West Gate | D97: 45844 | E97: 45844 | F97: 45874 | G97: 45860 | H97: 795 | O97: 795
A98: 12 | B98: LEASE-BH-F11-2025 | C98: Flat 11 - 3 West Gate | D98: 45875 | E98: 45875 | F98: 45905 | G98: 45877 | H98: 795 | I98: 45902 | J98: 795 | O98: 1590
A99: 12 | B99: LEASE-BH-F11-2025 | C99: Flat 11 - 3 West Gate | D99: 45906 | E99: 45906 | F99: 45935 | O99: 0
A100: 12 | B100: LEASE-BH-F11-2025 | C100: Flat 11 - 3 West Gate | D100: 45936 | E100: 45936 | F100: 45966 | G100: 45936 | H100: 795 | O100: 795
A101: 12 | B101: LEASE-BH-F11-2025 | C101: Flat 11 - 3 West Gate | D101: 45967 | E101: 45967 | F101: 45996 | G101: 45981 | H101: 795 | O101: 795
A102: 13 | B102: LEASE-BH-F12-2025 | C102: Flat 12 - 3 West Gate | D102: 45754 | E102: 45754 | F102: 45783 | G102: 45761 | H102: 675 | O102: 675
A103: 13 | B103: LEASE-BH-F12-2025 | C103: Flat 12 - 3 West Gate | D103: 45784 | E103: 45784 | F103: 45814 | G103: 45786 | H103: 675 | O103: 675
A104: 14 | B104: LEASE-BH-F12-2025B | C104: Flat 12 - 3 West Gate | D104: 45860 | E104: 45860 | F104: 45890 | G104: 45877 | H104: 5687.3 | O104: 5687.3
A105: 14 | B105: LEASE-BH-F12-2025B | C105: Flat 12 - 3 West Gate | D105: 45891 | E105: 45891 | F105: 45921 | O105: 0
A106: 14 | B106: LEASE-BH-F12-2025B | C106: Flat 12 - 3 West Gate | D106: 45922 | E106: 45922 | F106: 45951 | O106: 0
A107: 15 | B107: LEASE-BH-F13-2025 | C107: Flat 13 - 3 West Gate | D107: 45719 | E107: 45719 | F107: 45749 | G107: 45722 | H107: 800 | O107: 800
A108: 15 | B108: LEASE-BH-F13-2025 | C108: Flat 13 - 3 West Gate | D108: 45750 | E108: 45750 | F108: 45779 | G108: 45754 | H108: 800 | O108: 800
A109: 15 | B109: LEASE-BH-F13-2025 | C109: Flat 13 - 3 West Gate | D109: 45780 | E109: 45780 | F109: 45810 | G109: 45783 | H109: 800 | O109: 800
A110: 15 | B110: LEASE-BH-F13-2025 | C110: Flat 13 - 3 West Gate | D110: 45811 | E110: 45811 | F110: 45840 | G110: 45814 | H110: 800 | O110: 800
A111: 15 | B111: LEASE-BH-F13-2025 | C111: Flat 13 - 3 West Gate | D111: 45841 | E111: 45841 | F111: 45871 | G111: 45860 | H111: 800 | O111: 800
A112: 15 | B112: LEASE-BH-F13-2025 | C112: Flat 13 - 3 West Gate | D112: 45872 | E112: 45872 | F112: 45902 | G112: 45877 | H112: 800 | O112: 800
A113: 15 | B113: LEASE-BH-F13-2025 | C113: Flat 13 - 3 West Gate | D113: 45903 | E113: 45903 | F113: 45932 | G113: 45909 | H113: 800 | O113: 800
A114: 15 | B114: LEASE-BH-F13-2025 | C114: Flat 13 - 3 West Gate | D114: 45933 | E114: 45933 | F114: 45963 | G114: 45936 | H114: 800 | O114: 800
A115: 16 | B115: LEASE-BH-F14-2025 | C115: Flat 14 - 3 West Gate | D115: 45379 | E115: 45379 | F115: 45743 | G115: 45742 | H115: 795 | O115: 795
A116: 16 | B116: LEASE-BH-F14-2025 | C116: Flat 14 - 3 West Gate | D116: 45744 | E116: 45744 | F116: 45774 | O116: 0
A117: 16 | B117: LEASE-BH-F14-2025 | C117: Flat 14 - 3 West Gate | D117: 45775 | E117: 45775 | F117: 45804 | G117: 45775 | H117: 800 | I117: 45804 | J117: 795 | O117: 1595
A118: 16 | B118: LEASE-BH-F14-2025 | C118: Flat 14 - 3 West Gate | D118: 45805 | E118: 45805 | F118: 45835 | G118: 45834 | H118: 795 | O118: 795
A119: 16 | B119: LEASE-BH-F14-2025 | C119: Flat 14 - 3 West Gate | D119: 45836 | E119: 45836 | F119: 45865 | O119: 0
A120: 16 | B120: LEASE-BH-F14-2025 | C120: Flat 14 - 3 West Gate | D120: 45866 | E120: 45866 | F120: 45896 | G120: 45866 | H120: 795 | I120: 45895 | J120: 795 | O120: 1590
A121: 16 | B121: LEASE-BH-F14-2025 | C121: Flat 14 - 3 West Gate | D121: 45897 | E121: 45897 | F121: 45927 | G121: 45926 | H121: 795 | O121: 795
A122: 16 | B122: LEASE-BH-F14-2025 | C122: Flat 14 - 3 West Gate | D122: 45928 | E122: 45928 | F122: 45957 | G122: 45957 | H122: 795 | O122: 795
A123: 16 | B123: LEASE-BH-F14-2025 | C123: Flat 14 - 3 West Gate | D123: 45958 | E123: 45958 | F123: 45988 | O123: 0
A124: 17 | B124: LEASE-BH-F15-2025 | C124: Flat 15 - 3 West Gate | D124: 45703 | E124: 45703 | F124: 45730 | G124: 45707 | H124: 740 | O124: 740
A125: 17 | B125: LEASE-BH-F15-2025 | C125: Flat 15 - 3 West Gate | D125: 45731 | E125: 45731 | F125: 45761 | G125: 45735 | H125: 740 | O125: 740
A126: 17 | B126: LEASE-BH-F15-2025 | C126: Flat 15 - 3 West Gate | D126: 45762 | E126: 45762 | F126: 45791 | O126: 0
A127: 17 | B127: LEASE-BH-F15-2025 | C127: Flat 15 - 3 West Gate | D127: 45792 | E127: 45792 | F127: 45822 | G127: 45796 | H127: 1480 | O127: 1480
A128: 17 | B128: LEASE-BH-F15-2025 | C128: Flat 15 - 3 West Gate | D128: 45823 | E128: 45823 | F128: 45852 | G128: 45825 | H128: 740 | O128: 740
A129: 17 | B129: LEASE-BH-F15-2025 | C129: Flat 15 - 3 West Gate | D129: 45853 | E129: 45853 | F129: 45883 | G129: 45860 | H129: 740 | O129: 740
A130: 17 | B130: LEASE-BH-F15-2025 | C130: Flat 15 - 3 West Gate | D130: 45884 | E130: 45884 | F130: 45914 | G130: 45891 | H130: 740 | O130: 740
A131: 17 | B131: LEASE-BH-F15-2025 | C131: Flat 15 - 3 West Gate | D131: 45915 | E131: 45915 | F131: 45944 | G131: 45919 | H131: 740 | O131: 740
A132: 17 | B132: LEASE-BH-F15-2025 | C132: Flat 15 - 3 West Gate | D132: 45945 | E132: 45945 | F132: 45975 | G132: 45953 | H132: 740 | O132: 740
A133: 17 | B133: LEASE-BH-F15-2025 | C133: Flat 15 - 3 West Gate | D133: 45976 | E133: 45976 | F133: 46005 | G133: 45982 | H133: 740 | O133: 740
A134: 18 | B134: LEASE-BH-F16-2025 | C134: Flat 16 - 3 West Gate | D134: 45726 | E134: 45726 | F134: 45756 | G134: 45728 | H134: 740 | O134: 740
A135: 18 | B135: LEASE-BH-F16-2025 | C135: Flat 16 - 3 West Gate | D135: 45757 | E135: 45757 | F135: 45786 | G135: 45759 | H135: 740 | O135: 740
A136: 18 | B136: LEASE-BH-F16-2025 | C136: Flat 16 - 3 West Gate | D136: 45787 | E136: 45787 | F136: 45817 | G136: 45789 | H136: 740 | O136: 740
A137: 18 | B137: LEASE-BH-F16-2025 | C137: Flat 16 - 3 West Gate | D137: 45818 | E137: 45818 | F137: 45847 | G137: 45820 | H137: 740 | O137: 740
A138: 18 | B138: LEASE-BH-F16-2025 | C138: Flat 16 - 3 West Gate | D138: 45848 | E138: 45848 | F138: 45878 | G138: 45860 | H138: 740 | O138: 740
... A152: 20 | B152: LEASE-BH-F18-2025 | C152: Flat 18 - 3 West Gate | D152: 45746 | E152: 45746 | F152: 45776 | G152: 45761 | H152: 740 | O152: 740
A153: 20 | B153: LEASE-BH-F18-2025 | C153: Flat 18 - 3 West Gate | D153: 45777 | E153: 45777 | F153: 45783 | O153: 0
A154: 20 | B154: LEASE-BH-F18-2025 | C154: Flat 18 - 3 West Gate | D154: 45784 | E154: 45784 | F154: 45982 | G154: 45792 | H154: 185 | O154: 185
A155: 21 | B155: LEASE-BH-F18-2025B | C155: Flat 18 - 3 West Gate | D155: 45818 | E155: 45818 | F155: 45847 | G155: 45821 | H155: 795 | O155: 795
A156: 21 | B156: LEASE-BH-F18-2025B | C156: Flat 18 - 3 West Gate | D156: 45848 | E156: 45848 | F156: 45878 | G156: 45860 | H156: 855 | O156: 855
A157: 21 | B157: LEASE-BH-F18-2025B | C157: Flat 18 - 3 West Gate | D157: 45879 | E157: 45879 | F157: 45909 | G157: 45891 | H157: 855 | O157: 855
A158: 21 | B158: LEASE-BH-F18-2025B | C158: Flat 18 - 3 West Gate | D158: 45910 | E158: 45910 | F158: 45939 | G158: 45911 | H158: 855 | O158: 855
A159: 21 | B159: LEASE-BH-F18-2025B | C159: Flat 18 - 3 West Gate | D159: 45940 | E159: 45940 | F159: 45970 | G159: 45953 | H159: 795 | I159: 45953 | J159: 60 | O159: 855
...

Sheet EXPENSES
A1: lease_id | B1: lease_reference | C1: property_name | D1: expense_date | E1: expense_amount | F1: expense_category | G1: expense_description
A2: 4 | B2: LEASE-BH-F4-2025 | C2: Flat 4 - 3 West Gate | D2: 45982 | E2: 150 | F2: Disbursement | G2: Beneficiary: BODEN HOUSE BLOCK PROPERTY (beneficiary)
A3: 5 | B3: LEASE-BH-F5-2025 | C3: Flat 5 - 3 West Gate | D3: 45981 | E3: 150 | F3: Disbursement | G3: Beneficiary: BODEN HOUSE BLOCK PROPERTY (beneficiary)
A4: 5 | B4: LEASE-BH-F5-2025 | C4: Flat 5 - 3 West Gate | D4: 45981 | E4: -150 | F4: Disbursement | G4: Beneficiary: BODEN HOUSE BLOCK PROPERTY (beneficiary)
A5: 5 | B5: LEASE-BH-F5-2025 | C5: Flat 5 - 3 West Gate | D5: 45981 | E5: 150 | F5: Disbursement | G5: Beneficiary: BODEN HOUSE BLOCK PROPERTY (beneficiary)
A6: 6 | B6: LEASE-BH-F6-2025 | C6: Flat 6 - 3 West Gate | D6: 45982 | E6: 150 | F6: Disbursement | G6: Beneficiary: BODEN HOUSE BLOCK PROPERTY (beneficiary)
A7: 8 | B7: LEASE-BH-F8-2025 | C7: Flat 8 - 3 West Gate | D7: 45982 | E7: 100 | F7: Disbursement | G7: Beneficiary: BODEN HOUSE BLOCK PROPERTY (beneficiary)
A8: 9 | B8: LEASE-BH-F9-2025 | C8: Flat 9 - 3 West Gate | D8: 45982 | E8: 100 | F8: Disbursement | G8: Beneficiary: BODEN HOUSE BLOCK PROPERTY (beneficiary)
A9: 11 | B9: LEASE-BH-F10-2025B | C9: Flat 10 - 3 West Gate | D9: 45982 | E9: 100 | F9: Disbursement | G9: Beneficiary: BODEN HOUSE BLOCK PROPERTY (beneficiary)
A10: 11 | B10: LEASE-BH-F10-2025B | C10: Flat 10 - 3 West Gate | D10: 45982 | E10: 20.42 | F10: Council | G10: Beneficiary: EREWASH COUNCIL (beneficiary)
A11: 12 | B11: LEASE-BH-F11-2025 | C11: Flat 11 - 3 West Gate | D11: 45981 | E11: 120 | F11: Disbursement | G11: Beneficiary: BODEN HOUSE BLOCK PROPERTY (beneficiary)
A12: 14 | B12: LEASE-BH-F12-2025B | C12: Flat 12 - 3 West Gate | D12: 45922 | E12: 3157.75 | F12: refund | G12: Refund of rent to Adam Kirby
A13: 17 | B13: LEASE-BH-F15-2025 | C13: Flat 15 - 3 West Gate | D13: 45982 | E13: 120 | F13: Disbursement | G13: Beneficiary: BODEN HOUSE BLOCK PROPERTY (beneficiary)
... A56: 86 | B56: BODEN-BLOCK-2025 | C56: Boden House Block - Block Property | D56: 45982 | E56: 120 | F56: PROPERTY_ACCOUNT_ALLOCATION | G56: Beneficiary: PayProp property account (global_beneficiary)
A57: 86 | B57: BODEN-BLOCK-2025 | C57: Boden House Block - Block Property | D57: 45982 | E57: 0 | G57: Beneficiary: Unknown (agency)
A58: 88 | B58: LEASE-88 | C58: Flat 28 - 3 West Gate | D58: 45982 | E58: 114.37 | F58: Council | G58: Council Tax
A59: 88 | B59: LEASE-88 | C59: Flat 28 - 3 West Gate | D59: 45982 | E59: 120 | F59: Disbursement | G59: Beneficiary: BODEN HOUSE BLOCK PROPERTY (beneficiary)

Sheet PROPERTY_ACCOUNT
A1: block_name | B1: movement_type | C1: description | D1: amount | E1: date | F1: source_property | G1: batch_reference
A2: Boden House NG10 | B2: opening | C2: Opening Balance (prior to 2024-12-22) | D2: 0 | E2: 45648
A3: Boden House NG10 | B3: closing | C3: Closing Balance | D3: 0 | E3: 45982

Sheet Dec 22 - Jan 21, 2025
A1: lease_reference | B1: property_name | C1: customer_name | D1: tenant_name | E1: lease_start_date | F1: rent_due_day | G1: rent_due | H1: rent_received | I1: rent_batch | J1: opening_balance | K1: period_arrears | L1: closing_balance | M1: management_fee | N1: service_fee | O1: total_commission | P1: commission_batch | Q1: total_expenses | R1: expenses_batch | S1: net_to_owner | T1: block_name | U1: property_account_opening | V1: property_account_in | W1: property_account_out | X1: property_account_closing | Y1: allocated_amount | Z1: variance | AA1: allocation_status | AB1: batch_id | AC1: paid_date
A2: LEASE-KH-F-2024 | B2: Apartment F - Knighton Hayes Manor | C2: Achal (Delegated for Udayan) | D2: Mr Riaz Hamid, Ismat Tarr-Hamid | E2: 45648 | F2: 22 | G2: =IFERROR(SUMPRODUCT((RENT_DUE!$B$2:$B$1000="LEASE-KH-F-2024")*(RENT_DUE!$D$2:$D$1000>=DATE(2024,12,22))*(RENT_DUE!$D$2:$D$1000<=DATE(2025,1,21))*RENT_DUE!$L$2:$L$1000), 0) -> 0 | H2: =IFERROR(SUMPRODUCT((RENT_RECEIVED!$B$2:$B$1000="LEASE-KH-F-2024")*(RENT_RECEIVED!$E$2:$E$1000>=DATE(2024,12,22))*(RENT_RECEIVED!$E$2:$E$1000<=DATE(2025,1,21))*RENT_RECEIVED!$O$2:$O$1000), 0) -> 0 | J2: =IFERROR(SUMIFS(RENT_DUE!$L$2:$L$10000, RENT_DUE!$B$2:$B$10000, "LEASE-KH-F-2024", RENT_DUE!$D$2:$D$10000, "<"&DATE(2024,12,22)), 0) - IFERROR(SUMIFS(RENT_RECEIVED!$O$2:$O$10000, RENT_RECEIVED!$B$2:$B$10000, "LEASE-KH-F-2024", RENT_RECEIVED!$E$2:$E$10000, "<"&DATE(2024,12,22)), 0) -> 0 | K2: =G2 - H2 -> 0 | L2: =J2 + K2 -> 0 | M2: =H2 * 0.1000 -> 0 | N2: =H2 * 0.0000 -> 0 | O2: =ABS(M2 + N2) -> 0 | Q2: =SUMIFS(EXPENSES!E:E, EXPENSES!B:B, "LEASE-KH-F-2024", EXPENSES!D:D, ">="&DATE(2024,12,22), EXPENSES!D:D, "<="&DATE(2025,1,21)) -> 0 | S2: =H2 - O2 - Q2 -> 0 | Y2: 12150 | Z2: =S2-Y2 -> 0 | AA2: PAID | AB2: MULTIPLE | AC2: 45982
A3: TOTALS | G3: =SUM(G2:G2) -> 0 | H3: =SUM(H2:H2) -> 0 | J3: =SUM(J2:J2) -> 0 | K3: =SUM(K2:K2) -> 0 | L3: =SUM(L2:L2) -> 0 | M3: =SUM(M2:M2) -> 0 | N3: =SUM(N2:N2) -> 0 | O3: =SUM(O2:O2) -> 0 | Q3: =SUM(Q2:Q2) -> 0 | S3: =SUM(S2:S2) -> 0 | U3: =SUM(U2:U2) -> 0 | V3: =SUM(V2:V2) -> 0 | W3: =SUM(W2:W2) -> 0 | X3: =SUM(X2:X2) -> 0
A5: PAYMENT RECONCILIATION
A6: Period: 2024-12-22 to 2025-01-21
A8: BROUGHT FORWARD (items from prior periods paid this period)
A9: Prior Period Income: None
A10: Prior Period Expenses: None
A11: NET B/F (Income - Expenses): | B11: 0
A13: THIS PERIOD ACTIVITY (see transactions above for details)
A14: Period Income (0 transactions) | B14: 0
A15: Period Expenses (0 transactions) | B15: 0
A16: Net Activity (Income - Expenses): | B16: 0
A18: PAYMENTS MADE THIS PERIOD
A19: (No payments made this period)
A20: Total Payments Made: | B20: 0
A21: (See PAYMENT_ALLOCATIONS sheet for full details)
A23: SUMMARY
A24: Total Allocated (Income - Expenses): | B24: 0
A25: Total Payments Made: | B25: 0
A26: Unallocated Payment Amounts: | B26: 0
A28: Check: Allocated 0.00 + Unallocated 0.00 = 0.00 vs Payments 0.00

Sheet Jan 22 - Feb 21, 2025
A1: lease_reference | B1: property_name | C1: customer_name | D1: tenant_name | E1: lease_start_date | F1: rent_due_day | G1: rent_due | H1: rent_received | I1: rent_batch | J1: opening_balance | K1: period_arrears | L1: closing_balance | M1: management_fee | N1: service_fee | O1: total_commission | P1: commission_batch | Q1: total_expenses | R1: expenses_batch | S1: net_to_owner | T1: block_name | U1: property_account_opening | V1: property_account_in | W1: property_account_out | X1: property_account_closing | Y1: allocated_amount | Z1: variance | AA1: allocation_status | AB1: batch_id | AC1: paid_date
A2: LEASE-BH-F5-2025 | B2: Flat 5 - 3 West Gate | C2: Achal (Delegated for Udayan) | D2: Mr Amos Blyth | E2: 45698 | F2: 10 | G2: =IFERROR(SUMPRODUCT((RENT_DUE!$B$2:$B$1000="LEASE-BH-F5-2025")*(RENT_DUE!$D$2:$D$1000>=DATE(2025,1,22))*(RENT_DUE!$D$2:$D$1000<=DATE(2025,2,21))*RENT_DUE!$L$2:$L$1000), 0) -> 0 | H2: =IFERROR(SUMPRODUCT((RENT_RECEIVED!$B$2:$B$1000="LEASE-BH-F5-2025")*(RENT_RECEIVED!$E$2:$E$1000>=DATE(2025,1,22))*(RENT_RECEIVED!$E$2:$E$1000<=DATE(2025,2,21))*RENT_RECEIVED!$O$2:$O$1000), 0) -> 0 | I2: HIST-2025-03-1472 | J2: =IFERROR(SUMIFS(RENT_DUE!$L$2:$L$10000, RENT_DUE!$B$2:$B$10000, "LEASE-BH-F5-2025", RENT_DUE!$D$2:$D$10000, "<"&DATE(2025,1,22)), 0) - IFERROR(SUMIFS(RENT_RECEIVED!$O$2:$O$10000, RENT_RECEIVED!$B$2:$B$10000, "LEASE-BH-F5-2025", RENT_RECEIVED!$E$2:$E$10000, "<"&DATE(2025,1,22)), 0) -> 0 | K2: =G2 - H2 -> 0 | L2: =J2 + K2 -> 0 | M2: =H2 * 0.1500 -> 0 | N2: =H2 * 0.0000 -> 0 | O2: =ABS(M2 + N2) -> 0 | Q2: =SUMIFS(EXPENSES!E:E, EXPENSES!B:B, "LEASE-BH-F5-2025", EXPENSES!D:D, ">="&DATE(2025,1,22), EXPENSES!D:D, "<="&DATE(2025,2,21)) -> 0 | S2: =H2 - O2 - Q2 -> 0 | Y2: 6140 | Z2: =S2-Y2 -> 0 | AA2: PAID | AB2: MULTIPLE | AC2: 45982
A3: LEASE-BH-F7-2025 | B3: Flat 7 - 3 West Gate | C3: Achal (Delegated for Udayan) | D3: Mr Chun Hung Tang | E3: 45707 | F3: 19 | G3: =IFERROR(SUMPRODUCT((RENT_DUE!$B$2:$B$1000="LEASE-BH-F7-2025")*(RENT_DUE!$D$2:$D$1000>=DATE(2025,1,22))*(RENT_DUE!$D$2:$D$1000<=DATE(2025,2,21))*RENT_DUE!$L$2:$L$1000), 0) -> 0 | H3: =IFERROR(SUMPRODUCT((RENT_RECEIVED!$B$2:$B$1000="LEASE-BH-F7-2025")*(RENT_RECEIVED!$E$2:$E$1000>=DATE(2025,1,22))*(RENT_RECEIVED!$E$2:$E$1000<=DATE(2025,2,21))*RENT_RECEIVED!$O$2:$O$1000), 0) -> 0 | I3: HIST-2025-03-1472 | J3: =IFERROR(SUMIFS(RENT_DUE!$L$2:$L$10000, RENT_DUE!$B$2:$B$10000, "LEASE-BH-F7-2025", RENT_DUE!$D$2:$D$10000, "<"&DATE(2025,1,22)), 0) - IFERROR(SUMIFS(RENT_RECEIVED!$O$2:$O$10000, RENT_RECEIVED!$B$2:$B$10000, "LEASE-BH-F7-2025", RENT_RECEIVED!$E$2:$E$10000, "<"&DATE(2025,1,22)), 0) -> 0 | K3: =G3 - H3 -> 0 | L3: =J3 + K3 -> 0 | M3: =H3 * 0.1500 -> 0 | N3: =H3 * 0.0000 -> 0 | O3: =ABS(M3 + N3) -> 0 | Q3: =SUMIFS(EXPENSES!E:E, EXPENSES!B:B, "LEASE-BH-F7-2025", EXPENSES!D:D, ">="&DATE(2025,1,22), EXPENSES!D:D, "<="&DATE(2025,2,21)) -> 0 | S3: =H3 - O3 - Q3 -> 0 | Y3: 3570 | Z3: =S3-Y3 -> 0 | AA3: PAID | AB3: MULTIPLE | AC3: 45861
A4: LEASE-BH-F15-2025 | B4: Flat 15 - 3 West Gate | C4: Achal (Delegated for Udayan) | D4: Ms Lucy Cassell | E4: 45703 | F4: 15 | G4: =IFERROR(SUMPRODUCT((RENT_DUE!$B$2:$B$1000="LEASE-BH-F15-2025")*(RENT_DUE!$D$2:$D$1000>=DATE(2025,1,22))*(RENT_DUE!$D$2:$D$1000<=DATE(2025,2,21))*RENT_DUE!$L$2:$L$1000), 0) -> 0 | H4: =IFERROR(SUMPRODUCT((RENT_RECEIVED!$B$2:$B$1000="LEASE-BH-F15-2025")*(RENT_RECEIVED!$E$2:$E$1000>=DATE(2025,1,22))*(RENT_RECEIVED!$E$2:$E$1000<=DATE(2025,2,21))*RENT_RECEIVED!$O$2:$O$1000), 0) -> 0 | I4: HIST-2025-03-1472, HIST-2025-03-1501 | J4: =IFERROR(SUMIFS(RENT_DUE!$L$2:$L$10000, RENT_DUE!$B$2:$B$10000, "LEASE-BH-F15-2025", RENT_DUE!$D$2:$D$10000, "<"&DATE(2025,1,22)), 0) - IFERROR(SUMIFS(RENT_RECEIVED!$O$2:$O$10000, RENT_RECEIVED!$B$2:$B$10000, "LEASE-BH-F15-2025", RENT_RECEIVED!$E$2:$E$10000, "<"&DATE(2025,1,22)), 0) -> 0 | K4: =G4 - H4 -> 0 | L4: =J4 + K4 -> 0 | M4: =H4 * 0.1500 -> 0 | N4: =H4 * 0.0000 -> 0 | O4: =ABS(M4 + N4) -> 0 | Q4: =SUMIFS(EXPENSES!E:E, EXPENSES!B:B, "LEASE-BH-F15-2025", EXPENSES!D:D, ">="&DATE(2025,1,22), EXPENSES!D:D, "<="&DATE(2025,2,21)) -> 0 | S4: =H4 - O4 - Q4 -> 0 | Y4: 6170 | Z4: =S4-Y4 -> 0 | AA4: PAID | AB4: MULTIPLE | AC4: 45982
A5: LEASE-BH-F17-2025 | B5: Flat 17 - 3 West Gate | C5: Achal (Delegated for Udayan) | D5: Mr Harsh Patel | E5: 45705 | F5: 17 | G5: =IFERROR(SUMPRODUCT((RENT_DUE!$B$2:$B$1000="LEASE-BH-F17-2025")*(RENT_DUE!$D$2:$D$1000>=DATE(2025,1,22))*(RENT_DUE!$D$2:$D$1000<=DATE(2025,2,21))*RENT_DUE!$L$2:$L$1000), 0) -> 0 | H5: =IFERROR(SUMPRODUCT((RENT_RECEIVED!$B$2:$B$1000="LEASE-BH-F17-2025")*(RENT_RECEIVED!$E$2:$E$1000>=DATE(2025,1,22))*(RENT_RECEIVED!$E$2:$E$1000<=DATE(2025,2,21))*RENT_RECEIVED!$O$2:$O$1000), 0) -> 0 | I5: HIST-2025-03-1501 | J5: =IFERROR(SUMIFS(RENT_DUE!$L$2:$L$10000, RENT_DUE!$B$2:$B$10000, "LEASE-BH-F17-2025", RENT_DUE!$D$2:$D$10000, "<"&DATE(2025,1,22)), 0) - IFERROR(SUMIFS(RENT_RECEIVED!$O$2:$O$10000, RENT_RECEIVED!$B$2:$B$10000, "LEASE-BH-F17-2025", RENT_RECEIVED!$E$2:$E$10000, "<"&DATE(2025,1,22)), 0) -> 0 | K5: =G5 - H5 -> 0 | L5: =J5 + K5 -> 0 | M5: =H5 * 0.1500 -> 0 | N5: =H5 * 0.0000 -> 0 | O5: =ABS(M5 + N5) -> 0 | Q5: =SUMIFS(EXPENSES!E:E, EXPENSES!B:B, "LEASE-BH-F17-2025", EXPENSES!D:D, ">="&DATE(2025,1,22), EXPENSES!D:D, "<="&DATE(2025,2,21)) -> 0 | S5: =H5 - O5 - Q5 -> 0 | Y5: 5800 | Z5: =S5-Y5 -> 0 | AA5: PAID | AB5: MULTIPLE | AC5: 45982
A6: LEASE-BH-F18-2025 | B6: Flat 18 - 3 West Gate | C6: Achal (Delegated for Udayan) | D6: Marie Dinko | E6: 45687 | F6: 30 | G6: =IFERROR(SUMPRODUCT((RENT_DUE!$B$2:$B$1000="LEASE-BH-F18-2025")*(RENT_DUE!$D$2:$D$1000>=DATE(2025,1,22))*(RENT_DUE!$D$2:$D$1000<=DATE(2025,2,21))*RENT_DUE!$L$2:$L$1000), 0) -> 0 | H6: =IFERROR(SUMPRODUCT((RENT_RECEIVED!$B$2:$B$1000="LEASE-BH-F18-2025")*(RENT_RECEIVED!$E$2:$E$1000>=DATE(2025,1,22))*(RENT_RECEIVED!$E$2:$E$1000<=DATE(2025,2,21))*RENT_RECEIVED!$O$2:$O$1000), 0) -> 0 | I6: HIST-2025-03-1475 | J6: =IFERROR(SUMIFS(RENT_DUE!$L$2:$L$10000, RENT_DUE!$B$2:$B$10000, "LEASE-BH-F18-2025", RENT_DUE!$D$2:$D$10000, "<"&DATE(2025,1,22)), 0) - IFERROR(SUMIFS(RENT_RECEIVED!$O$2:$O$10000, RENT_RECEIVED!$B$2:$B$10000, "LEASE-BH-F18-2025", RENT_RECEIVED!$E$2:$E$10000, "<"&DATE(2025,1,22)), 0) -> 0 | K6: =G6 - H6 -> 0 | L6: =J6 + K6 -> 0 | M6: =H6 * 0.1500 -> 0 | N6: =H6 * 0.0000 -> 0 | O6: =ABS(M6 + N6) -> 0 | Q6: =SUMIFS(EXPENSES!E:E, EXPENSES!B:B, "LEASE-BH-F18-2025", EXPENSES!D:D, ">="&DATE(2025,1,22), EXPENSES!D:D, "<="&DATE(2025,2,21)) -> 0 | S6: =H6 - O6 - Q6 -> 0 | Y6: 2044.25 | Z6: =S6-Y6 -> 0 | AA6: PAID | AB6: MULTIPLE | AC6: 45804
A7: LEASE-BH-F21-2025 | B7: Flat 21 - 3 West Gate | C7: Achal (Delegated for Udayan) | D7: Mr Felwin Francis | E7: 45687 | F7: 30 | G7: =IFERROR(SUMPRODUCT((RENT_DUE!$B$2:$B$1000="LEASE-BH-F21-2025")*(RENT_DUE!$D$2:$D$1000>=DATE(2025,1,22))*(RENT_DUE!$D$2:$D$1000<=DATE(2025,2,21))*RENT_DUE!$L$2:$L$1000), 0) -> 0 | H7: =IFERROR(SUMPRODUCT((RENT_RECEIVED!$B$2:$B$1000="LEASE-BH-F21-2025")*(RENT_RECEIVED!$E$2:$E$1000>=DATE(2025,1,22))*(RENT_RECEIVED!$E$2:$E$1000<=DATE(2025,2,21))*RENT_RECEIVED!$O$2:$O$1000), 0) -> 0 | I7: HIST-2025-03-1472, HIST-2025-03-1475 | J7: =IFERROR(SUMIFS(RENT_DUE!$L$2:$L$10000, RENT_DUE!$B$2:$B$10000, "LEASE-BH-F21-2025", RENT_DUE!$D$2:$D$10000, "<"&DATE(2025,1,22)), 0) - IFERROR(SUMIFS(RENT_RECEIVED!$O$2:$O$10000, RENT_RECEIVED!$B$2:$B$10000, "LEASE-BH-F21-2025", RENT_RECEIVED!$E$2:$E$10000, "<"&DATE(2025,1,22)), 0) -> 0 | K7: =G7 - H7 -> 0 | L7: =J7 + K7 -> 0 | M7: =H7 * 0.1500 -> 0 | N7: =H7 * 0.0000 -> 0 | O7: =ABS(M7 + N7) -> 0 | Q7: =SUMIFS(EXPENSES!E:E, EXPENSES!B:B, "LEASE-BH-F21-2025", EXPENSES!D:D, ">="&DATE(2025,1,22), EXPENSES!D:D, "<="&DATE(2025,2,21)) -> 0 | S7: =H7 - O7 - Q7 -> 0 | Y7: 6637.5 | Z7: =S7-Y7 -> 0 | AA7: PAID | AB7: MULTIPLE | AC7: 45982
A8: LEASE-BH-F24-2025 | B8: Flat 24 - 3 West Gate | C8: Achal (Delegated for Udayan) | D8: Mr Ethan Maloney, Miss Soraya Fearon | E8: 45700 | F8: 12 | G8: =IFERROR(SUMPRODUCT((RENT_DUE!$B$2:$B$1000="LEASE-BH-F24-2025")*(RENT_DUE!$D$2:$D$1000>=DATE(2025,1,22))*(RENT_DUE!$D$2:$D$1000<=DATE(2025,2,21))*RENT_DUE!$L$2:$L$1000), 0) -> 0 | H8: =IFERROR(SUMPRODUCT((RENT_RECEIVED!$B$2:$B$1000="LEASE-BH-F24-2025")*(RENT_RECEIVED!$E$2:$E$1000>=DATE(2025,1,22))*(RENT_RECEIVED!$E$2:$E$1000<=DATE(2025,2,21))*RENT_RECEIVED!$O$2:$O$1000), 0) -> 0 | I8: HIST-2025-03-1501 | J8: =IFERROR(SUMIFS(RENT_DUE!$L$2:$L$10000, RENT_DUE!$B$2:$B$10000, "LEASE-BH-F24-2025", RENT_DUE!$D$2:$D$10000, "<"&DATE(2025,1,22)), 0) - IFERROR(SUMIFS(RENT_RECEIVED!$O$2:$O$10000, RENT_RECEIVED!$B$2:$B$10000, "LEASE-BH-F24-2025", RENT_RECEIVED!$E$2:$E$10000, "<"&DATE(2025,1,22)), 0) -> 0 | K8: =G8 - H8 -> 0 | L8: =J8 + K8 -> 0 | M8: =H8 * 0.1500 -> 0 | N8: =H8 * 0.0000 -> 0 | O8: =ABS(M8 + N8) -> 0 | Q8: =SUMIFS(EXPENSES!E:E, EXPENSES!B:B, "LEASE-BH-F24-2025", EXPENSES!D:D, ">="&DATE(2025,1,22), EXPENSES!D:D, "<="&DATE(2025,2,21)) -> 0 | S8: =H8 - O8 - Q8 -> 0 | Y8: 6765 | Z8: =S8-Y8 -> 0 | AA8: PAID | AB8: MULTIPLE | AC8: 45982
A9: LEASE-KH-F-2024 | B9: Apartment F - Knighton Hayes Manor | C9: Achal (Delegated for Udayan) | D9: Mr Riaz Hamid, Ismat Tarr-Hamid | E9: 45648 | F9: 22 | G9: =IFERROR(SUMPRODUCT((RENT_DUE!$B$2:$B$1000="LEASE-KH-F-2024")*(RENT_DUE!$D$2:$D$1000>=DATE(2025,1,22))*(RENT_DUE!$D$2:$D$1000<=DATE(2025,2,21))*RENT_DUE!$L$2:$L$1000), 0) -> 0 | H9: =IFERROR(SUMPRODUCT((RENT_RECEIVED!$B$2:$B$1000="LEASE-KH-F-2024")*(RENT_RECEIVED!$E$2:$E$1000>=DATE(2025,1,22))*(RENT_RECEIVED!$E$2:$E$1000<=DATE(2025,2,21))*RENT_RECEIVED!$O$2:$O$1000), 0) -> 0 | I9: HIST-2025-03-1473, HIST-2025-03-1474 | J9: =IFERROR(SUMIFS(RENT_DUE!$L$2:$L$10000, RENT_DUE!$B$2:$B$10000, "LEASE-KH-F-2024", RENT_DUE!$D$2:$D$10000, "<"&DATE(2025,1,22)), 0) - IFERROR(SUMIFS(RENT_RECEIVED!$O$2:$O$10000, RENT_RECEIVED!$B$2:$B$10000, "LEASE-KH-F-2024", RENT_RECEIVED!$E$2:$E$10000, "<"&DATE(2025,1,22)), 0) -> 0 | K9: =G9 - H9 -> 0 | L9: =J9 + K9 -> 0 | M9: =H9 * 0.1000 -> 0 | N9: =H9 * 0.0000 -> 0 | O9: =ABS(M9 + N9) -> 0 | Q9: =SUMIFS(EXPENSES!E:E, EXPENSES!B:B, "LEASE-KH-F-2024", EXPENSES!D:D, ">="&DATE(2025,1,22), EXPENSES!D:D, "<="&DATE(2025,2,21)) -> 0 | S9: =H9 - O9 - Q9 -> 0 | Y9: 12150 | Z9: =S9-Y9 -> 0 | AA9: PAID | AB9: MULTIPLE | AC9: 45982
A10: TOTALS | G10: =SUM(G2:G9) -> 0 | H10: =SUM(H2:H9) -> 0 | J10: =SUM(J2:J9) -> 0 | K10: =SUM(K2:K9) -> 0 | L10: =SUM(L2:L9) -> 0 | M10: =SUM(M2:M9) -> 0 | N10: =SUM(N2:N9) -> 0 | O10: =SUM(O2:O9) -> 0 | Q10: =SUM(Q2:Q9) -> 0 | S10: =SUM(S2:S9) -> 0 | U10: =SUM(U2:U9) -> 0 | V10: =SUM(V2:V9) -> 0 | W10: =SUM(W2:W9) -> 0 | X10: =SUM(X2:X9) -> 0
A12: PAYMENT RECONCILIATION
A13: Period: 2025-01-22 to 2025-02-21
A15: BROUGHT FORWARD (items from prior periods paid this period)
A16: Prior Period Income: None
A17: Prior Period Expenses: None
A18: NET B/F (Income - Expenses): | B18: 0
A20: THIS PERIOD ACTIVITY (see transactions above for details)
A21: Period Income (0 transactions) | B21: 0
A22: Period Expenses (0 transactions) | B22: 0
A23: Net Activity (Income - Expenses): | B23: 0
A25: PAYMENTS MADE THIS PERIOD
A26: (No payments made this period)
A27: Total Payments Made: | B27: 0
A28: (See PAYMENT_ALLOCATIONS sheet for full details)
A30: SUMMARY
A31: Total Allocated (Income - Expenses): | B31: 0
A32: Total Payments Made: | B32: 0
A33: Unallocated Payment Amounts: | B33: 0
A35: Check: Allocated 0.00 + Unallocated 0.00 = 0.00 vs Payments 0.00

Sheet Feb 22 - Mar 21, 2025
A1: lease_reference | B1: property_name | C1: customer_name | D1: tenant_name | E1: lease_start_date | F1: rent_due_day | G1: rent_due | H1: rent_received | I1: rent_batch | J1: opening_balance | K1: period_arrears | L1: closing_balance | M1: management_fee | N1: service_fee | O1: total_commission | P1: commission_batch | Q1: total_expenses | R1: expenses_batch | S1: net_to_owner | T1: block_name | U1: property_account_opening | V1: property_account_in | W1: property_account_out | X1: property_account_closing | Y1: allocated_amount | Z1: variance | AA1: allocation_status | AB1: batch_id | AC1: paid_date
A2: LEASE-BH-F1-2025 | B2: Flat 1 - 3 West Gate | C2: Achal (Delegated for Udayan) | D2: Ms Oleksandra Smoliarenko, Mr Illia Halii | E2: 45715 | F2: 27 | G2: =IFERROR(SUMPRODUCT((RENT_DUE!$B$2:$B$1000="LEASE-BH-F1-2025")*(RENT_DUE!$D$2:$D$1000>=DATE(2025,2,22))*(RENT_DUE!$D$2:$D$1000<=DATE(2025,3,21))*RENT_DUE!$L$2:$L$1000), 0) -> 0 | H2: =IFERROR(SUMPRODUCT((RENT_RECEIVED!$B$2:$B$1000="LEASE-BH-F1-2025")*(RENT_RECEIVED!$E$2:$E$1000>=DATE(2025,2,22))*(RENT_RECEIVED!$E$2:$E$1000<=DATE(2025,3,21))*RENT_RECEIVED!$O$2:$O$1000), 0) -> 0 | I2: HIST-2025-03-1501 | J2: =IFERROR(SUMIFS(RENT_DUE!$L$2:$L$10000, RENT_DUE!$B$2:$B$10000, "LEASE-BH-F1-2025", RENT_DUE!$D$2:$D$10000, "<"&DATE(2025,2,22)), 0) - IFERROR(SUMIFS(RENT_RECEIVED!$O$2:$O$10000, RENT_RECEIVED!$B$2:$B$10000, "LEASE-BH-F1-2025", RENT_RECEIVED!$E$2:$E$10000, "<"&DATE(2025,2,22)), 0) -> 0 | K2: =G2 - H2 -> 0 | L2: =J2 + K2 -> 0 | M2: =H2 * 0.1500 -> 0 | N2: =H2 * 0.0000 -> 0 | O2: =ABS(M2 + N2) -> 0 | Q2: =SUMIFS(EXPENSES!E:E, EXPENSES!B:B, "LEASE-BH-F1-2025", EXPENSES!D:D, ">="&DATE(2025,2,22), EXPENSES!D:D, "<="&DATE(2025,3,21)) -> 0 | S2: =H2 - O2 - Q2 -> 0 | Y2: 5985.52 | Z2: =S2-Y2 -> 0 | AA2: PAID | AB2: MULTIPLE | AC2: 45992
A3: LEASE-BH-F2-2025 | B3: Flat 2 - 3 West Gate | C3: Achal (Delegated for Udayan) | D3: Mr Mustafa Al Bayat, Mrs Gulala Al - Zangana | E3: 45715 | F3: 27 | G3: =IFERROR(SUMPRODUCT((RENT_DUE!$B$2:$B$1000="LEASE-BH-F2-2025")*(RENT_DUE!$D$2:$D$1000>=DATE(2025,2,22))*(RENT_DUE!$D$2:$D$1000<=DATE(2025,3,21))*RENT_DUE!$L$2:$L$1000), 0) -> 0 | H3: =IFERROR(SUMPRODUCT((RENT_RECEIVED!$B$2:$B$1000="LEASE-BH-F2-2025")*(RENT_RECEIVED!$E$2:$E$1000>=DATE(2025,2,22))*(RENT_RECEIVED!$E$2:$E$1000<=DATE(2025,3,21))*RENT_RECEIVED!$O$2:$O$1000), 0) -> 0 | I3: HIST-2025-03-1501 | J3: =IFERROR(SUMIFS(RENT_DUE!$L$2:$L$10000, RENT_DUE!$B$2:$B$10000, "LEASE-BH-F2-2025", RENT_DUE!$D$2:$D$10000, "<"&DATE(2025,2,22)), 0) - IFERROR(SUMIFS(RENT_RECEIVED!$O$2:$O$10000, RENT_RECEIVED!$B$2:$B$10000, "LEASE-BH-F2-2025", RENT_RECEIVED!$E$2:$E$10000, "<"&DATE(2025,2,22)), 0) -> 0 | K3: =G3 - H3 -> 0 | L3: =J3 + K3 -> 0 | M3: =H3 * 0.1500 -> 0 | N3: =H3 * 0.0000 -> 0 | O3: =ABS(M3 + N3) -> 0 | Q3: =SUMIFS(EXPENSES!E:E, EXPENSES!B:B, "LEASE-BH-F2-2025", EXPENSES!D:D, ">="&DATE(2025,2,22), EXPENSES!D:D, "<="&DATE(2025,3,21)) -> 0 | S3: =H3 - O3 - Q3 -> 0 | Y3: 5661 | Z3: =S3-Y3 -> 0 | AA3: PAID | AB3: MULTIPLE | AC3: 45992
A4: LEASE-BH-F3-2025 | B4: Flat 3 - 3 West Gate | C4: Achal (Delegated for Udayan) | D4: Mr Tracy Whyte | E4: 45727 | F4: 11 | G4: =IFERROR(SUMPRODUCT((RENT_DUE!$B$2:$B$1000="LEASE-BH-F3-2025")*(RENT_DUE!$D$2:$D$1000>=DATE(2025,2,22))*(RENT_DUE!$D$2:$D$1000<=DATE(2025,3,21))*RENT_DUE!$L$2:$L$1000), 0) -> 0 | H4: =IFERROR(SUMPRODUCT((RENT_RECEIVED!$B$2:$B$1000="LEASE-BH-F3-2025")*(RENT_RECEIVED!$E$2:$E$1000>=DATE(2025,2,22))*(RENT_RECEIVED!$E$2:$E$1000<=DATE(2025,3,21))*RENT_RECEIVED!$O$2:$O$1000), 0) -> 0 | I4: HIST-2025-03-1501 | J4: =IFERROR(SUMIFS(RENT_DUE!$L$2:$L$10000, RENT_DUE!$B$2:$B$10000, "LEASE-BH-F3-2025", RENT_DUE!$D$2:$D$10000, "<"&DATE(2025,2,22)), 0) - IFERROR(SUMIFS(RENT_RECEIVED!$O$2:$O$10000, RENT_RECEIVED!$B$2:$B$10000, "LEASE-BH-F3-2025", RENT_RECEIVED!$E$2:$E$10000, "<"&DATE(2025,2,22)), 0) -> 0 | K4: =G4 - H4 -> 0 | L4: =J4 + K4 -> 0 | M4: =H4 * 0.1500 -> 0 | N4: =H4 * 0.0000 -> 0 | O4: =ABS(M4 + N4) -> 0 | Q4: =SUMIFS(EXPENSES!E:E, EXPENSES!B:B, "LEASE-BH-F3-2025", EXPENSES!D:D, ">="&DATE(2025,2,22), EXPENSES!D:D, "<="&DATE(2025,3,21)) -> 0 | S4: =H4 - O4 - Q4 -> 0 | Y4: 5661 | Z4: =S4-Y4 -> 0 | AA4: PAID | AB4: MULTIPLE | AC4: 45992
A5: LEASE-BH-F4-2025 | B5: Flat 4 - 3 West Gate | C5: Achal (Delegated for Udayan) | D5: Miss Megan Delaney, Mr Joseph Williams | E5: 45713 | F5: 25 | G5: =IFERROR(SUMPRODUCT((RENT_DUE!$B$2:$B$1000="LEASE-BH-F4-2025")*(RENT_DUE!$D$2:$D$1000>=DATE(2025,2,22))*(RENT_DUE!$D$2:$D$1000<=DATE(2025,3,21))*RENT_DUE!$L$2:$L$1000), 0) -> 0 | H5: =IFERROR(SUMPRODUCT((RENT_RECEIVED!$B$2:$B$1000="LEASE-BH-F4-2025")*(RENT_RECEIVED!$E$2:$E$1000>=DATE(2025,2,22))*(RENT_RECEIVED!$E$2:$E$1000<=DATE(2025,3,21))*RENT_RECEIVED!$O$2:$O$1000), 0) -> 0 | I5: HIST-2025-03-1501 | J5: =IFERROR(SUMIFS(RENT_DUE!$L$2:$L$10000, RENT_DUE!$B$2:$B$10000, "LEASE-BH-F4-2025", RENT_DUE!$D$2:$D$10000, "<"&DATE(2025,2,22)), 0) - IFERROR(SUMIFS(RENT_RECEIVED!$O$2:$O$10000, RENT_RECEIVED!$B$2:$B$10000, "LEASE-BH-F4-2025", RENT_RECEIVED!$E$2:$E$10000, "<"&DATE(2025,2,22)), 0) -> 0 | K5: =G5 - H5 -> 0 | L5: =J5 + K5 -> 0 | M5: =H5 * 0.1500 -> 0 | N5: =H5 * 0.0000 -> 0 | O5: =ABS(M5 + N5) -> 0 | Q5: =SUMIFS(EXPENSES!E:E, EXPENSES!B:B, "LEASE-BH-F4-2025", EXPENSES!D:D, ">="&DATE(2025,2,22), EXPENSES!D:D, "<="&DATE(2025,3,21)) -> 0 | S5: =H5 - O5 - Q5 -> 0 | Y5: 6390.75 | Z5: =S5-Y5 -> 0 | AA5: PAID | AB5: MULTIPLE | AC5: 45982
A6: LEASE-BH-F5-2025 | B6: Flat 5 - 3 West Gate | C6: Achal (Delegated for Udayan) | D6: Mr Amos Blyth | E6: 45698 | F6: 10 | G6: =IFERROR(SUMPRODUCT((RENT_DUE!$B$2:$B$1000="LEASE-BH-F5-2025")*(RENT_DUE!$D$2:$D$1000>=DATE(2025,2,22))*(RENT_DUE!$D$2:$D$1000<=DATE(2025,3,21))*RENT_DUE!$L$2:$L$1000), 0) -> 0 | H6: =IFERROR(SUMPRODUCT((RENT_RECEIVED!$B$2:$B$1000="LEASE-BH-F5-2025")*(RENT_RECEIVED!$E$2:$E$1000>=DATE(2025,2,22))*(RENT_RECEIVED!$E$2:$E$1000<=DATE(2025,3,21))*RENT_RECEIVED!$O$2:$O$1000), 0) -> 0 | I6: HIST-2025-03-1501 | J6: =IFERROR(SUMIFS(RENT_DUE!$L$2:$L$10000, RENT_DUE!$B$2:$B$10000, "LEASE-BH-F5-2025", RENT_DUE!$D$2:$D$10000, "<"&DATE(2025,2,22)), 0) - IFERROR(SUMIFS(RENT_RECEIVED!$O$2:$O$10000, RENT_RECEIVED!$B$2:$B$10000, "LEASE-BH-F5-2025", RENT_RECEIVED!$E$2:$E$10000, "<"&DATE(2025,2,22)), 0) -> 0 | K6: =G6 - H6 -> 0 | L6: =J6 + K6 -> 0 | M6: =H6 * 0.1500 -> 0 | N6: =H6 * 0.0000 -> 0 | O6: =ABS(M6 + N6) -> 0 | Q6: =SUMIFS(EXPENSES!E:E, EXPENSES!B:B, "LEASE-BH-F5-2025", EXPENSES!D:D, ">="&DATE(2025,2,22), EXPENSES!D:D, "<="&DATE(2025,3,21)) -> 0 | S6: =H6 - O6 - Q6 -> 0 | Y6: 6140 | Z6: =S6-Y6 -> 0 | AA6: PAID | AB6: MULTIPLE | AC6: 45982
A7: LEASE-BH-F7-2025 | B7: Flat 7 - 3 West Gate | C7: Achal (Delegated for Udayan) | D7: Mr Chun Hung Tang | E7: 45707 | F7: 19 | G7: =IFERROR(SUMPRODUCT((RENT_DUE!$B$2:$B$1000="LEASE-BH-F7-2025")*(RENT_DUE!$D$2:$D$1000>=DATE(2025,2,22))*(RENT_DUE!$D$2:$D$1000<=DATE(2025,3,21))*RENT_DUE!$L$2:$L$1000), 0) -> 0 | H7: =IFERROR(SUMPRODUCT((RENT_RECEIVED!$B$2:$B$1000="LEASE-BH-F7-2025")*(RENT_RECEIVED!$E$2:$E$1000>=DATE(2025,2,22))*(RENT_RECEIVED!$E$2:$E$1000<=DATE(2025,3,21))*RENT_RECEIVED!$O$2:$O$1000), 0) -> 0 | I7: HIST-2025-03-1501 | J7: =IFERROR(SUMIFS(RENT_DUE!$L$2:$L$10000, RENT_DUE!$B$2:$B$10000, "LEASE-BH-F7-2025", RENT_DUE!$D$2:$D$10000, "<"&DATE(2025,2,22)), 0) - IFERROR(SUMIFS(RENT_RECEIVED!$O$2:$O$10000, RENT_RECEIVED!$B$2:$B$10000, "LEASE-BH-F7-2025", RENT_RECEIVED!$E$2:$E$10000, "<"&DATE(2025,2,22)), 0) -> 0 | K7: =G7 - H7 -> 0 | L7: =J7 + K7 -> 0 | M7: =H7 * 0.1500 -> 0 | N7: =H7 * 0.0000 -> 0 | O7: =ABS(M7 + N7) -> 0 | Q7: =SUMIFS(EXPENSES!E:E, EXPENSES!B:B, "LEASE-BH-F7-2025", EXPENSES!D:D, ">="&DATE(2025,2,22), EXPENSES!D:D, "<="&DATE(2025,3,21)) -> 0 | S7: =H7 - O7 - Q7 -> 0 | Y7: 3570 | Z7: =S7-Y7 -> 0 | AA7: PAID | AB7: MULTIPLE | AC7: 45861
A8: LEASE-BH-F8-2025 | B8: Flat 8 - 3 West Gate | C8: Achal (Delegated for Udayan) | D8: Mr Shermal Wijesinghage, Mrs Udeshika Dona | E8: 45712 | F8: 24 | G8: =IFERROR(SUMPRODUCT((RENT_DUE!$B$2:$B$1000="LEASE-BH-F8-2025")*(RENT_DUE!$D$2:$D$1000>=DATE(2025,2,22))*(RENT_DUE!$D$2:$D$1000<=DATE(2025,3,21))*RENT_DUE!$L$2:$L$1000), 0) -> 0 | H8: =IFERROR(SUMPRODUCT((RENT_RECEIVED!$B$2:$B$1000="LEASE-BH-F8-2025")*(RENT_RECEIVED!$E$2:$E$1000>=DATE(2025,2,22))*(RENT_RECEIVED!$E$2:$E$1000<=DATE(2025,3,21))*RENT_RECEIVED!$O$2:$O$1000), 0) -> 0 | I8: HIST-2025-03-1501 | J8: =IFERROR(SUMIFS(RENT_DUE!$L$2:$L$10000, RENT_DUE!$B$2:$B$10000, "LEASE-BH-F8-2025", RENT_DUE!$D$2:$D$10000, "<"&DATE(2025,2,22)), 0) - IFERROR(SUMIFS(RENT_RECEIVED!$O$2:$O$10000, RENT_RECEIVED!$B$2:$B$10000, "LEASE-BH-F8-2025", RENT_RECEIVED!$E$2:$E$10000, "<"&DATE(2025,2,22)), 0) -> 0 | K8: =G8 - H8 -> 0 | L8: =J8 + K8 -> 0 | M8: =H8 * 0.1500 -> 0 | N8: =H8 * 0.0000 -> 0 | O8: =ABS(M8 + N8) -> 0 | Q8: =SUMIFS(EXPENSES!E:E, EXPENSES!B:B, "LEASE-BH-F8-2025", EXPENSES!D:D, ">="&DATE(2025,2,22), EXPENSES!D:D, "<="&DATE(2025,3,21)) -> 0 | S8: =H8 - O8 - Q8 -> 0 | Y8: 5318.75 | Z8: =S8-Y8 -> 0 | AA8: PAID | AB8: MULTIPLE | AC8: 45982
A9: LEASE-BH-F9-2025 | B9: Flat 9 - 3 West Gate | C9: Achal (Delegated for Udayan) | D9: Mr Scott Warner | E9: 45736 | F9: 20 | G9: =IFERROR(SUMPRODUCT((RENT_DUE!$B$2:$B$1000="LEASE-BH-F9-2025")*(RENT_DUE!$D$2:$D$1000>=DATE(2025,2,22))*(RENT_DUE!$D$2:$D$1000<=DATE(2025,3,21))*RENT_DUE!$L$2:$L$1000), 0) -> 0 | H9: =IFERROR(SUMPRODUCT((RENT_RECEIVED!$B$2:$B$1000="LEASE-BH-F9-2025")*(RENT_RECEIVED!$E$2:$E$1000>=DATE(2025,2,22))*(RENT_RECEIVED!$E$2:$E$1000<=DATE(2025,3,21))*RENT_RECEIVED!$O$2:$O$1000), 0) -> 0 | I9: HIST-2025-03-1501 | J9: =IFERROR(SUMIFS(RENT_DUE!$L$2:$L$10000, RENT_DUE!$B$2:$B$10000, "LEASE-BH-F9-2025", RENT_DUE!$D$2:$D$10000, "<"&DATE(2025,2,22)), 0) - IFERROR(SUMIFS(RENT_RECEIVED!$O$2:$O$10000, RENT_RECEIVED!$B$2:$B$10000, "LEASE-BH-F9-2025", RENT_RECEIVED!$E$2:$E$10000, "<"&DATE(2025,2,22)), 0) -> 0 | K9: =G9 - H9 -> 0 | L9: =J9 + K9 -> 0 | M9: =H9 * 0.1500 -> 0 | N9: =H9 * 0.0000 -> 0 | O9: =ABS(M9 + N9) -> 0 | Q9: =SUMIFS(EXPENSES!E:E, EXPENSES!B:B, "LEASE-BH-F9-2025", EXPENSES!D:D, ">="&DATE(2025,2,22), EXPENSES!D:D, "<="&DATE(2025,3,21)) -> 0 | S9: =H9 - O9 - Q9 -> 0 | Y9: 5255 | Z9: =S9-Y9 -> 0 | AA9: PAID | AB9: MULTIPLE | AC9: 45982
A10: LEASE-BH-F10-2025 | B10: Flat 10 - 3 West Gate | C10: Achal (Delegated for Udayan) | D10: Mr Ferenc Peter | E10: 45722 | F10: 6 | G10: =IFERROR(SUMPRODUCT((RENT_DUE!$B$2:$B$1000="LEASE-BH-F10-2025")*(RENT_DUE!$D$2:$D$1000>=DATE(2025,2,22))*(RENT_DUE!$D$2:$D$1000<=DATE(2025,3,21))*RENT_DUE!$L$2:$L$1000), 0) -> 0 | H10: =IFERROR(SUMPRODUCT((RENT_RECEIVED!$B$2:$B$1000="LEASE-BH-F10-2025")*(RENT_RECEIVED!$E$2:$E$1000>=DATE(2025,2,22))*(RENT_RECEIVED!$E$2:$E$1000<=DATE(2025,3,21))*RENT_RECEIVED!$O$2:$O$1000), 0) -> 0 | I10: HIST-2025-03-1501 | J10: =IFERROR(SUMIFS(RENT_DUE!$L$2:$L$10000, RENT_DUE!$B$2:$B$10000, "LEASE-BH-F10-2025", RENT_DUE!$D$2:$D$10000, "<"&DATE(2025,2,22)), 0) - IFERROR(SUMIFS(RENT_RECEIVED!$O$2:$O$10000, RENT_RECEIVED!$B$2:$B$10000, "LEASE-BH-F10-2025", RENT_RECEIVED!$E$2:$E$10000, "<"&DATE(2025,2,22)), 0) -> 0 | K10: =G10 - H10 -> 0 | L10: =J10 + K10 -> 0 | M10: =H10 * 0.1500 -> 0 | N10: =H10 * 0.0000 -> 0 | O10: =ABS(M10 + N10) -> 0 | Q10: =SUMIFS(EXPENSES!E:E, EXPENSES!B:B, "LEASE-BH-F10-2025", EXPENSES!D:D, ">="&DATE(2025,2,22), EXPENSES!D:D, "<="&DATE(2025,3,21)) -> 0 | S10: =H10 - O10 - Q10 -> 0 | Y10: 3534.47 | Z10: =S10-Y10 -> 0 | AA10: PAID | AB10: MULTIPLE | AC10: 45920
A11: LEASE-BH-F11-2025 | B11: Flat 11 - 3 West Gate | C11: Achal (Delegated for Udayan) | D11: Mr Richard Perrotta | E11: 45722 | F11: 26 | G11: =IFERROR(SUMPRODUCT((RENT_DUE!$B$2:$B$1000="LEASE-BH-F11-2025")*(RENT_DUE!$D$2:$D$1000>=DATE(2025,2,22))*(RENT_DUE!$D$2:$D$1000<=DATE(2025,3,21))*RENT_DUE!$L$2:$L$1000), 0) -> 0 | H11: =IFERROR(SUMPRODUCT((RENT_RECEIVED!$B$2:$B$1000="LEASE-BH-F11-2025")*(RENT_RECEIVED!$E$2:$E$1000>=DATE(2025,2,22))*(RENT_RECEIVED!$E$2:$E$1000<=DATE(2025,3,21))*RENT_RECEIVED!$O$2:$O$1000), 0) -> 0 | I11: HIST-2025-03-1501 | J11: =IFERROR(SUMIFS(RENT_DUE!$L$2:$L$10000, RENT_DUE!$B$2:$B$10000, "LEASE-BH-F11-2025", RENT_DUE!$D$2:$D$10000, "<"&DATE(2025,2,22)), 0) - IFERROR(SUMIFS(RENT_RECEIVED!$O$2:$O$10000, RENT_RECEIVED!$B$2:$B$10000, "LEASE-BH-F11-2025", RENT_RECEIVED!$E$2:$E$10000, "<"&DATE(2025,2,22)), 0) -> 0 | K11: =G11 - H11 -> 0 | L11: =J11 + K11 -> 0 | M11: =H11 * 0.1500 -> 0 | N11: =H11 * 0.0000 -> 0 | O11: =ABS(M11 + N11) -> 0 | Q11: =SUMIFS(EXPENSES!E:E, EXPENSES!B:B, "LEASE-BH-F11-2025", EXPENSES!D:D, ">="&DATE(2025,2,22), EXPENSES!D:D, "<="&DATE(2025,3,21)) -> 0 | S11: =H11 - O11 - Q11 -> 0 | Y11: 5979.75 | Z11: =S11-Y11 -> 0 | AA11: PAID | AB11: MULTIPLE | AC11: 45981
A12: LEASE-BH-F13-2025 | B12: Flat 13 - 3 West Gate | C12: Achal (Delegated for Udayan) | D12: Mr Nathan Holland | E12: 45719 | F12: 3 | G12: =IFERROR(SUMPRODUCT((RENT_DUE!$B$2:$B$1000="LEASE-BH-F13-2025")*(RENT_DUE!$D$2:$D$1000>=DATE(2025,2,22))*(RENT_DUE!$D$2:$D$1000<=DATE(2025,3,21))*RENT_DUE!$L$2:$L$1000), 0) -> 0 | H12: =IFERROR(SUMPRODUCT((RENT_RECEIVED!$B$2:$B$1000="LEASE-BH-F13-2025")*(RENT_RECEIVED!$E$2:$E$1000>=DATE(2025,2,22))*(RENT_RECEIVED!$E$2:$E$1000<=DATE(2025,3,21))*RENT_RECEIVED!$O$2:$O$1000), 0) -> 0 | I12: HIST-2025-03-1501 | J12: =IFERROR(SUMIFS(RENT_DUE!$L$2:$L$10000, RENT_DUE!$B$2:$B$10000, "LEASE-BH-F13-2025", RENT_DUE!$D$2:$D$10000, "<"&DATE(2025,2,22)), 0) - IFERROR(SUMIFS(RENT_RECEIVED!$O$2:$O$10000, RENT_RECEIVED!$B$2:$B$10000, "LEASE-BH-F13-2025", RENT_RECEIVED!$E$2:$E$10000, "<"&DATE(2025,2,22)), 0) -> 0 | K12: =G12 - H12 -> 0 | L12: =J12 + K12 -> 0 | M12: =H12 * 0.1500 -> 0 | N12: =H12 * 0.0000 -> 0 | O12: =ABS(M12 + N12) -> 0 | Q12: =SUMIFS(EXPENSES!E:E, EXPENSES!B:B, "LEASE-BH-F13-2025", EXPENSES!D:D, ">="&DATE(2025,2,22), EXPENSES!D:D, "<="&DATE(2025,3,21)) -> 0 | S12: =H12 - O12 - Q12 -> 0 | Y12: 5440 | Z12: =S12-Y12 -> 0 | AA12: PAID | AB12: MULTIPLE | AC12: 45936
A13: LEASE-BH-F15-2025 | B13: Flat 15 - 3 West Gate | C13: Achal (Delegated for Udayan) | D13: Ms Lucy Cassell | E13: 45703 | F13: 15 | G13: =IFERROR(SUMPRODUCT((RENT_DUE!$B$2:$B$1000="LEASE-BH-F15-2025")*(RENT_DUE!$D$2:$D$1000>=DATE(2025,2,22))*(RENT_DUE!$D$2:$D$1000<=DATE(2025,3,21))*RENT_DUE!$L$2:$L$1000), 0) -> 0 | H13: =IFERROR(SUMPRODUCT((RENT_RECEIVED!$B$2:$B$1000="LEASE-BH-F15-2025")*(RENT_RECEIVED!$E$2:$E$1000>=DATE(2025,2,22))*(RENT_RECEIVED!$E$2:$E$1000<=DATE(2025,3,21))*RENT_RECEIVED!$O$2:$O$1000), 0) -> 0 | I13: HIST-2025-03-1501 | J13: =IFERROR(SUMIFS(RENT_DUE!$L$2:$L$10000, RENT_DUE!$B$2:$B$10000, "LEASE-BH-F15-2025", RENT_DUE!$D$2:$D$10000, "<"&DATE(2025,2,22)), 0) - IFERROR(SUMIFS(RENT_RECEIVED!$O$2:$O$10000, RENT_RECEIVED!$B$2:$B$10000, "LEASE-BH-F15-2025", RENT_RECEIVED!$E$2:$E$10000, "<"&DATE(2025,2,22)), 0) -> 0 | K13: =G13 - H13 -> 0 | L13: =J13 + K13 -> 0 | M13: =H13 * 0.1500 -> 0 | N13: =H13 * 0.0000 -> 0 | O13: =ABS(M13 + N13) -> 0 | Q13: =SUMIFS(EXPENSES!E:E, EXPENSES!B:B, "LEASE-BH-F15-2025", EXPENSES!D:D, ">="&DATE(2025,2,22), EXPENSES!D:D, "<="&DATE(2025,3,21)) -> 0 | S13: =H13 - O13 - Q13 -> 0 | Y13: 6170 | Z13: =S13-Y13 -> 0 | AA13: PAID | AB13: MULTIPLE | AC13: 45982
A14: LEASE-BH-F16-2025 | B14: Flat 16 - 3 West Gate | C14: Achal (Delegated for Udayan) | D14: Mr Riley Paul Beresford, Ms Gina Louise Judge | E14: 45726 | F14: 10 | G14: =IFERROR(SUMPRODUCT((RENT_DUE!$B$2:$B$1000="LEASE-BH-F16-2025")*(RENT_DUE!$D$2:$D$1000>=DATE(2025,2,22))*(RENT_DUE!$D$2:$D$1000<=DATE(2025,3,21))*RENT_DUE!$L$2:$L$1000), 0) -> 0 | H14: =IFERROR(SUMPRODUCT((RENT_RECEIVED!$B$2:$B$1000="LEASE-BH-F16-2025")*(RENT_RECEIVED!$E$2:$E$1000>=DATE(2025,2,22))*(RENT_RECEIVED!$E$2:$E$1000<=DATE(2025,3,21))*RENT_RECEIVED!$O$2:$O$1000), 0) -> 0 | I14: HIST-2025-03-1501 | J14: =IFERROR(SUMIFS(RENT_DUE!$L$2:$L$10000, RENT_DUE!$B$2:$B$10000, "LEASE-BH-F16-2025", RENT_DUE!$D$2:$D$10000, "<"&DATE(2025,2,22)), 0) - IFERROR(SUMIFS(RENT_RECEIVED!$O$2:$O$10000, RENT_RECEIVED!$B$2:$B$10000, "LEASE-BH-F16-2025", RENT_RECEIVED!$E$2:$E$10000, "<"&DATE(2025,2,22)), 0) -> 0 | K14: =G14 - H14 -> 0 | L14: =J14 + K14 -> 0 | M14: =H14 * 0.1500 -> 0 | N14: =H14 * 0.0000 -> 0 | O14: =ABS(M14 + N14) -> 0 | Q14: =SUMIFS(EXPENSES!E:E, EXPENSES!B:B, "LEASE-BH-F16-2025", EXPENSES!D:D, ">="&DATE(2025,2,22), EXPENSES!D:D, "<="&DATE(2025,3,21)) -> 0 | S14: =H14 - O14 - Q14 -> 0 | Y14: 3641.31 | Z14: =S14-Y14 -> 0 | AA14: PAID | AB14: MULTIPLE | AC14: 45891
A15: LEASE-BH-F17-2025 | B15: Flat 17 - 3 West Gate | C15: Achal (Delegated for Udayan) | D15: Mr Harsh Patel | E15: 45705 | F15: 17 | G15: =IFERROR(SUMPRODUCT((RENT_DUE!$B$2:$B$1000="LEASE-BH-F17-2025")*(RENT_DUE!$D$2:$D$1000>=DATE(2025,2,22))*(RENT_DUE!$D$2:$D$1000<=DATE(2025,3,21))*RENT_DUE!$L$2:$L$1000), 0) -> 0 | H15: =IFERROR(SUMPRODUCT((RENT_RECEIVED!$B$2:$B$1000="LEASE-BH-F17-2025")*(RENT_RECEIVED!$E$2:$E$1000>=DATE(2025,2,22))*(RENT_RECEIVED!$E$2:$E$1000<=DATE(2025,3,21))*RENT_RECEIVED!$O$2:$O$1000), 0) -> 0 | I15: HIST-2025-03-1501 | J15: =IFERROR(SUMIFS(RENT_DUE!$L$2:$L$10000, RENT_DUE!$B$2:$B$10000, "LEASE-BH-F17-2025", RENT_DUE!$D$2:$D$10000, "<"&DATE(2025,2,22)), 0) - IFERROR(SUMIFS(RENT_RECEIVED!$O$2:$O$10000, RENT_RECEIVED!$B$2:$B$10000, "LEASE-BH-F17-2025", RENT_RECEIVED!$E$2:$E$10000, "<"&DATE(2025,2,22)), 0) -> 0 | K15: =G15 - H15 -> 0 | L15: =J15 + K15 -> 0 | M15: =H15 * 0.1500 -> 0 | N15: =H15 * 0.0000 -> 0 | O15: =ABS(M15 + N15) -> 0 | Q15: =SUMIFS(EXPENSES!E:E, EXPENSES!B:B, "LEASE-BH-F17-2025", EXPENSES!D:D, ">="&DATE(2025,2,22), EXPENSES!D:D, "<="&DATE(2025,3,21)) -> 0 | S15: =H15 - O15 - Q15 -> 0 | Y15: 5800 | Z15: =S15-Y15 -> 0 | AA15: PAID | AB15: MULTIPLE | AC15: 45982
A16: LEASE-BH-F18-2025 | B16: Flat 18 - 3 West Gate | C16: Achal (Delegated for Udayan) | D16: Marie Dinko | E16: 45687 | F16: 30 | G16: =IFERROR(SUMPRODUCT((RENT_DUE!$B$2:$B$1000="LEASE-BH-F18-2025")*(RENT_DUE!$D$2:$D$1000>=DATE(2025,2,22))*(RENT_DUE!$D$2:$D$1000<=DATE(2025,3,21))*RENT_DUE!$L$2:$L$1000), 0) -> 0 | H16: =IFERROR(SUMPRODUCT((RENT_RECEIVED!$B$2:$B$1000="LEASE-BH-F18-2025")*(RENT_RECEIVED!$E$2:$E$1000>=DATE(2025,2,22))*(RENT_RECEIVED!$E$2:$E$1000<=DATE(2025,3,21))*RENT_RECEIVED!$O$2:$O$1000), 0) -> 0 | I16: HIST-2025-03-1501 | J16: =IFERROR(SUMIFS(RENT_DUE!$L$2:$L$10000, RENT_DUE!$B$2:$B$10000, "LEASE-BH-F18-2025", RENT_DUE!$D$2:$D$10000, "<"&DATE(2025,2,22)), 0) - IFERROR(SUMIFS(RENT_RECEIVED!$O$2:$O$10000, RENT_RECEIVED!$B$2:$B$10000, "LEASE-BH-F18-2025", RENT_RECEIVED!$E$2:$E$10000, "<"&DATE(2025,2,22)), 0) -> 0 | K16: =G16 - H16 -> 0 | L16: =J16 + K16 -> 0 | M16: =H16 * 0.1500 -> 0 | N16: =H16 * 0.0000 -> 0 | O16: =ABS(M16 + N16) -> 0 | Q16: =SUMIFS(EXPENSES!E:E, EXPENSES!B:B, "LEASE-BH-F18-2025", EXPENSES!D:D, ">="&DATE(2025,2,22), EXPENSES!D:D, "<="&DATE(2025,3,21)) -> 0 | S16: =H16 - O16 - Q16 -> 0 | Y16: 2044.25 | Z16: =S16-Y16 -> 0 | AA16: PAID | AB16: MULTIPLE | AC16: 45804
A17: LEASE-BH-F19-2025 | B17: Flat 19 - 3 West Gate | C17: Achal (Delegated for Udayan) | D17: Mr Joshua Banks, Miss Layla Middlemass | E17: 45730 | F17: 14 | G17: =IFERROR(SUMPRODUCT((RENT_DUE!$B$2:$B$1000="LEASE-BH-F19-2025")*(RENT_DUE!$D$2:$D$1000>=DATE(2025,2,22))*(RENT_DUE!$D$2:$D$1000<=DATE(2025,3,21))*RENT_DUE!$L$2:$L$1000), 0) -> 0 | H17: =IFERROR(SUMPRODUCT((RENT_RECEIVED!$B$2:$B$1000="LEASE-BH-F19-2025")*(RENT_RECEIVED!$E$2:$E$1000>=DATE(2025,2,22))*(RENT_RECEIVED!$E$2:$E$1000<=DATE(2025,3,21))*RENT_RECEIVED!$O$2:$O$1000), 0) -> 0 | I17: HIST-2025-03-1501 | J17: =IFERROR(SUMIFS(RENT_DUE!$L$2:$L$10000, RENT_DUE!$B$2:$B$10000, "LEASE-BH-F19-2025", RENT_DUE!$D$2:$D$10000, "<"&DATE(2025,2,22)), 0) - IFERROR(SUMIFS(RENT_RECEIVED!$O$2:$O$10000, RENT_RECEIVED!$B$2:$B$10000, "LEASE-BH-F19-2025", RENT_RECEIVED!$E$2:$E$10000, "<"&DATE(2025,2,22)), 0) -> 0 | K17: =G17 - H17 -> 0 | L17: =J17 + K17 -> 0 | M17: =H17 * 0.1500 -> 0 | N17: =H17 * 0.0000 -> 0 | O17: =ABS(M17 + N17) -> 0 | Q17: =SUMIFS(EXPENSES!E:E, EXPENSES!B:B, "LEASE-BH-F19-2025", EXPENSES!D:D, ">="&DATE(2025,2,22), EXPENSES!D:D, "<="&DATE(2025,3,21)) -> 0 | S17: =H17 - O17 - Q17 -> 0 | Y17: 2888.3 | Z17: =S17-Y17 -> 0 | AA17: PAID | AB17: MULTIPLE | AC17: 45846
A18: LEASE-BH-F20-2025 | B18: Flat 20 - 3 West Gate | C18: Achal (Delegated for Udayan) | D18: Mr James Kay | E18: 45732 | F18: 16 | G18: =IFERROR(SUMPRODUCT((RENT_DUE!$B$2:$B$1000="LEASE-BH-F20-2025")*(RENT_DUE!$D$2:$D$1000>=DATE(2025,2,22))*(RENT_DUE!$D$2:$D$1000<=DATE(2025,3,21))*RENT_DUE!$L$2:$L$1000), 0) -> 0 | H18: =IFERROR(SUMPRODUCT((RENT_RECEIVED!$B$2:$B$1000="LEASE-BH-F20-2025")*(RENT_RECEIVED!$E$2:$E$1000>=DATE(2025,2,22))*(RENT_RECEIVED!$E$2:$E$1000<=DATE(2025,3,21))*RENT_RECEIVED!$O$2:$O$1000), 0) -> 0 | I18: HIST-2025-03-1501 | J18: =IFERROR(SUMIFS(RENT_DUE!$L$2:$L$10000, RENT_DUE!$B$2:$B$10000, "LEASE-BH-F20-2025", RENT_DUE!$D$2:$D$10000, "<"&DATE(2025,2,22)), 0) - IFERROR(SUMIFS(RENT_RECEIVED!$O$2:$O$10000, RENT_RECEIVED!$B$2:$B$10000, "LEASE-BH-F20-2025", RENT_RECEIVED!$E$2:$E$10000, "<"&DATE(2025,2,22)), 0) -> 0 | K18: =G18 - H18 -> 0 | L18: =J18 + K18 -> 0 | M18: =H18 * 0.1500 -> 0 | N18: =H18 * 0.0000 -> 0 | O18: =ABS(M18 + N18) -> 0 | Q18: =SUMIFS(EXPENSES!E:E, EXPENSES!B:B, "LEASE-BH-F20-2025", EXPENSES!D:D, ">="&DATE(2025,2,22), EXPENSES!D:D, "<="&DATE(2025,3,21)) -> 0 | S18: =H18 - O18 - Q18 -> 0 | Y18: 5255 | Z18: =S18-Y18 -> 0 | AA18: PAID | AB18: MULTIPLE | AC18: 45982
A19: LEASE-BH-F21-2025 | B19: Flat 21 - 3 West Gate | C19: Achal (Delegated for Udayan) | D19: Mr Felwin Francis | E19: 45687 | F19: 30 | G19: =IFERROR(SUMPRODUCT((RENT_DUE!$B$2:$B$1000="LEASE-BH-F21-2025")*(RENT_DUE!$D$2:$D$1000>=DATE(2025,2,22))*(RENT_DUE!$D$2:$D$1000<=DATE(2025,3,21))*RENT_DUE!$L$2:$L$1000), 0) -> 0 | H19: =IFERROR(SUMPRODUCT((RENT_RECEIVED!$B$2:$B$1000="LEASE-BH-F21-2025")*(RENT_RECEIVED!$E$2:$E$1000>=DATE(2025,2,22))*(RENT_RECEIVED!$E$2:$E$1000<=DATE(2025,3,21))*RENT_RECEIVED!$O$2:$O$1000), 0) -> 0 | I19: HIST-2025-03-1501 | J19: =IFERROR(SUMIFS(RENT_DUE!$L$2:$L$10000, RENT_DUE!$B$2:$B$10000, "LEASE-BH-F21-2025", RENT_DUE!$D$2:$D$10000, "<"&DATE(2025,2,22)), 0) - IFERROR(SUMIFS(RENT_RECEIVED!$O$2:$O$10000, RENT_RECEIVED!$B$2:$B$10000, "LEASE-BH-F21-2025", RENT_RECEIVED!$E$2:$E$10000, "<"&DATE(2025,2,22)), 0) -> 0 | K19: =G19 - H19 -> 0 | L19: =J19 + K19 -> 0 | M19: =H19 * 0.1500 -> 0 | N19: =H19 * 0.0000 -> 0 | O19: =ABS(M19 + N19) -> 0 | Q19: =SUMIFS(EXPENSES!E:E, EXPENSES!B:B, "LEASE-BH-F21-2025", EXPENSES!D:D, ">="&DATE(2025,2,22), EXPENSES!D:D, "<="&DATE(2025,3,21)) -> 0 | S19: =H19 - O19 - Q19 -> 0 | Y19: 6637.5 | Z19: =S19-Y19 -> 0 | AA19: PAID | AB19: MULTIPLE | AC19: 45982
A20: LEASE-BH-F22-2025 | B20: Flat 22 - 3 West Gate | C20: Achal (Delegated for Udayan) | D20: Mr Brian Lowe | E20: 45717 | F20: 1 | G20: =IFERROR(SUMPRODUCT((RENT_DUE!$B$2:$B$1000="LEASE-BH-F22-2025")*(RENT_DUE!$D$2:$D$1000>=DATE(2025,2,22))*(RENT_DUE!$D$2:$D$1000<=DATE(2025,3,21))*RENT_DUE!$L$2:$L$1000), 0) -> 0 | H20: =IFERROR(SUMPRODUCT((RENT_RECEIVED!$B$2:$B$1000="LEASE-BH-F22-2025")*(RENT_RECEIVED!$E$2:$E$1000>=DATE(2025,2,22))*(RENT_RECEIVED!$E$2:$E$1000<=DATE(2025,3,21))*RENT_RECEIVED!$O$2:$O$1000), 0) -> 0 | I20: HIST-2025-03-1501 | J20: =IFERROR(SUMIFS(RENT_DUE!$L$2:$L$10000, RENT_DUE!$B$2:$B$10000, "LEASE-BH-F22-2025", RENT_DUE!$D$2:$D$10000, "<"&DATE(2025,2,22)), 0) - IFERROR(SUMIFS(RENT_RECEIVED!$O$2:$O$10000, RENT_RECEIVED!$B$2:$B$10000, "LEASE-BH-F22-2025", RENT_RECEIVED!$E$2:$E$10000, "<"&DATE(2025,2,22)), 0) -> 0 | K20: =G20 - H20 -> 0 | L20: =J20 + K20 -> 0 | M20: =H20 * 0.1500 -> 0 | N20: =H20 * 0.0000 -> 0 | O20: =ABS(M20 + N20) -> 0 | Q20: =SUMIFS(EXPENSES!E:E, EXPENSES!B:B, "LEASE-BH-F22-2025", EXPENSES!D:D, ">="&DATE(2025,2,22), EXPENSES!D:D, "<="&DATE(2025,3,21)) -> 0 | S20: =H20 - O20 - Q20 -> 0 | Y20: 5661 | Z20: =S20-Y20 -> 0 | AA20: PAID | AB20: MULTIPLE | AC20: 45982
A21: LEASE-BH-F24-2025 | B21: Flat 24 - 3 West Gate | C21: Achal (Delegated for Udayan) | D21: Mr Ethan Maloney, Miss Soraya Fearon | E21: 45700 | F21: 12 | G21: =IFERROR(SUMPRODUCT((RENT_DUE!$B$2:$B$1000="LEASE-BH-F24-2025")*(RENT_DUE!$D$2:$D$1000>=DATE(2025,2,22))*(RENT_DUE!$D$2:$D$1000<=DATE(2025,3,21))*RENT_DUE!$L$2:$L$1000), 0) -> 0 | H21: =IFERROR(SUMPRODUCT((RENT_RECEIVED!$B$2:$B$1000="LEASE-BH-F24-2025")*(RENT_RECEIVED!$E$2:$E$1000>=DATE(2025,2,22))*(RENT_RECEIVED!$E$2:$E$1000<=DATE(2025,3,21))*RENT_RECEIVED!$O$2:$O$1000), 0) -> 0 | I21: HIST-2025-03-1501 | J21: =IFERROR(SUMIFS(RENT_DUE!$L$2:$L$10000, RENT_DUE!$B$2:$B$10000, "LEASE-BH-F24-2025", RENT_DUE!$D$2:$D$10000, "<"&DATE(2025,2,22)), 0) - IFERROR(SUMIFS(RENT_RECEIVED!$O$2:$O$10000, RENT_RECEIVED!$B$2:$B$10000, "LEASE-BH-F24-2025", RENT_RECEIVED!$E$2:$E$10000, "<"&DATE(2025,2,22)), 0) -> 0 | K21: =G21 - H21 -> 0 | L21: =J21 + K21 -> 0 | M21: =H21 * 0.1500 -> 0 | N21: =H21 * 0.0000 -> 0 | O21: =ABS(M21 + N21) -> 0 | Q21: =SUMIFS(EXPENSES!E:E, EXPENSES!B:B, "LEASE-BH-F24-2025", EXPENSES!D:D, ">="&DATE(2025,2,22), EXPENSES!D:D, "<="&DATE(2025,3,21)) -> 0 | S21: =H21 - O21 - Q21 -> 0 | Y21: 6765 | Z21: =S21-Y21 -> 0 | AA21: PAID | AB21: MULTIPLE | AC21: 45982
A22: LEASE-BH-F26-2025 | B22: Flat 26 - 3 West Gate | C22: Achal (Delegated for Udayan) | D22: Mr Louis Scotting | E22: 45730 | F22: 14 | G22: =IFERROR(SUMPRODUCT((RENT_DUE!$B$2:$B$1000="LEASE-BH-F26-2025")*(RENT_DUE!$D$2:$D$1000>=DATE(2025,2,22))*(RENT_DUE!$D$2:$D$1000<=DATE(2025,3,21))*RENT_DUE!$L$2:$L$1000), 0) -> 0 | H22: =IFERROR(SUMPRODUCT((RENT_RECEIVED!$B$2:$B$1000="LEASE-BH-F26-2025")*(RENT_RECEIVED!$E$2:$E$1000>=DATE(2025,2,22))*(RENT_RECEIVED!$E$2:$E$1000<=DATE(2025,3,21))*RENT_RECEIVED!$O$2:$O$1000), 0) -> 0 | I22: HIST-2025-03-1501 | J22: =IFERROR(SUMIFS(RENT_DUE!$L$2:$L$10000, RENT_DUE!$B$2:$B$10000, "LEASE-BH-F26-2025", RENT_DUE!$D$2:$D$10000, "<"&DATE(2025,2,22)), 0) - IFERROR(SUMIFS(RENT_RECEIVED!$O$2:$O$10000, RENT_RECEIVED!$B$2:$B$10000, "LEASE-BH-F26-2025", RENT_RECEIVED!$E$2:$E$10000, "<"&DATE(2025,2,22)), 0) -> 0 | K22: =G22 - H22 -> 0 | L22: =J22 + K22 -> 0 | M22: =H22 * 0.1500 -> 0 | N22: =H22 * 0.0000 -> 0 | O22: =ABS(M22 + N22) -> 0 | Q22: =SUMIFS(EXPENSES!E:E, EXPENSES!B:B, "LEASE-BH-F26-2025", EXPENSES!D:D, ">="&DATE(2025,2,22), EXPENSES!D:D, "<="&DATE(2025,3,21)) -> 0 | S22: =H22 - O22 - Q22 -> 0 | Y22: 5163.75 | Z22: =S22-Y22 -> 0 | AA22: PAID | AB22: MULTIPLE | AC22: 45992
A23: LEASE-BH-F27-2025 | B23: Flat 27 - 3 West Gate | C23: Achal (Delegated for Udayan) | D23: Miss Sophie Murray | E23: 45716 | F23: 30 | G23: =IFERROR(SUMPRODUCT((RENT_DUE!$B$2:$B$1000="LEASE-BH-F27-2025")*(RENT_DUE!$D$2:$D$1000>=DATE(2025,2,22))*(RENT_DUE!$D$2:$D$1000<=DATE(2025,3,21))*RENT_DUE!$L$2:$L$1000), 0) -> 0 | H23: =IFERROR(SUMPRODUCT((RENT_RECEIVED!$B$2:$B$1000="LEASE-BH-F27-2025")*(RENT_RECEIVED!$E$2:$E$1000>=DATE(2025,2,22))*(RENT_RECEIVED!$E$2:$E$1000<=DATE(2025,3,21))*RENT_RECEIVED!$O$2:$O$1000), 0) -> 0 | I23: HIST-2025-03-1501 | J23: =IFERROR(SUMIFS(RENT_DUE!$L$2:$L$10000, RENT_DUE!$B$2:$B$10000, "LEASE-BH-F27-2025", RENT_DUE!$D$2:$D$10000, "<"&DATE(2025,2,22)), 0) - IFERROR(SUMIFS(RENT_RECEIVED!$O$2:$O$10000, RENT_RECEIVED!$B$2:$B$10000, "LEASE-BH-F27-2025", RENT_RECEIVED!$E$2:$E$10000, "<"&DATE(2025,2,22)), 0) -> 0 | K23: =G23 - H23 -> 0 | L23: =J23 + K23 -> 0 | M23: =H23 * 0.1500 -> 0 | N23: =H23 * 0.0000 -> 0 | O23: =ABS(M23 + N23) -> 0 | Q23: =SUMIFS(EXPENSES!E:E, EXPENSES!B:B, "LEASE-BH-F27-2025", EXPENSES!D:D, ">="&DATE(2025,2,22), EXPENSES!D:D, "<="&DATE(2025,3,21)) -> 0 | S23: =H23 - O23 - Q23 -> 0 | Y23: 5355 | Z23: =S23-Y23 -> 0 | AA23: PAID | AB23: MULTIPLE | AC23: 45982
A24: LEASE-BH-F29-2025 | B24: Flat 29 - 3 West Gate | C24: Achal (Delegated for Udayan) | D24: Mrs Margaret Fritchley | E24: 45715 | F24: 27 | G24: =IFERROR(SUMPRODUCT((RENT_DUE!$B$2:$B$1000="LEASE-BH-F29-2025")*(RENT_DUE!$D$2:$D$1000>=DATE(2025,2,22))*(RENT_DUE!$D$2:$D$1000<=DATE(2025,3,21))*RENT_DUE!$L$2:$L$1000), 0) -> 0 | H24: =IFERROR(SUMPRODUCT((RENT_RECEIVED!$B$2:$B$1000="LEASE-BH-F29-2025")*(RENT_RECEIVED!$E$2:$E$1000>=DATE(2025,2,22))*(RENT_RECEIVED!$E$2:$E$1000<=DATE(2025,3,21))*RENT_RECEIVED!$O$2:$O$1000), 0) -> 0 | I24: HIST-2025-03-1501 | J24: =IFERROR(SUMIFS(RENT_DUE!$L$2:$L$10000, RENT_DUE!$B$2:$B$10000, "LEASE-BH-F29-2025", RENT_DUE!$D$2:$D$10000, "<"&DATE(2025,2,22)), 0) - IFERROR(SUMIFS(RENT_RECEIVED!$O$2:$O$10000, RENT_RECEIVED!$B$2:$B$10000, "LEASE-BH-F29-2025", RENT_RECEIVED!$E$2:$E$10000, "<"&DATE(2025,2,22)), 0) -> 0 | K24: =G24 - H24 -> 0 | L24: =J24 + K24 -> 0 | M24: =H24 * 0.1500 -> 0 | N24: =H24 * 0.0000 -> 0 | O24: =ABS(M24 + N24) -> 0 | Q24: =SUMIFS(EXPENSES!E:E, EXPENSES!B:B, "LEASE-BH-F29-2025", EXPENSES!D:D, ">="&DATE(2025,2,22), EXPENSES!D:D, "<="&DATE(2025,3,21)) -> 0 | S24: =H24 - O24 - Q24 -> 0 | Y24: 5541 | Z24: =S24-Y24 -> 0 | AA24: PAID | AB24: MULTIPLE | AC24: 45982
A25: LEASE-BH-F30-2025 | B25: Flat 30 - 3 West Gate | C25: Achal (Delegated for Udayan) | D25: Mr Joel Bryan | E25: 45722 | F25: 6 | G25: =IFERROR(SUMPRODUCT((RENT_DUE!$B$2:$B$1000="LEASE-BH-F30-2025")*(RENT_DUE!$D$2:$D$1000>=DATE(2025,2,22))*(RENT_DUE!$D$2:$D$1000<=DATE(2025,3,21))*RENT_DUE!$L$2:$L$1000), 0) -> 0 | H25: =IFERROR(SUMPRODUCT((RENT_RECEIVED!$B$2:$B$1000="LEASE-BH-F30-2025")*(RENT_RECEIVED!$E$2:$E$1000>=DATE(2025,2,22))*(RENT_RECEIVED!$E$2:$E$1000<=DATE(2025,3,21))*RENT_RECEIVED!$O$2:$O$1000), 0) -> 0 | I25: HIST-2025-03-1501 | J25: =IFERROR(SUMIFS(RENT_DUE!$L$2:$L$10000, RENT_DUE!$B$2:$B$10000, "LEASE-BH-F30-2025", RENT_DUE!$D$2:$D$10000, "<"&DATE(2025,2,22)), 0) - IFERROR(SUMIFS(RENT_RECEIVED!$O$2:$O$10000, RENT_RECEIVED!$B$2:$B$10000, "LEASE-BH-F30-2025", RENT_RECEIVED!$E$2:$E$10000, "<"&DATE(2025,2,22)), 0) -> 0 | K25: =G25 - H25 -> 0 | L25: =J25 + K25 -> 0 | M25: =H25 * 0.1500 -> 0 | N25: =H25 * 0.0000 -> 0 | O25: =ABS(M25 + N25) -> 0 | Q25: =SUMIFS(EXPENSES!E:E, EXPENSES!B:B, "LEASE-BH-F30-2025", EXPENSES!D:D, ">="&DATE(2025,2,22), EXPENSES!D:D, "<="&DATE(2025,3,21)) -> 0 | S25: =H25 - O25 - Q25 -> 0 | Y25: 5032 | Z25: =S25-Y25 -> 0 | AA25: PAID | AB25: MULTIPLE | AC25: 45992
A26: LEASE-KH-F-2024 | B26: Apartment F - Knighton Hayes Manor | C26: Achal (Delegated for Udayan) | D26: Mr Riaz Hamid, Ismat Tarr-Hamid | E26: 45648 | F26: 22 | G26: =IFERROR(SUMPRODUCT((RENT_DUE!$B$2:$B$1000="LEASE-KH-F-2024")*(RENT_DUE!$D$2:$D$1000>=DATE(2025,2,22))*(RENT_DUE!$D$2:$D$1000<=DATE(2025,3,21))*RENT_DUE!$L$2:$L$1000), 0) -> 0 | H26: =IFERROR(SUMPRODUCT((RENT_RECEIVED!$B$2:$B$1000="LEASE-KH-F-2024")*(RENT_RECEIVED!$E$2:$E$1000>=DATE(2025,2,22))*(RENT_RECEIVED!$E$2:$E$1000<=DATE(2025,3,21))*RENT_RECEIVED!$O$2:$O$1000), 0) -> 0 | I26: HIST-2025-03-1501, HIST-2025-03-1502 | J26: =IFERROR(SUMIFS(RENT_DUE!$L$2:$L$10000, RENT_DUE!$B$2:$B$10000, "LEASE-KH-F-2024", RENT_DUE!$D$2:$D$10000, "<"&DATE(2025,2,22)), 0) - IFERROR(SUMIFS(RENT_RECEIVED!$O$2:$O$10000, RENT_RECEIVED!$B$2:$B$10000, "LEASE-KH-F-2024", RENT_RECEIVED!$E$2:$E$10000, "<"&DATE(2025,2,22)), 0) -> 0 | K26: =G26 - H26 -> 0 | L26: =J26 + K26 -> 0 | M26: =H26 * 0.1000 -> 0 | N26: =H26 * 0.0000 -> 0 | O26: =ABS(M26 + N26) -> 0 | Q26: =SUMIFS(EXPENSES!E:E, EXPENSES!B:B, "LEASE-KH-F-2024", EXPENSES!D:D, ">="&DATE(2025,2,22), EXPENSES!D:D, "<="&DATE(2025,3,21)) -> 0 | S26: =H26 - O26 - Q26 -> 0 | Y26: 12150 | Z26: =S26-Y26 -> 0 | AA26: PAID | AB26: MULTIPLE | AC26: 45982
A27: BODEN-BLOCK-2025 | B27: Boden House Block - Block Property | C27: Achal (Delegated for Udayan) | D27: Prestvale Properties Limited | E27: 45717 | F27: 1 | G27: =IFERROR(SUMPRODUCT((RENT_DUE!$B$2:$B$1000="BODEN-BLOCK-2025")*(RENT_DUE!$D$2:$D$1000>=DATE(2025,2,22))*(RENT_DUE!$D$2:$D$1000<=DATE(2025,3,21))*RENT_DUE!$L$2:$L$1000), 0) -> 0 | H27: =IFERROR(SUMPRODUCT((RENT_RECEIVED!$B$2:$B$1000="BODEN-BLOCK-2025")*(RENT_RECEIVED!$E$2:$E$1000>=DATE(2025,2,22))*(RENT_RECEIVED!$E$2:$E$1000<=DATE(2025,3,21))*RENT_RECEIVED!$O$2:$O$1000), 0) -> 0 | J27: =IFERROR(SUMIFS(RENT_DUE!$L$2:$L$10000, RENT_DUE!$B$2:$B$10000, "BODEN-BLOCK-2025", RENT_DUE!$D$2:$D$10000, "<"&DATE(2025,2,22)), 0) - IFERROR(SUMIFS(RENT_RECEIVED!$O$2:$O$10000, RENT_RECEIVED!$B$2:$B$10000, "BODEN-BLOCK-2025", RENT_RECEIVED!$E$2:$E$10000, "<"&DATE(2025,2,22)), 0) -> 0 | K27: =G27 - H27 -> 0 | L27: =J27 + K27 -> 0 | M27: =H27 * 0.0000 -> 0 | N27: =H27 * 0.0500 -> 0 | O27: =ABS(M27 + N27) -> 0 | P27: HIST-2025-03-1501 | Q27: =SUMIFS(EXPENSES!E:E, EXPENSES!B:B, "BODEN-BLOCK-2025", EXPENSES!D:D, ">="&DATE(2025,2,22), EXPENSES!D:D, "<="&DATE(2025,3,21)) -> 0 | S27: =H27 - O27 - Q27 -> 0 | T27: Boden House NG10 | U27: =IFERROR(SUMIFS(PROPERTY_ACCOUNT!D:D, PROPERTY_ACCOUNT!A:A, T27, PROPERTY_ACCOUNT!B:B, "opening"), 0) -> 0 | V27: =IFERROR(SUMIFS(PROPERTY_ACCOUNT!D:D, PROPERTY_ACCOUNT!A:A, T27, PROPERTY_ACCOUNT!B:B, "in"), 0) -> 0 | W27: =IFERROR(SUMIFS(PROPERTY_ACCOUNT!D:D, PROPERTY_ACCOUNT!A:A, T27, PROPERTY_ACCOUNT!B:B, "out"), 0) -> 0 | X27: =U27 + V27 - W27 -> 0 | Y27: 0 | Z27: =S27-Y27 -> 0 | AA27: PAID | AB27: MULTIPLE | AC27: 45993
A28: TOTALS | G28: =SUM(G2:G27) -> 0 | H28: =SUM(H2:H27) -> 0 | J28: =SUM(J2:J27) -> 0 | K28: =SUM(K2:K27) -> 0 | L28: =SUM(L2:L27) -> 0 | M28: =SUM(M2:M27) -> 0 | N28: =SUM(N2:N27) -> 0 | O28: =SUM(O2:O27) -> 0 | Q28: =SUM(Q2:Q27) -> 0 | S28: =SUM(S2:S27) -> 0 | U28: =SUM(U2:U27) -> 0 | V28: =SUM(V2:V27) -> 0 | W28: =SUM(W2:W27) -> 0 | X28: =SUM(X2:X27) -> 0
A30: PAYMENT RECONCILIATION
A31: Period: 2025-02-22 to 2025-03-21
A33: BROUGHT FORWARD (items from prior periods paid this period)
A34: Prior Period Income:
A35: 2025-02-15 | Flat 21 - 3 West Gate | rent | B35: 488.5
A36: 2025-02-17 | Flat 5 - 3 West Gate | rent | B36: 629
A37: 2025-02-19 | Flat 15 - 3 West Gate | rent | B37: 398.5
A38: 2025-02-19 | Flat 7 - 3 West Gate | rent | B38: 595
A39: 2025-01-28 | Apartment F - Knighton Hayes Manor | rent | B39: 1012.5
A40: 2025-01-28 | Apartment F - Knighton Hayes Manor | rent | B40: 1012.5
A41: 2025-02-15 | Flat 18 - 3 West Gate | rent | B41: 629
A42: 2025-02-15 | Flat 21 - 3 West Gate | rent | B42: 187.25
A43: Prior Period Income Total (8 items): | B43: 4952.25
A44: Prior Period Expenses: None
A45: NET B/F (Income - Expenses): | B45: 4952.25
A47: THIS PERIOD ACTIVITY (see transactions above for details)
A48: Period Income (0 transactions) | B48: 0
A49: Period Expenses (0 transactions) | B49: 0
A50: Net Activity (Income - Expenses): | B50: 0
A52: PAYMENTS MADE THIS PERIOD
A53: HIST-2025-03-1472 (2025-03-06) | B53: 2111
A54: Covers: 4 income (£2111.00) = £2111.00
A55: HIST-2025-03-1473 (2025-03-06) | B55: 1012.5
A56: Covers: 1 income (£1012.50) = £1012.50
A57: HIST-2025-03-1474 (2025-03-06) | B57: 1012.5
A58: Covers: 1 income (£1012.50) = £1012.50
A59: HIST-2025-03-1475 (2025-03-06) | B59: 816.25
A60: Covers: 2 income (£816.25) = £816.25
A61: Total Payments Made: | B61: 4952.25
A62: (See PAYMENT_ALLOCATIONS sheet for full details)
A64: SUMMARY
A65: Total Allocated (Income - Expenses): | B65: 4952.25
A66: Total Payments Made: | B66: 4952.25
A67: Unallocated Payment Amounts: | B67: 0
A69: Check: Allocated 4952.25 + Unallocated 0.00 = 4952.25 vs Payments 4952.25

Sheet Mar 22 - Apr 21, 2025
A1: lease_reference | B1: property_name | C1: customer_name | D1: tenant_name | E1: lease_start_date | F1: rent_due_day | G1: rent_due | H1: rent_received | I1: rent_batch | J1: opening_balance | K1: period_arrears | L1: closing_balance | M1: management_fee | N1: service_fee | O1: total_commission | P1: commission_batch | Q1: total_expenses | R1: expenses_batch | S1: net_to_owner | T1: block_name | U1: property_account_opening | V1: property_account_in | W1: property_account_out | X1: property_account_closing | Y1: allocated_amount | Z1: variance | AA1: allocation_status | AB1: batch_id | AC1: paid_date
A2: LEASE-BH-F1-2025 | B2: Flat 1 - 3 West Gate | C2: Achal (Delegated for Udayan) | D2: Ms Oleksandra Smoliarenko, Mr Illia Halii | E2: 45715 | F2: 27 | G2: =IFERROR(SUMPRODUCT((RENT_DUE!$B$2:$B$1000="LEASE-BH-F1-2025")*(RENT_DUE!$D$2:$D$1000>=DATE(2025,3,22))*(RENT_DUE!$D$2:$D$1000<=DATE(2025,4,21))*RENT_DUE!$L$2:$L$1000), 0) -> 0 | H2: =IFERROR(SUMPRODUCT((RENT_RECEIVED!$B$2:$B$1000="LEASE-BH-F1-2025")*(RENT_RECEIVED!$E$2:$E$1000>=DATE(2025,3,22))*(RENT_RECEIVED!$E$2:$E$1000<=DATE(2025,4,21))*RENT_RECEIVED!$O$2:$O$1000), 0) -> 0 | I2: HIST-2025-04-1532 | J2: =IFERROR(SUMIFS(RENT_DUE!$L$2:$L$10000, RENT_DUE!$B$2:$B$10000, "LEASE-BH-F1-2025", RENT_DUE!$D$2:$D$10000, "<"&DATE(2025,3,22)), 0) - IFERROR(SUMIFS(RENT_RECEIVED!$O$2:$O$10000, RENT_RECEIVED!$B$2:$B$10000, "LEASE-BH-F1-2025", RENT_RECEIVED!$E$2:$E$10000, "<"&DATE(2025,3,22)), 0) -> 0 | K2: =G2 - H2 -> 0 | L2: =J2 + K2 -> 0 | M2: =H2 * 0.1500 -> 0 | N2: =H2 * 0.0000 -> 0 | O2: =ABS(M2 + N2) -> 0 | Q2: =SUMIFS(EXPENSES!E:E, EXPENSES!B:B, "LEASE-BH-F1-2025", EXPENSES!D:D, ">="&DATE(2025,3,22), EXPENSES!D:D, "<="&DATE(2025,4,21)) -> 0 | S2: =H2 - O2 - Q2 -> 0 | Y2: 5985.52 | Z2: =S2-Y2 -> 0 | AA2: PAID | AB2: MULTIPLE | AC2: 45992
A3: LEASE-BH-F2-2025 | B3: Flat 2 - 3 West Gate | C3: Achal (Delegated for Udayan) | D3: Mr Mustafa Al Bayat, Mrs Gulala Al - Zangana | E3: 45715 | F3: 27 | G3: =IFERROR(SUMPRODUCT((RENT_DUE!$B$2:$B$1000="LEASE-BH-F2-2025")*(RENT_DUE!$D$2:$D$1000>=DATE(2025,3,22))*(RENT_DUE!$D$2:$D$1000<=DATE(2025,4,21))*RENT_DUE!$L$2:$L$1000), 0) -> 0 | H3: =IFERROR(SUMPRODUCT((RENT_RECEIVED!$B$2:$B$1000="LEASE-BH-F2-2025")*(RENT_RECEIVED!$E$2:$E$1000>=DATE(2025,3,22))*(RENT_RECEIVED!$E$2:$E$1000<=DATE(2025,4,21))*RENT_RECEIVED!$O$2:$O$1000), 0) -> 0 | I3: HIST-2025-04-1532 | J3: =IFERROR(SUMIFS(RENT_DUE!$L$2:$L$10000, RENT_DUE!$B$2:$B$10000, "LEASE-BH-F2-2025", RENT_DUE!$D$2:$D$10000, "<"&DATE(2025,3,22)), 0) - IFERROR(SUMIFS(RENT_RECEIVED!$O$2:$O$10000, RENT_RECEIVED!$B$2:$B$10000, "LEASE-BH-F2-2025", RENT_RECEIVED!$E$2:$E$10000, "<"&DATE(2025,3,22)), 0) -> 0 | K3: =G3 - H3 -> 0 | L3: =J3 + K3 -> 0 | M3: =H3 * 0.1500 -> 0 | N3: =H3 * 0.0000 -> 0 | O3: =ABS(M3 + N3) -> 0 | Q3: =SUMIFS(EXPENSES!E:E, EXPENSES!B:B, "LEASE-BH-F2-2025", EXPENSES!D:D, ">="&DATE(2025,3,22), EXPENSES!D:D, "<="&DATE(2025,4,21)) -> 0 | S3: =H3 - O3 - Q3 -> 0 | Y3: 5661 | Z3: =S3-Y3 -> 0 | AA3: PAID | AB3: MULTIPLE | AC3: 45992
A4: LEASE-BH-F3-2025 | B4: Flat 3 - 3 West Gate | C4: Achal (Delegated for Udayan) | D4: Mr Tracy Whyte | E4: 45727 | F4: 11 | G4: =IFERROR(SUMPRODUCT((RENT_DUE!$B$2:$B$1000="LEASE-BH-F3-2025")*(RENT_DUE!$D$2:$D$1000>=DATE(2025,3,22))*(RENT_DUE!$D$2:$D$1000<=DATE(2025,4,21))*RENT_DUE!$L$2:$L$1000), 0) -> 0 | H4: =IFERROR(SUMPRODUCT((RENT_RECEIVED!$B$2:$B$1000="LEASE-BH-F3-2025")*(RENT_RECEIVED!$E$2:$E$1000>=DATE(2025,3,22))*(RENT_RECEIVED!$E$2:$E$1000<=DATE(2025,4,21))*RENT_RECEIVED!$O$2:$O$1000), 0) -> 0 | I4: HIST-2025-04-1532 | J4: =IFERROR(SUMIFS(RENT_DUE!$L$2:$L$10000, RENT_DUE!$B$2:$B$10000, "LEASE-BH-F3-2025", RENT_DUE!$D$2:$D$10000, "<"&DATE(2025,3,22)), 0) - IFERROR(SUMIFS(RENT_RECEIVED!$O$2:$O$10000, RENT_RECEIVED!$B$2:$B$10000, "LEASE-BH-F3-2025", RENT_RECEIVED!$E$2:$E$10000, "<"&DATE(2025,3,22)), 0) -> 0 | K4: =G4 - H4 -> 0 | L4: =J4 + K4 -> 0 | M4: =H4 * 0.1500 -> 0 | N4: =H4 * 0.0000 -> 0 | O4: =ABS(M4 + N4) -> 0 | Q4: =SUMIFS(EXPENSES!E:E, EXPENSES!B:B, "LEASE-BH-F3-2025", EXPENSES!D:D, ">="&DATE(2025,3,22), EXPENSES!D:D, "<="&DATE(2025,4,21)) -> 0 | S4: =H4 - O4 - Q4 -> 0 | Y4: 5661 | Z4: =S4-Y4 -> 0 | AA4: PAID | AB4: MULTIPLE | AC4: 45992
A5: LEASE-BH-F4-2025 | B5: Flat 4 - 3 West Gate | C5: Achal (Delegated for Udayan) | D5: Miss Megan Delaney, Mr Joseph Williams | E5: 45713 | F5: 25 | G5: =IFERROR(SUMPRODUCT((RENT_DUE!$B$2:$B$1000="LEASE-BH-F4-2025")*(RENT_DUE!$D$2:$D$1000>=DATE(2025,3,22))*(RENT_DUE!$D$2:$D$1000<=DATE(2025,4,21))*RENT_DUE!$L$2:$L$1000), 0) -> 0 | H5: =IFERROR(SUMPRODUCT((RENT_RECEIVED!$B$2:$B$1000="LEASE-BH-F4-2025")*(RENT_RECEIVED!$E$2:$E$1000>=DATE(2025,3,22))*(RENT_RECEIVED!$E$2:$E$1000<=DATE(2025,4,21))*RENT_RECEIVED!$O$2:$O$1000), 0) -> 0 | I5: HIST-2025-04-1532 | J5: =IFERROR(SUMIFS(RENT_DUE!$L$2:$L$10000, RENT_DUE!$B$2:$B$10000, "LEASE-BH-F4-2025", RENT_DUE!$D$2:$D$10000, "<"&DATE(2025,3,22)), 0) - IFERROR(SUMIFS(RENT_RECEIVED!$O$2:$O$10000, RENT_RECEIVED!$B$2:$B$10000, "LEASE-BH-F4-2025", RENT_RECEIVED!$E$2:$E$10000, "<"&DATE(2025,3,22)), 0) -> 0 | K5: =G5 - H5 -> 0 | L5: =J5 + K5 -> 0 | M5: =H5 * 0.1500 -> 0 | N5: =H5 * 0.0000 -> 0 | O5: =ABS(M5 + N5) -> 0 | Q5: =SUMIFS(EXPENSES!E:E, EXPENSES!B:B, "LEASE-BH-F4-2025", EXPENSES!D:D, ">="&DATE(2025,3,22), EXPENSES!D:D, "<="&DATE(2025,4,21)) -> 0 | S5: =H5 - O5 - Q5 -> 0 | Y5: 6390.75 | Z5: =S5-Y5 -> 0 | AA5: PAID | AB5: MULTIPLE | AC5: 45982
A6: LEASE-BH-F5-2025 | B6: Flat 5 - 3 West Gate | C6: Achal (Delegated for Udayan) | D6: Mr Amos Blyth | E6: 45698 | F6: 10 | G6: =IFERROR(SUMPRODUCT((RENT_DUE!$B$2:$B$1000="LEASE-BH-F5-2025")*(RENT_DUE!$D$2:$D$1000>=DATE(2025,3,22))*(RENT_DUE!$D$2:$D$1000<=DATE(2025,4,21))*RENT_DUE!$L$2:$L$1000), 0) -> 0 | H6: =IFERROR(SUMPRODUCT((RENT_RECEIVED!$B$2:$B$1000="LEASE-BH-F5-2025")*(RENT_RECEIVED!$E$2:$E$1000>=DATE(2025,3,22))*(RENT_RECEIVED!$E$2:$E$1000<=DATE(2025,4,21))*RENT_RECEIVED!$O$2:$O$1000), 0) -> 0 | I6: HIST-2025-04-1532 | J6: =IFERROR(SUMIFS(RENT_DUE!$L$2:$L$10000, RENT_DUE!$B$2:$B$10000, "LEASE-BH-F5-2025", RENT_DUE!$D$2:$D$10000, "<"&DATE(2025,3,22)), 0) - IFERROR(SUMIFS(RENT_RECEIVED!$O$2:$O$10000, RENT_RECEIVED!$B$2:$B$10000, "LEASE-BH-F5-2025", RENT_RECEIVED!$E$2:$E$10000, "<"&DATE(2025,3,22)), 0) -> 0 | K6: =G6 - H6 -> 0 | L6: =J6 + K6 -> 0 | M6: =H6 * 0.1500 -> 0 | N6: =H6 * 0.0000 -> 0 | O6: =ABS(M6 + N6) -> 0 | Q6: =SUMIFS(EXPENSES!E:E, EXPENSES!B:B, "LEASE-BH-F5-2025", EXPENSES!D:D, ">="&DATE(2025,3,22), EXPENSES!D:D, "<="&DATE(2025,4,21)) -> 0 | S6: =H6 - O6 - Q6 -> 0 | Y6: 6140 | Z6: =S6-Y6 -> 0 | AA6: PAID | AB6: MULTIPLE | AC6: 45982
A7: LEASE-BH-F6-2025 | B7: Flat 6 - 3 West Gate | C7: Achal (Delegated for Udayan) | D7: Miss Shelley Lees | E7: 45744 | F7: 28 | G7: =IFERROR(SUMPRODUCT((RENT_DUE!$B$2:$B$1000="LEASE-BH-F6-2025")*(RENT_DUE!$D$2:$D$1000>=DATE(2025,3,22))*(RENT_DUE!$D$2:$D$1000<=DATE(2025,4,21))*RENT_DUE!$L$2:$L$1000), 0) -> 0 | H7: =IFERROR(SUMPRODUCT((RENT_RECEIVED!$B$2:$B$1000="LEASE-BH-F6-2025")*(RENT_RECEIVED!$E$2:$E$1000>=DATE(2025,3,22))*(RENT_RECEIVED!$E$2:$E$1000<=DATE(2025,4,21))*RENT_RECEIVED!$O$2:$O$1000), 0) -> 0 | I7: HIST-2025-04-1532 | J7: =IFERROR(SUMIFS(RENT_DUE!$L$2:$L$10000, RENT_DUE!$B$2:$B$10000, "LEASE-BH-F6-2025", RENT_DUE!$D$2:$D$10000, "<"&DATE(2025,3,22)), 0) - IFERROR(SUMIFS(RENT_RECEIVED!$O$2:$O$10000, RENT_RECEIVED!$B$2:$B$10000, "LEASE-BH-F6-2025", RENT_RECEIVED!$E$2:$E$10000, "<"&DATE(2025,3,22)), 0) -> 0 | K7: =G7 - H7 -> 0 | L7: =J7 + K7 -> 0 | M7: =H7 * 0.1500 -> 0 | N7: =H7 * 0.0000 -> 0 | O7: =ABS(M7 + N7) -> 0 | Q7: =SUMIFS(EXPENSES!E:E, EXPENSES!B:B, "LEASE-BH-F6-2025", EXPENSES!D:D, ">="&DATE(2025,3,22), EXPENSES!D:D, "<="&DATE(2025,4,21)) -> 0 | S7: =H7 - O7 - Q7 -> 0 | Y7: 4882 | Z7: =S7-Y7 -> 0 | AA7: PAID | AB7: MULTIPLE | AC7: 45982
A8: LEASE-BH-F7-2025 | B8: Flat 7 - 3 West Gate | C8: Achal (Delegated for Udayan) | D8: Mr Chun Hung Tang | E8: 45707 | F8: 19 | G8: =IFERROR(SUMPRODUCT((RENT_DUE!$B$2:$B$1000="LEASE-BH-F7-2025")*(RENT_DUE!$D$2:$D$1000>=DATE(2025,3,22))*(RENT_DUE!$D$2:$D$1000<=DATE(2025,4,21))*RENT_DUE!$L$2:$L$1000), 0) -> 0 | H8: =IFERROR(SUMPRODUCT((RENT_RECEIVED!$B$2:$B$1000="LEASE-BH-F7-2025")*(RENT_RECEIVED!$E$2:$E$1000>=DATE(2025,3,22))*(RENT_RECEIVED!$E$2:$E$1000<=DATE(2025,4,21))*RENT_RECEIVED!$O$2:$O$1000), 0) -> 0 | J8: =IFERROR(SUMIFS(RENT_DUE!$L$2:$L$10000, RENT_DUE!$B$2:$B$10000, "LEASE-BH-F7-2025", RENT_DUE!$D$2:$D$10000, "<"&DATE(2025,3,22)), 0) - IFERROR(SUMIFS(RENT_RECEIVED!$O$2:$O$10000, RENT_RECEIVED!$B$2:$B$10000, "LEASE-BH-F7-2025", RENT_RECEIVED!$E$2:$E$10000, "<"&DATE(2025,3,22)), 0) -> 0 | K8: =G8 - H8 -> 0 | L8: =J8 + K8 -> 0 | M8: =H8 * 0.1500 -> 0 | N8: =H8 * 0.0000 -> 0 | O8: =ABS(M8 + N8) -> 0 | Q8: =SUMIFS(EXPENSES!E:E, EXPENSES!B:B, "LEASE-BH-F7-2025", EXPENSES!D:D, ">="&DATE(2025,3,22), EXPENSES!D:D, "<="&DATE(2025,4,21)) -> 0 | S8: =H8 - O8 - Q8 -> 0 | Y8: 3570 | Z8: =S8-Y8 -> 0 | AA8: PAID | AB8: MULTIPLE | AC8: 45861
A9: LEASE-BH-F8-2025 | B9: Flat 8 - 3 West Gate | C9: Achal (Delegated for Udayan) | D9: Mr Shermal Wijesinghage, Mrs Udeshika Dona | E9: 45712 | F9: 24 | G9: =IFERROR(SUMPRODUCT((RENT_DUE!$B$2:$B$1000="LEASE-BH-F8-2025")*(RENT_DUE!$D$2:$D$1000>=DATE(2025,3,22))*(RENT_DUE!$D$2:$D$1000<=DATE(2025,4,21))*RENT_DUE!$L$2:$L$1000), 0) -> 0 | H9: =IFERROR(SUMPRODUCT((RENT_RECEIVED!$B$2:$B$1000="LEASE-BH-F8-2025")*(RENT_RECEIVED!$E$2:$E$1000>=DATE(2025,3,22))*(RENT_RECEIVED!$E$2:$E$1000<=DATE(2025,4,21))*RENT_RECEIVED!$O$2:$O$1000), 0) -> 0 | I9: HIST-2025-04-1532 | J9: =IFERROR(SUMIFS(RENT_DUE!$L$2:$L$10000, RENT_DUE!$B$2:$B$10000, "LEASE-BH-F8-2025", RENT_DUE!$D$2:$D$10000, "<"&DATE(2025,3,22)), 0) - IFERROR(SUMIFS(RENT_RECEIVED!$O$2:$O$10000, RENT_RECEIVED!$B$2:$B$10000, "LEASE-BH-F8-2025", RENT_RECEIVED!$E$2:$E$10000, "<"&DATE(2025,3,22)), 0) -> 0 | K9: =G9 - H9 -> 0 | L9: =J9 + K9 -> 0 | M9: =H9 * 0.1500 -> 0 | N9: =H9 * 0.0000 -> 0 | O9: =ABS(M9 + N9) -> 0 | Q9: =SUMIFS(EXPENSES!E:E, EXPENSES!B:B, "LEASE-BH-F8-2025", EXPENSES!D:D, ">="&DATE(2025,3,22), EXPENSES!D:D, "<="&DATE(2025,4,21)) -> 0 | S9: =H9 - O9 - Q9 -> 0 | Y9: 5318.75 | Z9: =S9-Y9 -> 0 | AA9: PAID | AB9: MULTIPLE | AC9: 45982
A10: LEASE-BH-F9-2025 | B10: Flat 9 - 3 West Gate | C10: Achal (Delegated for Udayan) | D10: Mr Scott Warner | E10: 45736 | F10: 20 | G10: =IFERROR(SUMPRODUCT((RENT_DUE!$B$2:$B$1000="LEASE-BH-F9-2025")*(RENT_DUE!$D$2:$D$1000>=DATE(2025,3,22))*(RENT_DUE!$D$2:$D$1000<=DATE(2025,4,21))*RENT_DUE!$L$2:$L$1000), 0) -> 0 | H10: =IFERROR(SUMPRODUCT((RENT_RECEIVED!$B$2:$B$1000="LEASE-BH-F9-2025")*(RENT_RECEIVED!$E$2:$E$1000>=DATE(2025,3,22))*(RENT_RECEIVED!$E$2:$E$1000<=DATE(2025,4,21))*RENT_RECEIVED!$O$2:$O$1000), 0) -> 0 | I10: HIST-2025-04-1532 | J10: =IFERROR(SUMIFS(RENT_DUE!$L$2:$L$10000, RENT_DUE!$B$2:$B$10000, "LEASE-BH-F9-2025", RENT_DUE!$D$2:$D$10000, "<"&DATE(2025,3,22)), 0) - IFERROR(SUMIFS(RENT_RECEIVED!$O$2:$O$10000, RENT_RECEIVED!$B$2:$B$10000, "LEASE-BH-F9-2025", RENT_RECEIVED!$E$2:$E$10000, "<"&DATE(2025,3,22)), 0) -> 0 | K10: =G10 - H10 -> 0 | L10: =J10 + K10 -> 0 | M10: =H10 * 0.1500 -> 0 | N10: =H10 * 0.0000 -> 0 | O10: =ABS(M10 + N10) -> 0 | Q10: =SUMIFS(EXPENSES!E:E, EXPENSES!B:B, "LEASE-BH-F9-2025", EXPENSES!D:D, ">="&DATE(2025,3,22), EXPENSES!D:D, "<="&DATE(2025,4,21)) -> 0 | S10: =H10 - O10 - Q10 -> 0 | Y10: 5255 | Z10: =S10-Y10 -> 0 | AA10: PAID | AB10: MULTIPLE | AC10: 45982
A11: LEASE-BH-F10-2025 | B11: Flat 10 - 3 West Gate | C11: Achal (Delegated for Udayan) | D11: Mr Ferenc Peter | E11: 45722 | F11: 6 | G11: =IFERROR(SUMPRODUCT((RENT_DUE!$B$2:$B$1000="LEASE-BH-F10-2025")*(RENT_DUE!$D$2:$D$1000>=DATE(2025,3,22))*(RENT_DUE!$D$2:$D$1000<=DATE(2025,4,21))*RENT_DUE!$L$2:$L$1000), 0) -> 0 | H11: =IFERROR(SUMPRODUCT((RENT_RECEIVED!$B$2:$B$1000="LEASE-BH-F10-2025")*(RENT_RECEIVED!$E$2:$E$1000>=DATE(2025,3,22))*(RENT_RECEIVED!$E$2:$E$1000<=DATE(2025,4,21))*RENT_RECEIVED!$O$2:$O$1000), 0) -> 0 | I11: HIST-2025-04-1532 | J11: =IFERROR(SUMIFS(RENT_DUE!$L$2:$L$10000, RENT_DUE!$B$2:$B$10000, "LEASE-BH-F10-2025", RENT_DUE!$D$2:$D$10000, "<"&DATE(2025,3,22)), 0) - IFERROR(SUMIFS(RENT_RECEIVED!$O$2:$O$10000, RENT_RECEIVED!$B$2:$B$10000, "LEASE-BH-F10-2025", RENT_RECEIVED!$E$2:$E$10000, "<"&DATE(2025,3,22)), 0) -> 0 | K11: =G11 - H11 -> 0 | L11: =J11 + K11 -> 0 | M11: =H11 * 0.1500 -> 0 | N11: =H11 * 0.0000 -> 0 | O11: =ABS(M11 + N11) -> 0 | Q11: =SUMIFS(EXPENSES!E:E, EXPENSES!B:B, "LEASE-BH-F10-2025", EXPENSES!D:D, ">="&DATE(2025,3,22), EXPENSES!D:D, "<="&DATE(2025,4,21)) -> 0 | S11: =H11 - O11 - Q11 -> 0 | Y11: 3534.47 | Z11: =S11-Y11 -> 0 | AA11: PAID | AB11: MULTIPLE | AC11: 45920
A12: LEASE-BH-F11-2025 | B12: Flat 11 - 3 West Gate | C12: Achal (Delegated for Udayan) | D12: Mr Richard Perrotta | E12: 45722 | F12: 26 | G12: =IFERROR(SUMPRODUCT((RENT_DUE!$B$2:$B$1000="LEASE-BH-F11-2025")*(RENT_DUE!$D$2:$D$1000>=DATE(2025,3,22))*(RENT_DUE!$D$2:$D$1000<=DATE(2025,4,21))*RENT_DUE!$L$2:$L$1000), 0) -> 0 | H12: =IFERROR(SUMPRODUCT((RENT_RECEIVED!$B$2:$B$1000="LEASE-BH-F11-2025")*(RENT_RECEIVED!$E$2:$E$1000>=DATE(2025,3,22))*(RENT_RECEIVED!$E$2:$E$1000<=DATE(2025,4,21))*RENT_RECEIVED!$O$2:$O$1000), 0) -> 0 | I12: HIST-2025-04-1532 | J12: =IFERROR(SUMIFS(RENT_DUE!$L$2:$L$10000, RENT_DUE!$B$2:$B$10000, "LEASE-BH-F11-2025", RENT_DUE!$D$2:$D$10000, "<"&DATE(2025,3,22)), 0) - IFERROR(SUMIFS(RENT_RECEIVED!$O$2:$O$10000, RENT_RECEIVED!$B$2:$B$10000, "LEASE-BH-F11-2025", RENT_RECEIVED!$E$2:$E$10000, "<"&DATE(2025,3,22)), 0) -> 0 | K12: =G12 - H12 -> 0 | L12: =J12 + K12 -> 0 | M12: =H12 * 0.1500 -> 0 | N12: =H12 * 0.0000 -> 0 | O12: =ABS(M12 + N12) -> 0 | Q12: =SUMIFS(EXPENSES!E:E, EXPENSES!B:B, "LEASE-BH-F11-2025", EXPENSES!D:D, ">="&DATE(2025,3,22), EXPENSES!D:D, "<="&DATE(2025,4,21)) -> 0 | S12: =H12 - O12 - Q12 -> 0 | Y12: 5979.75 | Z12: =S12-Y12 -> 0 | AA12: PAID | AB12: MULTIPLE | AC12: 45981
A13: LEASE-BH-F12-2025 | B13: Flat 12 - 3 West Gate | C13: Achal (Delegated for Udayan) | D13: MR J SOOPIYADAKATH THEKKE PURAYIL & MS S | E13: 45754 | F13: 7 | G13: =IFERROR(SUMPRODUCT((RENT_DUE!$B$2:$B$1000="LEASE-BH-F12-2025")*(RENT_DUE!$D$2:$D$1000>=DATE(2025,3,22))*(RENT_DUE!$D$2:$D$1000<=DATE(2025,4,21))*RENT_DUE!$L$2:$L$1000), 0) -> 0 | H13: =IFERROR(SUMPRODUCT((RENT_RECEIVED!$B$2:$B$1000="LEASE-BH-F12-2025")*(RENT_RECEIVED!$E$2:$E$1000>=DATE(2025,3,22))*(RENT_RECEIVED!$E$2:$E$1000<=DATE(2025,4,21))*RENT_RECEIVED!$O$2:$O$1000), 0) -> 0 | I13: HIST-2025-04-1532 | J13: =IFERROR(SUMIFS(RENT_DUE!$L$2:$L$10000, RENT_DUE!$B$2:$B$10000, "LEASE-BH-F12-2025", RENT_DUE!$D$2:$D$10000, "<"&DATE(2025,3,22)), 0) - IFERROR(SUMIFS(RENT_RECEIVED!$O$2:$O$10000, RENT_RECEIVED!$B$2:$B$10000, "LEASE-BH-F12-2025", RENT_RECEIVED!$E$2:$E$10000, "<"&DATE(2025,3,22)), 0) -> 0 | K13: =G13 - H13 -> 0 | L13: =J13 + K13 -> 0 | M13: =H13 * 0.1500 -> 0 | N13: =H13 * 0.0000 -> 0 | O13: =ABS(M13 + N13) -> 0 | Q13: =SUMIFS(EXPENSES!E:E, EXPENSES!B:B, "LEASE-BH-F12-2025", EXPENSES!D:D, ">="&DATE(2025,3,22), EXPENSES!D:D, "<="&DATE(2025,4,21)) -> 0 | S13: =H13 - O13 - Q13 -> 0 | Y13: 1147.5 | Z13: =S13-Y13 -> 0 | AA13: PAID | AB13: MULTIPLE | AC13: 45804
A14: LEASE-BH-F13-2025 | B14: Flat 13 - 3 West Gate | C14: Achal (Delegated for Udayan) | D14: Mr Nathan Holland | E14: 45719 | F14: 3 | G14: =IFERROR(SUMPRODUCT((RENT_DUE!$B$2:$B$1000="LEASE-BH-F13-2025")*(RENT_DUE!$D$2:$D$1000>=DATE(2025,3,22))*(RENT_DUE!$D$2:$D$1000<=DATE(2025,4,21))*RENT_DUE!$L$2:$L$1000), 0) -> 0 | H14: =IFERROR(SUMPRODUCT((RENT_RECEIVED!$B$2:$B$1000="LEASE-BH-F13-2025")*(RENT_RECEIVED!$E$2:$E$1000>=DATE(2025,3,22))*(RENT_RECEIVED!$E$2:$E$1000<=DATE(2025,4,21))*RENT_RECEIVED!$O$2:$O$1000), 0) -> 0 | I14: HIST-2025-04-1532 | J14: =IFERROR(SUMIFS(RENT_DUE!$L$2:$L$10000, RENT_DUE!$B$2:$B$10000, "LEASE-BH-F13-2025", RENT_DUE!$D$2:$D$10000, "<"&DATE(2025,3,22)), 0) - IFERROR(SUMIFS(RENT_RECEIVED!$O$2:$O$10000, RENT_RECEIVED!$B$2:$B$10000, "LEASE-BH-F13-2025", RENT_RECEIVED!$E$2:$E$10000, "<"&DATE(2025,3,22)), 0) -> 0 | K14: =G14 - H14 -> 0 | L14: =J14 + K14 -> 0 | M14: =H14 * 0.1500 -> 0 | N14: =H14 * 0.0000 -> 0 | O14: =ABS(M14 + N14) -> 0 | Q14: =SUMIFS(EXPENSES!E:E, EXPENSES!B:B, "LEASE-BH-F13-2025", EXPENSES!D:D, ">="&DATE(2025,3,22), EXPENSES!D:D, "<="&DATE(2025,4,21)) -> 0 | S14: =H14 - O14 - Q14 -> 0 | Y14: 5440 | Z14: =S14-Y14 -> 0 | AA14: PAID | AB14: MULTIPLE | AC14: 45936
A15: LEASE-BH-F14-2025 | B15: Flat 14 - 3 West Gate | C15: Achal (Delegated for Udayan) | D15: Ms Sarah Buckle, Mr Matthew Lewsley | E15: 45744 | F15: 28 | G15: =IFERROR(SUMPRODUCT((RENT_DUE!$B$2:$B$1000="LEASE-BH-F14-2025")*(RENT_DUE!$D$2:$D$1000>=DATE(2025,3,22))*(RENT_DUE!$D$2:$D$1000<=DATE(2025,4,21))*RENT_DUE!$L$2:$L$1000), 0) -> 0 | H15: =IFERROR(SUMPRODUCT((RENT_RECEIVED!$B$2:$B$1000="LEASE-BH-F14-2025")*(RENT_RECEIVED!$E$2:$E$1000>=DATE(2025,3,22))*(RENT_RECEIVED!$E$2:$E$1000<=DATE(2025,4,21))*RENT_RECEIVED!$O$2:$O$1000), 0) -> 0 | I15: HIST-2025-04-1533 | J15: =IFERROR(SUMIFS(RENT_DUE!$L$2:$L$10000, RENT_DUE!$B$2:$B$10000, "LEASE-BH-F14-2025", RENT_DUE!$D$2:$D$10000, "<"&DATE(2025,3,22)), 0) - IFERROR(SUMIFS(RENT_RECEIVED!$O$2:$O$10000, RENT_RECEIVED!$B$2:$B$10000, "LEASE-BH-F14-2025", RENT_RECEIVED!$E$2:$E$10000, "<"&DATE(2025,3,22)), 0) -> 0 | K15: =G15 - H15 -> 0 | L15: =J15 + K15 -> 0 | M15: =H15 * 0.1500 -> 0 | N15: =H15 * 0.0000 -> 0 | O15: =ABS(M15 + N15) -> 0 | Q15: =SUMIFS(EXPENSES!E:E, EXPENSES!B:B, "LEASE-BH-F14-2025", EXPENSES!D:D, ">="&DATE(2025,3,22), EXPENSES!D:D, "<="&DATE(2025,4,21)) -> 0 | S15: =H15 - O15 - Q15 -> 0 | Y15: 5410.25 | Z15: =S15-Y15 -> 0 | AA15: PAID | AB15: MULTIPLE | AC15: 45992
A16: LEASE-BH-F15-2025 | B16: Flat 15 - 3 West Gate | C16: Achal (Delegated for Udayan) | D16: Ms Lucy Cassell | E16: 45703 | F16: 15 | G16: =IFERROR(SUMPRODUCT((RENT_DUE!$B$2:$B$1000="LEASE-BH-F15-2025")*(RENT_DUE!$D$2:$D$1000>=DATE(2025,3,22))*(RENT_DUE!$D$2:$D$1000<=DATE(2025,4,21))*RENT_DUE!$L$2:$L$1000), 0) -> 0 | H16: =IFERROR(SUMPRODUCT((RENT_RECEIVED!$B$2:$B$1000="LEASE-BH-F15-2025")*(RENT_RECEIVED!$E$2:$E$1000>=DATE(2025,3,22))*(RENT_RECEIVED!$E$2:$E$1000<=DATE(2025,4,21))*RENT_RECEIVED!$O$2:$O$1000), 0) -> 0 | J16: =IFERROR(SUMIFS(RENT_DUE!$L$2:$L$10000, RENT_DUE!$B$2:$B$10000, "LEASE-BH-F15-2025", RENT_DUE!$D$2:$D$10000, "<"&DATE(2025,3,22)), 0) - IFERROR(SUMIFS(RENT_RECEIVED!$O$2:$O$10000, RENT_RECEIVED!$B$2:$B$10000, "LEASE-BH-F15-2025", RENT_RECEIVED!$E$2:$E$10000, "<"&DATE(2025,3,22)), 0) -> 0 | K16: =G16 - H16 -> 0 | L16: =J16 + K16 -> 0 | M16: =H16 * 0.1500 -> 0 | N16: =H16 * 0.0000 -> 0 | O16: =ABS(M16 + N16) -> 0 | Q16: =SUMIFS(EXPENSES!E:E, EXPENSES!B:B, "LEASE-BH-F15-2025", EXPENSES!D:D, ">="&DATE(2025,3,22), EXPENSES!D:D, "<="&DATE(2025,4,21)) -> 0 | S16: =H16 - O16 - Q16 -> 0 | Y16: 6170 | Z16: =S16-Y16 -> 0 | AA16: PAID | AB16: MULTIPLE | AC16: 45982
A17: LEASE-BH-F16-2025 | B17: Flat 16 - 3 West Gate | C17: Achal (Delegated for Udayan) | D17: Mr Riley Paul Beresford, Ms Gina Louise Judge | E17: 45726 | F17: 10 | G17: =IFERROR(SUMPRODUCT((RENT_DUE!$B$2:$B$1000="LEASE-BH-F16-2025")*(RENT_DUE!$D$2:$D$1000>=DATE(2025,3,22))*(RENT_DUE!$D$2:$D$1000<=DATE(2025,4,21))*RENT_DUE!$L$2:$L$1000), 0) -> 0 | H17: =IFERROR(SUMPRODUCT((RENT_RECEIVED!$B$2:$B$1000="LEASE-BH-F16-2025")*(RENT_RECEIVED!$E$2:$E$1000>=DATE(2025,3,22))*(RENT_RECEIVED!$E$2:$E$1000<=DATE(2025,4,21))*RENT_RECEIVED!$O$2:$O$1000), 0) -> 0 | I17: HIST-2025-04-1532 | J17: =IFERROR(SUMIFS(RENT_DUE!$L$2:$L$10000, RENT_DUE!$B$2:$B$10000, "LEASE-BH-F16-2025", RENT_DUE!$D$2:$D$10000, "<"&DATE(2025,3,22)), 0) - IFERROR(SUMIFS(RENT_RECEIVED!$O$2:$O$10000, RENT_RECEIVED!$B$2:$B$10000, "LEASE-BH-F16-2025", RENT_RECEIVED!$E$2:$E$10000, "<"&DATE(2025,3,22)), 0) -> 0 | K17: =G17 - H17 -> 0 | L17: =J17 + K17 -> 0 | M17: =H17 * 0.1500 -> 0 | N17: =H17 * 0.0000 -> 0 | O17: =ABS(M17 + N17) -> 0 | Q17: =SUMIFS(EXPENSES!E:E, EXPENSES!B:B, "LEASE-BH-F16-2025", EXPENSES!D:D, ">="&DATE(2025,3,22), EXPENSES!D:D, "<="&DATE(2025,4,21)) -> 0 | S17: =H17 - O17 - Q17 -> 0 | Y17: 3641.31 | Z17: =S17-Y17 -> 0 | AA17: PAID | AB17: MULTIPLE | AC17: 45891
A18: LEASE-BH-F17-2025 | B18: Flat 17 - 3 West Gate | C18: Achal (Delegated for Udayan) | D18: Mr Harsh Patel | E18: 45705 | F18: 17 | G18: =IFERROR(SUMPRODUCT((RENT_DUE!$B$2:$B$1000="LEASE-BH-F17-2025")*(RENT_DUE!$D$2:$D$1000>=DATE(2025,3,22))*(RENT_DUE!$D$2:$D$1000<=DATE(2025,4,21))*RENT_DUE!$L$2:$L$1000), 0) -> 0 | H18: =IFERROR(SUMPRODUCT((RENT_RECEIVED!$B$2:$B$1000="LEASE-BH-F17-2025")*(RENT_RECEIVED!$E$2:$E$1000>=DATE(2025,3,22))*(RENT_RECEIVED!$E$2:$E$1000<=DATE(2025,4,21))*RENT_RECEIVED!$O$2:$O$1000), 0) -> 0 | I18: HIST-2025-04-1532 | J18: =IFERROR(SUMIFS(RENT_DUE!$L$2:$L$10000, RENT_DUE!$B$2:$B$10000, "LEASE-BH-F17-2025", RENT_DUE!$D$2:$D$10000, "<"&DATE(2025,3,22)), 0) - IFERROR(SUMIFS(RENT_RECEIVED!$O$2:$O$10000, RENT_RECEIVED!$B$2:$B$10000, "LEASE-BH-F17-2025", RENT_RECEIVED!$E$2:$E$10000, "<"&DATE(2025,3,22)), 0) -> 0 | K18: =G18 - H18 -> 0 | L18: =J18 + K18 -> 0 | M18: =H18 * 0.1500 -> 0 | N18: =H18 * 0.0000 -> 0 | O18: =ABS(M18 + N18) -> 0 | Q18: =SUMIFS(EXPENSES!E:E, EXPENSES!B:B, "LEASE-BH-F17-2025", EXPENSES!D:D, ">="&DATE(2025,3,22), EXPENSES!D:D, "<="&DATE(2025,4,21)) -> 0 | S18: =H18 - O18 - Q18 -> 0 | Y18: 5800 | Z18: =S18-Y18 -> 0 | AA18: PAID | AB18: MULTIPLE | AC18: 45982
A19: LEASE-BH-F18-2025 | B19: Flat 18 - 3 West Gate | C19: Achal (Delegated for Udayan) | D19: Marie Dinko | E19: 45687 | F19: 30 | G19: =IFERROR(SUMPRODUCT((RENT_DUE!$B$2:$B$1000="LEASE-BH-F18-2025")*(RENT_DUE!$D$2:$D$1000>=DATE(2025,3,22))*(RENT_DUE!$D$2:$D$1000<=DATE(2025,4,21))*RENT_DUE!$L$2:$L$1000), 0) -> 0 | H19: =IFERROR(SUMPRODUCT((RENT_RECEIVED!$B$2:$B$1000="LEASE-BH-F18-2025")*(RENT_RECEIVED!$E$2:$E$1000>=DATE(2025,3,22))*(RENT_RECEIVED!$E$2:$E$1000<=DATE(2025,4,21))*RENT_RECEIVED!$O$2:$O$1000), 0) -> 0 | I19: HIST-2025-04-1532 | J19: =IFERROR(SUMIFS(RENT_DUE!$L$2:$L$10000, RENT_DUE!$B$2:$B$10000, "LEASE-BH-F18-2025", RENT_DUE!$D$2:$D$10000, "<"&DATE(2025,3,22)), 0) - IFERROR(SUMIFS(RENT_RECEIVED!$O$2:$O$10000, RENT_RECEIVED!$B$2:$B$10000, "LEASE-BH-F18-2025", RENT_RECEIVED!$E$2:$E$10000, "<"&DATE(2025,3,22)), 0) -> 0 | K19: =G19 - H19 -> 0 | L19: =J19 + K19 -> 0 | M19: =H19 * 0.1500 -> 0 | N19: =H19 * 0.0000 -> 0 | O19: =ABS(M19 + N19) -> 0 | Q19: =SUMIFS(EXPENSES!E:E, EXPENSES!B:B, "LEASE-BH-F18-2025", EXPENSES!D:D, ">="&DATE(2025,3,22), EXPENSES!D:D, "<="&DATE(2025,4,21)) -> 0 | S19: =H19 - O19 - Q19 -> 0 | Y19: 2044.25 | Z19: =S19-Y19 -> 0 | AA19: PAID | AB19: MULTIPLE | AC19: 45804
A20: LEASE-BH-F19-2025 | B20: Flat 19 - 3 West Gate | C20: Achal (Delegated for Udayan) | D20: Mr Joshua Banks, Miss Layla Middlemass | E20: 45730 | F20: 14 | G20: =IFERROR(SUMPRODUCT((RENT_DUE!$B$2:$B$1000="LEASE-BH-F19-2025")*(RENT_DUE!$D$2:$D$1000>=DATE(2025,3,22))*(RENT_DUE!$D$2:$D$1000<=DATE(2025,4,21))*RENT_DUE!$L$2:$L$1000), 0) -> 0 | H20: =IFERROR(SUMPRODUCT((RENT_RECEIVED!$B$2:$B$1000="LEASE-BH-F19-2025")*(RENT_RECEIVED!$E$2:$E$1000>=DATE(2025,3,22))*(RENT_RECEIVED!$E$2:$E$1000<=DATE(2025,4,21))*RENT_RECEIVED!$O$2:$O$1000), 0) -> 0 | I20: HIST-2025-04-1532 | J20: =IFERROR(SUMIFS(RENT_DUE!$L$2:$L$10000, RENT_DUE!$B$2:$B$10000, "LEASE-BH-F19-2025", RENT_DUE!$D$2:$D$10000, "<"&DATE(2025,3,22)), 0) - IFERROR(SUMIFS(RENT_RECEIVED!$O$2:$O$10000, RENT_RECEIVED!$B$2:$B$10000, "LEASE-BH-F19-2025", RENT_RECEIVED!$E$2:$E$10000, "<"&DATE(2025,3,22)), 0) -> 0 | K20: =G20 - H20 -> 0 | L20: =J20 + K20 -> 0 | M20: =H20 * 0.1500 -> 0 | N20: =H20 * 0.0000 -> 0 | O20: =ABS(M20 + N20) -> 0 | Q20: =SUMIFS(EXPENSES!E:E, EXPENSES!B:B, "LEASE-BH-F19-2025", EXPENSES!D:D, ">="&DATE(2025,3,22), EXPENSES!D:D, "<="&DATE(2025,4,21)) -> 0 | S20: =H20 - O20 - Q20 -> 0 | Y20: 2888.3 | Z20: =S20-Y20 -> 0 | AA20: PAID | AB20: MULTIPLE | AC20: 45846
A21: LEASE-BH-F20-2025 | B21: Flat 20 - 3 West Gate | C21: Achal (Delegated for Udayan) | D21: Mr James Kay | E21: 45732 | F21: 16 | G21: =IFERROR(SUMPRODUCT((RENT_DUE!$B$2:$B$1000="LEASE-BH-F20-2025")*(RENT_DUE!$D$2:$D$1000>=DATE(2025,3,22))*(RENT_DUE!$D$2:$D$1000<=DATE(2025,4,21))*RENT_DUE!$L$2:$L$1000), 0) -> 0 | H21: =IFERROR(SUMPRODUCT((RENT_RECEIVED!$B$2:$B$1000="LEASE-BH-F20-2025")*(RENT_RECEIVED!$E$2:$E$1000>=DATE(2025,3,22))*(RENT_RECEIVED!$E$2:$E$1000<=DATE(2025,4,21))*RENT_RECEIVED!$O$2:$O$1000), 0) -> 0 | I21: HIST-2025-04-1532 | J21: =IFERROR(SUMIFS(RENT_DUE!$L$2:$L$10000, RENT_DUE!$B$2:$B$10000, "LEASE-BH-F20-2025", RENT_DUE!$D$2:$D$10000, "<"&DATE(2025,3,22)), 0) - IFERROR(SUMIFS(RENT_RECEIVED!$O$2:$O$10000, RENT_RECEIVED!$B$2:$B$10000, "LEASE-BH-F20-2025", RENT_RECEIVED!$E$2:$E$10000, "<"&DATE(2025,3,22)), 0) -> 0 | K21: =G21 - H21 -> 0 | L21: =J21 + K21 -> 0 | M21: =H21 * 0.1500 -> 0 | N21: =H21 * 0.0000 -> 0 | O21: =ABS(M21 + N21) -> 0 | Q21: =SUMIFS(EXPENSES!E:E, EXPENSES!B:B, "LEASE-BH-F20-2025", EXPENSES!D:D, ">="&DATE(2025,3,22), EXPENSES!D:D, "<="&DATE(2025,4,21)) -> 0 | S21: =H21 - O21 - Q21 -> 0 | Y21: 5255 | Z21: =S21-Y21 -> 0 | AA21: PAID | AB21: MULTIPLE | AC21: 45982
A22: LEASE-BH-F21-2025 | B22: Flat 21 - 3 West Gate | C22: Achal (Delegated for Udayan) | D22: Mr Felwin Francis | E22: 45687 | F22: 30 | G22: =IFERROR(SUMPRODUCT((RENT_DUE!$B$2:$B$1000="LEASE-BH-F21-2025")*(RENT_DUE!$D$2:$D$1000>=DATE(2025,3,22))*(RENT_DUE!$D$2:$D$1000<=DATE(2025,4,21))*RENT_DUE!$L$2:$L$1000), 0) -> 0 | H22: =IFERROR(SUMPRODUCT((RENT_RECEIVED!$B$2:$B$1000="LEASE-BH-F21-2025")*(RENT_RECEIVED!$E$2:$E$1000>=DATE(2025,3,22))*(RENT_RECEIVED!$E$2:$E$1000<=DATE(2025,4,21))*RENT_RECEIVED!$O$2:$O$1000), 0) -> 0 | I22: HIST-2025-04-1532 | J22: =IFERROR(SUMIFS(RENT_DUE!$L$2:$L$10000, RENT_DUE!$B$2:$B$10000, "LEASE-BH-F21-2025", RENT_DUE!$D$2:$D$10000, "<"&DATE(2025,3,22)), 0) - IFERROR(SUMIFS(RENT_RECEIVED!$O$2:$O$10000, RENT_RECEIVED!$B$2:$B$10000, "LEASE-BH-F21-2025", RENT_RECEIVED!$E$2:$E$10000, "<"&DATE(2025,3,22)), 0) -> 0 | K22: =G22 - H22 -> 0 | L22: =J22 + K22 -> 0 | M22: =H22 * 0.1500 -> 0 | N22: =H22 * 0.0000 -> 0 | O22: =ABS(M22 + N22) -> 0 | Q22: =SUMIFS(EXPENSES!E:E, EXPENSES!B:B, "LEASE-BH-F21-2025", EXPENSES!D:D, ">="&DATE(2025,3,22), EXPENSES!D:D, "<="&DATE(2025,4,21)) -> 0 | S22: =H22 - O22 - Q22 -> 0 | Y22: 6637.5 | Z22: =S22-Y22 -> 0 | AA22: PAID | AB22: MULTIPLE | AC22: 45982
A23: LEASE-BH-F22-2025 | B23: Flat 22 - 3 West Gate | C23: Achal (Delegated for Udayan) | D23: Mr Brian Lowe | E23: 45717 | F23: 1 | G23: =IFERROR(SUMPRODUCT((RENT_DUE!$B$2:$B$1000="LEASE-BH-F22-2025")*(RENT_DUE!$D$2:$D$1000>=DATE(2025,3,22))*(RENT_DUE!$D$2:$D$1000<=DATE(2025,4,21))*RENT_DUE!$L$2:$L$1000), 0) -> 0 | H23: =IFERROR(SUMPRODUCT((RENT_RECEIVED!$B$2:$B$1000="LEASE-BH-F22-2025")*(RENT_RECEIVED!$E$2:$E$1000>=DATE(2025,3,22))*(RENT_RECEIVED!$E$2:$E$1000<=DATE(2025,4,21))*RENT_RECEIVED!$O$2:$O$1000), 0) -> 0 | I23: HIST-2025-04-1532 | J23: =IFERROR(SUMIFS(RENT_DUE!$L$2:$L$10000, RENT_DUE!$B$2:$B$10000, "LEASE-BH-F22-2025", RENT_DUE!$D$2:$D$10000, "<"&DATE(2025,3,22)), 0) - IFERROR(SUMIFS(RENT_RECEIVED!$O$2:$O$10000, RENT_RECEIVED!$B$2:$B$10000, "LEASE-BH-F22-2025", RENT_RECEIVED!$E$2:$E$10000, "<"&DATE(2025,3,22)), 0) -> 0 | K23: =G23 - H23 -> 0 | L23: =J23 + K23 -> 0 | M23: =H23 * 0.1500 -> 0 | N23: =H23 * 0.0000 -> 0 | O23: =ABS(M23 + N23) -> 0 | Q23: =SUMIFS(EXPENSES!E:E, EXPENSES!B:B, "LEASE-BH-F22-2025", EXPENSES!D:D, ">="&DATE(2025,3,22), EXPENSES!D:D, "<="&DATE(2025,4,21)) -> 0 | S23: =H23 - O23 - Q23 -> 0 | Y23: 5661 | Z23: =S23-Y23 -> 0 | AA23: PAID | AB23: MULTIPLE | AC23: 45982
A24: LEASE-BH-F24-2025 | B24: Flat 24 - 3 West Gate | C24: Achal (Delegated for Udayan) | D24: Mr Ethan Maloney, Miss Soraya Fearon | E24: 45700 | F24: 12 | G24: =IFERROR(SUMPRODUCT((RENT_DUE!$B$2:$B$1000="LEASE-BH-F24-2025")*(RENT_DUE!$D$2:$D$1000>=DATE(2025,3,22))*(RENT_DUE!$D$2:$D$1000<=DATE(2025,4,21))*RENT_DUE!$L$2:$L$1000), 0) -> 0 | H24: =IFERROR(SUMPRODUCT((RENT_RECEIVED!$B$2:$B$1000="LEASE-BH-F24-2025")*(RENT_RECEIVED!$E$2:$E$1000>=DATE(2025,3,22))*(RENT_RECEIVED!$E$2:$E$1000<=DATE(2025,4,21))*RENT_RECEIVED!$O$2:$O$1000), 0) -> 0 | I24: HIST-2025-04-1532 | J24: =IFERROR(SUMIFS(RENT_DUE!$L$2:$L$10000, RENT_DUE!$B$2:$B$10000, "LEASE-BH-F24-2025", RENT_DUE!$D$2:$D$10000, "<"&DATE(2025,3,22)), 0) - IFERROR(SUMIFS(RENT_RECEIVED!$O$2:$O$10000, RENT_RECEIVED!$B$2:$B$10000, "LEASE-BH-F24-2025", RENT_RECEIVED!$E$2:$E$10000, "<"&DATE(2025,3,22)), 0) -> 0 | K24: =G24 - H24 -> 0 | L24: =J24 + K24 -> 0 | M24: =H24 * 0.1500 -> 0 | N24: =H24 * 0.0000 -> 0 | O24: =ABS(M24 + N24) -> 0 | Q24: =SUMIFS(EXPENSES!E:E, EXPENSES!B:B, "LEASE-BH-F24-2025", EXPENSES!D:D, ">="&DATE(2025,3,22), EXPENSES!D:D, "<="&DATE(2025,4,21)) -> 0 | S24: =H24 - O24 - Q24 -> 0 | Y24: 6765 | Z24: =S24-Y24 -> 0 | AA24: PAID | AB24: MULTIPLE | AC24: 45982
A25: LEASE-BH-F26-2025 | B25: Flat 26 - 3 West Gate | C25: Achal (Delegated for Udayan) | D25: Mr Louis Scotting | E25: 45730 | F25: 14 | G25: =IFERROR(SUMPRODUCT((RENT_DUE!$B$2:$B$1000="LEASE-BH-F26-2025")*(RENT_DUE!$D$2:$D$1000>=DATE(2025,3,22))*(RENT_DUE!$D$2:$D$1000<=DATE(2025,4,21))*RENT_DUE!$L$2:$L$1000), 0) -> 0 | H25: =IFERROR(SUMPRODUCT((RENT_RECEIVED!$B$2:$B$1000="LEASE-BH-F26-2025")*(RENT_RECEIVED!$E$2:$E$1000>=DATE(2025,3,22))*(RENT_RECEIVED!$E$2:$E$1000<=DATE(2025,4,21))*RENT_RECEIVED!$O$2:$O$1000), 0) -> 0 | I25: HIST-2025-04-1532, HIST-2025-04-1533 | J25: =IFERROR(SUMIFS(RENT_DUE!$L$2:$L$10000, RENT_DUE!$B$2:$B$10000, "LEASE-BH-F26-2025", RENT_DUE!$D$2:$D$10000, "<"&DATE(2025,3,22)), 0) - IFERROR(SUMIFS(RENT_RECEIVED!$O$2:$O$10000, RENT_RECEIVED!$B$2:$B$10000, "LEASE-BH-F26-2025", RENT_RECEIVED!$E$2:$E$10000, "<"&DATE(2025,3,22)), 0) -> 0 | K25: =G25 - H25 -> 0 | L25: =J25 + K25 -> 0 | M25: =H25 * 0.1500 -> 0 | N25: =H25 * 0.0000 -> 0 | O25: =ABS(M25 + N25) -> 0 | Q25: =SUMIFS(EXPENSES!E:E, EXPENSES!B:B, "LEASE-BH-F26-2025", EXPENSES!D:D, ">="&DATE(2025,3,22), EXPENSES!D:D, "<="&DATE(2025,4,21)) -> 0 | S25: =H25 - O25 - Q25 -> 0 | Y25: 5163.75 | Z25: =S25-Y25 -> 0 | AA25: PAID | AB25: MULTIPLE | AC25: 45992
A26: LEASE-BH-F27-2025 | B26: Flat 27 - 3 West Gate | C26: Achal (Delegated for Udayan) | D26: Miss Sophie Murray | E26: 45716 | F26: 30 | G26: =IFERROR(SUMPRODUCT((RENT_DUE!$B$2:$B$1000="LEASE-BH-F27-2025")*(RENT_DUE!$D$2:$D$1000>=DATE(2025,3,22))*(RENT_DUE!$D$2:$D$1000<=DATE(2025,4,21))*RENT_DUE!$L$2:$L$1000), 0) -> 0 | H26: =IFERROR(SUMPRODUCT((RENT_RECEIVED!$B$2:$B$1000="LEASE-BH-F27-2025")*(RENT_RECEIVED!$E$2:$E$1000>=DATE(2025,3,22))*(RENT_RECEIVED!$E$2:$E$1000<=DATE(2025,4,21))*RENT_RECEIVED!$O$2:$O$1000), 0) -> 0 | I26: HIST-2025-04-1532 | J26: =IFERROR(SUMIFS(RENT_DUE!$L$2:$L$10000, RENT_DUE!$B$2:$B$10000, "LEASE-BH-F27-2025", RENT_DUE!$D$2:$D$10000, "<"&DATE(2025,3,22)), 0) - IFERROR(SUMIFS(RENT_RECEIVED!$O$2:$O$10000, RENT_RECEIVED!$B$2:$B$10000, "LEASE-BH-F27-2025", RENT_RECEIVED!$E$2:$E$10000, "<"&DATE(2025,3,22)), 0) -> 0 | K26: =G26 - H26 -> 0 | L26: =J26 + K26 -> 0 | M26: =H26 * 0.1500 -> 0 | N26: =H26 * 0.0000 -> 0 | O26: =ABS(M26 + N26) -> 0 | Q26: =SUMIFS(EXPENSES!E:E, EXPENSES!B:B, "LEASE-BH-F27-2025", EXPENSES!D:D, ">="&DATE(2025,3,22), EXPENSES!D:D, "<="&DATE(2025,4,21)) -> 0 | S26: =H26 - O26 - Q26 -> 0 | Y26: 5355 | Z26: =S26-Y26 -> 0 | AA26: PAID | AB26: MULTIPLE | AC26: 45982
A27: LEASE-BH-F28-2025 | B27: Flat 28 - 3 West Gate | C27: Achal (Delegated for Udayan) | D27: Ms Shiu Lun Cheung, Mr Chi Man Poon | E27: 45744 | F27: 18 | G27: =IFERROR(SUMPRODUCT((RENT_DUE!$B$2:$B$1000="LEASE-BH-F28-2025")*(RENT_DUE!$D$2:$D$1000>=DATE(2025,3,22))*(RENT_DUE!$D$2:$D$1000<=DATE(2025,4,21))*RENT_DUE!$L$2:$L$1000), 0) -> 0 | H27: =IFERROR(SUMPRODUCT((RENT_RECEIVED!$B$2:$B$1000="LEASE-BH-F28-2025")*(RENT_RECEIVED!$E$2:$E$1000>=DATE(2025,3,22))*(RENT_RECEIVED!$E$2:$E$1000<=DATE(2025,4,21))*RENT_RECEIVED!$O$2:$O$1000), 0) -> 0 | I27: HIST-2025-04-1532 | J27: =IFERROR(SUMIFS(RENT_DUE!$L$2:$L$10000, RENT_DUE!$B$2:$B$10000, "LEASE-BH-F28-2025", RENT_DUE!$D$2:$D$10000, "<"&DATE(2025,3,22)), 0) - IFERROR(SUMIFS(RENT_RECEIVED!$O$2:$O$10000, RENT_RECEIVED!$B$2:$B$10000, "LEASE-BH-F28-2025", RENT_RECEIVED!$E$2:$E$10000, "<"&DATE(2025,3,22)), 0) -> 0 | K27: =G27 - H27 -> 0 | L27: =J27 + K27 -> 0 | M27: =H27 * 0.1500 -> 0 | N27: =H27 * 0.0000 -> 0 | O27: =ABS(M27 + N27) -> 0 | Q27: =SUMIFS(EXPENSES!E:E, EXPENSES!B:B, "LEASE-BH-F28-2025", EXPENSES!D:D, ">="&DATE(2025,3,22), EXPENSES!D:D, "<="&DATE(2025,4,21)) -> 0 | S27: =H27 - O27 - Q27 -> 0 | Y27: 0 | Z27: =S27-Y27 -> 0 | AA27: PAID | AB27: HIST-2025-10-1650 | AC27: 45951
A28: LEASE-BH-F29-2025 | B28: Flat 29 - 3 West Gate | C28: Achal (Delegated for Udayan) | D28: Mrs Margaret Fritchley | E28: 45715 | F28: 27 | G28: =IFERROR(SUMPRODUCT((RENT_DUE!$B$2:$B$1000="LEASE-BH-F29-2025")*(RENT_DUE!$D$2:$D$1000>=DATE(2025,3,22))*(RENT_DUE!$D$2:$D$1000<=DATE(2025,4,21))*RENT_DUE!$L$2:$L$1000), 0) -> 0 | H28: =IFERROR(SUMPRODUCT((RENT_RECEIVED!$B$2:$B$1000="LEASE-BH-F29-2025")*(RENT_RECEIVED!$E$2:$E$1000>=DATE(2025,3,22))*(RENT_RECEIVED!$E$2:$E$1000<=DATE(2025,4,21))*RENT_RECEIVED!$O$2:$O$1000), 0) -> 0 | I28: HIST-2025-04-1532 | J28: =IFERROR(SUMIFS(RENT_DUE!$L$2:$L$10000, RENT_DUE!$B$2:$B$10000, "LEASE-BH-F29-2025", RENT_DUE!$D$2:$D$10000, "<"&DATE(2025,3,22)), 0) - IFERROR(SUMIFS(RENT_RECEIVED!$O$2:$O$10000, RENT_RECEIVED!$B$2:$B$10000, "LEASE-BH-F29-2025", RENT_RECEIVED!$E$2:$E$10000, "<"&DATE(2025,3,22)), 0) -> 0 | K28: =G28 - H28 -> 0 | L28: =J28 + K28 -> 0 | M28: =H28 * 0.1500 -> 0 | N28: =H28 * 0.0000 -> 0 | O28: =ABS(M28 + N28) -> 0 | Q28: =SUMIFS(EXPENSES!E:E, EXPENSES!B:B, "LEASE-BH-F29-2025", EXPENSES!D:D, ">="&DATE(2025,3,22), EXPENSES!D:D, "<="&DATE(2025,4,21)) -> 0 | S28: =H28 - O28 - Q28 -> 0 | Y28: 5541 | Z28: =S28-Y28 -> 0 | AA28: PAID | AB28: MULTIPLE | AC28: 45982
A29: LEASE-BH-F30-2025 | B29: Flat 30 - 3 West Gate | C29: Achal (Delegated for Udayan) | D29: Mr Joel Bryan | E29: 45722 | F29: 6 | G29: =IFERROR(SUMPRODUCT((RENT_DUE!$B$2:$B$1000="LEASE-BH-F30-2025")*(RENT_DUE!$D$2:$D$1000>=DATE(2025,3,22))*(RENT_DUE!$D$2:$D$1000<=DATE(2025,4,21))*RENT_DUE!$L$2:$L$1000), 0) -> 0 | H29: =IFERROR(SUMPRODUCT((RENT_RECEIVED!$B$2:$B$1000="LEASE-BH-F30-2025")*(RENT_RECEIVED!$E$2:$E$1000>=DATE(2025,3,22))*(RENT_RECEIVED!$E$2:$E$1000<=DATE(2025,4,21))*RENT_RECEIVED!$O$2:$O$1000), 0) -> 0 | I29: HIST-2025-04-1532 | J29: =IFERROR(SUMIFS(RENT_DUE!$L$2:$L$10000, RENT_DUE!$B$2:$B$10000, "LEASE-BH-F30-2025", RENT_DUE!$D$2:$D$10000, "<"&DATE(2025,3,22)), 0) - IFERROR(SUMIFS(RENT_RECEIVED!$O$2:$O$10000, RENT_RECEIVED!$B$2:$B$10000, "LEASE-BH-F30-2025", RENT_RECEIVED!$E$2:$E$10000, "<"&DATE(2025,3,22)), 0) -> 0 | K29: =G29 - H29 -> 0 | L29: =J29 + K29 -> 0 | M29: =H29 * 0.1500 -> 0 | N29: =H29 * 0.0000 -> 0 | O29: =ABS(M29 + N29) -> 0 | Q29: =SUMIFS(EXPENSES!E:E, EXPENSES!B:B, "LEASE-BH-F30-2025", EXPENSES!D:D, ">="&DATE(2025,3,22), EXPENSES!D:D, "<="&DATE(2025,4,21)) -> 0 | S29: =H29 - O29 - Q29 -> 0 | Y29: 5032 | Z29: =S29-Y29 -> 0 | AA29: PAID | AB29: MULTIPLE | AC29: 45992
A30: LEASE-KH-F-2024 | B30: Apartment F - Knighton Hayes Manor | C30: Achal (Delegated for Udayan) | D30: Mr Riaz Hamid, Ismat Tarr-Hamid | E30: 45648 | F30: 22 | G30: =IFERROR(SUMPRODUCT((RENT_DUE!$B$2:$B$1000="LEASE-KH-F-2024")*(RENT_DUE!$D$2:$D$1000>=DATE(2025,3,22))*(RENT_DUE!$D$2:$D$1000<=DATE(2025,4,21))*RENT_DUE!$L$2:$L$1000), 0) -> 0 | H30: =IFERROR(SUMPRODUCT((RENT_RECEIVED!$B$2:$B$1000="LEASE-KH-F-2024")*(RENT_RECEIVED!$E$2:$E$1000>=DATE(2025,3,22))*(RENT_RECEIVED!$E$2:$E$1000<=DATE(2025,4,21))*RENT_RECEIVED!$O$2:$O$1000), 0) -> 0 | I30: HIST-2025-04-1532 | J30: =IFERROR(SUMIFS(RENT_DUE!$L$2:$L$10000, RENT_DUE!$B$2:$B$10000, "LEASE-KH-F-2024", RENT_DUE!$D$2:$D$10000, "<"&DATE(2025,3,22)), 0) - IFERROR(SUMIFS(RENT_RECEIVED!$O$2:$O$10000, RENT_RECEIVED!$B$2:$B$10000, "LEASE-KH-F-2024", RENT_RECEIVED!$E$2:$E$10000, "<"&DATE(2025,3,22)), 0) -> 0 | K30: =G30 - H30 -> 0 | L30: =J30 + K30 -> 0 | M30: =H30 * 0.1000 -> 0 | N30: =H30 * 0.0000 -> 0 | O30: =ABS(M30 + N30) -> 0 | Q30: =SUMIFS(EXPENSES!E:E, EXPENSES!B:B, "LEASE-KH-F-2024", EXPENSES!D:D, ">="&DATE(2025,3,22), EXPENSES!D:D, "<="&DATE(2025,4,21)) -> 0 | S30: =H30 - O30 - Q30 -> 0 | Y30: 12150 | Z30: =S30-Y30 -> 0 | AA30: PAID | AB30: MULTIPLE | AC30: 45982
A31: BODEN-BLOCK-2025 | B31: Boden House Block - Block Property | C31: Achal (Delegated for Udayan) | D31: Prestvale Properties Limited | E31: 45717 | F31: 1 | G31: =IFERROR(SUMPRODUCT((RENT_DUE!$B$2:$B$1000="BODEN-BLOCK-2025")*(RENT_DUE!$D$2:$D$1000>=DATE(2025,3,22))*(RENT_DUE!$D$2:$D$1000<=DATE(2025,4,21))*RENT_DUE!$L$2:$L$1000), 0) -> 0 | H31: =IFERROR(SUMPRODUCT((RENT_RECEIVED!$B$2:$B$1000="BODEN-BLOCK-2025")*(RENT_RECEIVED!$E$2:$E$1000>=DATE(2025,3,22))*(RENT_RECEIVED!$E$2:$E$1000<=DATE(2025,4,21))*RENT_RECEIVED!$O$2:$O$1000), 0) -> 0 | J31: =IFERROR(SUMIFS(RENT_DUE!$L$2:$L$10000, RENT_DUE!$B$2:$B$10000, "BODEN-BLOCK-2025", RENT_DUE!$D$2:$D$10000, "<"&DATE(2025,3,22)), 0) - IFERROR(SUMIFS(RENT_RECEIVED!$O$2:$O$10000, RENT_RECEIVED!$B$2:$B$10000, "BODEN-BLOCK-2025", RENT_RECEIVED!$E$2:$E$10000, "<"&DATE(2025,3,22)), 0) -> 0 | K31: =G31 - H31 -> 0 | L31: =J31 + K31 -> 0 | M31: =H31 * 0.0000 -> 0 | N31: =H31 * 0.0500 -> 0 | O31: =ABS(M31 + N31) -> 0 | Q31: =SUMIFS(EXPENSES!E:E, EXPENSES!B:B, "BODEN-BLOCK-2025", EXPENSES!D:D, ">="&DATE(2025,3,22), EXPENSES!D:D, "<="&DATE(2025,4,21)) -> 0 | R31: HIST-2025-04-1533 | S31: =H31 - O31 - Q31 -> 0 | T31: Boden House NG10 | U31: =IFERROR(SUMIFS(PROPERTY_ACCOUNT!D:D, PROPERTY_ACCOUNT!A:A, T31, PROPERTY_ACCOUNT!B:B, "opening"), 0) -> 0 | V31: =IFERROR(SUMIFS(PROPERTY_ACCOUNT!D:D, PROPERTY_ACCOUNT!A:A, T31, PROPERTY_ACCOUNT!B:B, "in"), 0) -> 0 | W31: =IFERROR(SUMIFS(PROPERTY_ACCOUNT!D:D, PROPERTY_ACCOUNT!A:A, T31, PROPERTY_ACCOUNT!B:B, "out"), 0) -> 0 | X31: =U31 + V31 - W31 -> 0 | Y31: 0 | Z31: =S31-Y31 -> 0 | AA31: PAID | AB31: MULTIPLE | AC31: 45993
A32: TOTALS | G32: =SUM(G2:G31) -> 0 | H32: =SUM(H2:H31) -> 0 | J32: =SUM(J2:J31) -> 0 | K32: =SUM(K2:K31) -> 0 | L32: =SUM(L2:L31) -> 0 | M32: =SUM(M2:M31) -> 0 | N32: =SUM(N2:N31) -> 0 | O32: =SUM(O2:O31) -> 0 | Q32: =SUM(Q2:Q31) -> 0 | S32: =SUM(S2:S31) -> 0 | U32: =SUM(U2:U31) -> 0 | V32: =SUM(V2:V31) -> 0 | W32: =SUM(W2:W31) -> 0 | X32: =SUM(X2:X31) -> 0
A34: PAYMENT RECONCILIATION
A35: Period: 2025-03-22 to 2025-04-21
A37: BROUGHT FORWARD (items from prior periods paid this period)
A38: Prior Period Income:
A39: 2025-02-19 | Flat 15 - 3 West Gate | rent | B39: 230.5
A40: 2025-02-20 | Flat 17 - 3 West Gate | rent | B40: 595
A41: 2025-02-20 | Flat 24 - 3 West Gate | rent | B41: 688.5
A42: 2025-02-24 | Apartment F - Knighton Hayes Manor | rent | B42: 1012.5
A43: 2025-02-28 | Flat 22 - 3 West Gate | rent | B43: 629
A44: 2025-02-28 | Flat 26 - 3 West Gate | rent | B44: 573.75
A45: 2025-03-02 | Flat 11 - 3 West Gate | rent | B45: 675.75
A46: 2025-03-03 | Flat 19 - 3 West Gate | rent | B46: 629
A47: 2025-03-03 | Flat 2 - 3 West Gate | rent | B47: 629
A48: 2025-03-03 | Flat 27 - 3 West Gate | rent | B48: 595
A49: 2025-03-03 | Flat 29 - 3 West Gate | rent | B49: 629
A50: 2025-03-03 | Flat 4 - 3 West Gate | rent | B50: 726.75
... A68: Prior Period Income Total (29 items): | B68: 18698.75
A69: Prior Period Expenses: None
A70: NET B/F (Income - Expenses): | B70: 18698.75
A72: THIS PERIOD ACTIVITY (see transactions above for details)
A73: Period Income (2 transactions) | B73: 846.5
A74: Period Expenses (2 transactions) | B74: 288.38
A75: Net Activity (Income - Expenses): | B75: 558.12
A77: PAYMENTS MADE THIS PERIOD
A78: HIST-2025-03-1501 (2025-03-23) | B78: 14606.25
A79: Covers: 28 income (£17686.25) = £17686.25
A80: HIST-2025-03-1502 (2025-03-25) | B80: 1012.5
A81: Covers: 1 income (£1012.50) = £1012.50
A82: HIST-2025-04-1533 (2025-04-18) | B82: 558.12
A83: Covers: 2 income (£846.50) - 2 expenses (£288.38) = £558.12
A84: Total Payments Made: | B84: 16176.87
A85: (See PAYMENT_ALLOCATIONS sheet for full details)
A87: SUMMARY
A88: Total Allocated (Income - Expenses): | B88: 19256.87
A89: Total Payments Made: | B89: 16176.87
A90: Unallocated Payment Amounts: | B90: 0
A92: Check: Allocated 19256.87 + Unallocated 0.00 = 19256.87 vs Payments 16176.87
A93: Variance: -3080.00 (check allocations)

Sheet Apr 22 - May 21, 2025
A1: lease_reference | B1: property_name | C1: customer_name | D1: tenant_name | E1: lease_start_date | F1: rent_due_day | G1: rent_due | H1: rent_received | I1: rent_batch | J1: opening_balance | K1: period_arrears | L1: closing_balance | M1: management_fee | N1: service_fee | O1: total_commission | P1: commission_batch | Q1: total_expenses | R1: expenses_batch | S1: net_to_owner | T1: block_name | U1: property_account_opening | V1: property_account_in | W1: property_account_out | X1: property_account_closing | Y1: allocated_amount | Z1: variance | AA1: allocation_status | AB1: batch_id | AC1: paid_date
A2: LEASE-BH-F1-2025 | B2: Flat 1 - 3 West Gate | C2: Achal (Delegated for Udayan) | D2: Ms Oleksandra Smoliarenko, Mr Illia Halii | E2: 45715 | F2: 27 | G2: =IFERROR(SUMPRODUCT((RENT_DUE!$B$2:$B$1000="LEASE-BH-F1-2025")*(RENT_DUE!$D$2:$D$1000>=DATE(2025,4,22))*(RENT_DUE!$D$2:$D$1000<=DATE(2025,5,21))*RENT_DUE!$L$2:$L$1000), 0) -> 0 | H2: =IFERROR(SUMPRODUCT((RENT_RECEIVED!$B$2:$B$1000="LEASE-BH-F1-2025")*(RENT_RECEIVED!$E$2:$E$1000>=DATE(2025,4,22))*(RENT_RECEIVED!$E$2:$E$1000<=DATE(2025,5,21))*RENT_RECEIVED!$O$2:$O$1000), 0) -> 0 | I2: HIST-2025-05-1564 | J2: =IFERROR(SUMIFS(RENT_DUE!$L$2:$L$10000, RENT_DUE!$B$2:$B$10000, "LEASE-BH-F1-2025", RENT_DUE!$D$2:$D$10000, "<"&DATE(2025,4,22)), 0) - IFERROR(SUMIFS(RENT_RECEIVED!$O$2:$O$10000, RENT_RECEIVED!$B$2:$B$10000, "LEASE-BH-F1-2025", RENT_RECEIVED!$E$2:$E$10000, "<"&DATE(2025,4,22)), 0) -> 0 | K2: =G2 - H2 -> 0 | L2: =J2 + K2 -> 0 | M2: =H2 * 0.1500 -> 0 | N2: =H2 * 0.0000 -> 0 | O2: =ABS(M2 + N2) -> 0 | Q2: =SUMIFS(EXPENSES!E:E, EXPENSES!B:B, "LEASE-BH-F1-2025", EXPENSES!D:D, ">="&DATE(2025,4,22), EXPENSES!D:D, "<="&DATE(2025,5,21)) -> 0 | S2: =H2 - O2 - Q2 -> 0 | Y2: 5985.52 | Z2: =S2-Y2 -> 0 | AA2: PAID | AB2: MULTIPLE | AC2: 45992
A3: LEASE-BH-F2-2025 | B3: Flat 2 - 3 West Gate | C3: Achal (Delegated for Udayan) | D3: Mr Mustafa Al Bayat, Mrs Gulala Al - Zangana | E3: 45715 | F3: 27 | G3: =IFERROR(SUMPRODUCT((RENT_DUE!$B$2:$B$1000="LEASE-BH-F2-2025")*(RENT_DUE!$D$2:$D$1000>=DATE(2025,4,22))*(RENT_DUE!$D$2:$D$1000<=DATE(2025,5,21))*RENT_DUE!$L$2:$L$1000), 0) -> 0 | H3: =IFERROR(SUMPRODUCT((RENT_RECEIVED!$B$2:$B$1000="LEASE-BH-F2-2025")*(RENT_RECEIVED!$E$2:$E$1000>=DATE(2025,4,22))*(RENT_RECEIVED!$E$2:$E$1000<=DATE(2025,5,21))*RENT_RECEIVED!$O$2:$O$1000), 0) -> 0 | I3: HIST-2025-05-1564 | J3: =IFERROR(SUMIFS(RENT_DUE!$L$2:$L$10000, RENT_DUE!$B$2:$B$10000, "LEASE-BH-F2-2025", RENT_DUE!$D$2:$D$10000, "<"&DATE(2025,4,22)), 0) - IFERROR(SUMIFS(RENT_RECEIVED!$O$2:$O$10000, RENT_RECEIVED!$B$2:$B$10000, "LEASE-BH-F2-2025", RENT_RECEIVED!$E$2:$E$10000, "<"&DATE(2025,4,22)), 0) -> 0 | K3: =G3 - H3 -> 0 | L3: =J3 + K3 -> 0 | M3: =H3 * 0.1500 -> 0 | N3: =H3 * 0.0000 -> 0 | O3: =ABS(M3 + N3) -> 0 | Q3: =SUMIFS(EXPENSES!E:E, EXPENSES!B:B, "LEASE-BH-F2-2025", EXPENSES!D:D, ">="&DATE(2025,4,22), EXPENSES!D:D, "<="&DATE(2025,5,21)) -> 0 | S3: =H3 - O3 - Q3 -> 0 | Y3: 5661 | Z3: =S3-Y3 -> 0 | AA3: PAID | AB3: MULTIPLE | AC3: 45992
A4: LEASE-BH-F3-2025 | B4: Flat 3 - 3 West Gate | C4: Achal (Delegated for Udayan) | D4: Mr Tracy Whyte | E4: 45727 | F4: 11 | G4: =IFERROR(SUMPRODUCT((RENT_DUE!$B$2:$B$1000="LEASE-BH-F3-2025")*(RENT_DUE!$D$2:$D$1000>=DATE(2025,4,22))*(RENT_DUE!$D$2:$D$1000<=DATE(2025,5,21))*RENT_DUE!$L$2:$L$1000), 0) -> 0 | H4: =IFERROR(SUMPRODUCT((RENT_RECEIVED!$B$2:$B$1000="LEASE-BH-F3-2025")*(RENT_RECEIVED!$E$2:$E$1000>=DATE(2025,4,22))*(RENT_RECEIVED!$E$2:$E$1000<=DATE(2025,5,21))*RENT_RECEIVED!$O$2:$O$1000), 0) -> 0 | I4: HIST-2025-05-1564 | J4: =IFERROR(SUMIFS(RENT_DUE!$L$2:$L$10000, RENT_DUE!$B$2:$B$10000, "LEASE-BH-F3-2025", RENT_DUE!$D$2:$D$10000, "<"&DATE(2025,4,22)), 0) - IFERROR(SUMIFS(RENT_RECEIVED!$O$2:$O$10000, RENT_RECEIVED!$B$2:$B$10000, "LEASE-BH-F3-2025", RENT_RECEIVED!$E$2:$E$10000, "<"&DATE(2025,4,22)), 0) -> 0 | K4: =G4 - H4 -> 0 | L4: =J4 + K4 -> 0 | M4: =H4 * 0.1500 -> 0 | N4: =H4 * 0.0000 -> 0 | O4: =ABS(M4 + N4) -> 0 | Q4: =SUMIFS(EXPENSES!E:E, EXPENSES!B:B, "LEASE-BH-F3-2025", EXPENSES!D:D, ">="&DATE(2025,4,22), EXPENSES!D:D, "<="&DATE(2025,5,21)) -> 0 | S4: =H4 - O4 - Q4 -> 0 | Y4: 5661 | Z4: =S4-Y4 -> 0 | AA4: PAID | AB4: MULTIPLE | AC4: 45992
A5: LEASE-BH-F4-2025 | B5: Flat 4 - 3 West Gate | C5: Achal (Delegated for Udayan) | D5: Miss Megan Delaney, Mr Joseph Williams | E5: 45713 | F5: 25 | G5: =IFERROR(SUMPRODUCT((RENT_DUE!$B$2:$B$1000="LEASE-BH-F4-2025")*(RENT_DUE!$D$2:$D$1000>=DATE(2025,4,22))*(RENT_DUE!$D$2:$D$1000<=DATE(2025,5,21))*RENT_DUE!$L$2:$L$1000), 0) -> 0 | H5: =IFERROR(SUMPRODUCT((RENT_RECEIVED!$B$2:$B$1000="LEASE-BH-F4-2025")*(RENT_RECEIVED!$E$2:$E$1000>=DATE(2025,4,22))*(RENT_RECEIVED!$E$2:$E$1000<=DATE(2025,5,21))*RENT_RECEIVED!$O$2:$O$1000), 0) -> 0 | I5: HIST-2025-05-1564 | J5: =IFERROR(SUMIFS(RENT_DUE!$L$2:$L$10000, RENT_DUE!$B$2:$B$10000, "LEASE-BH-F4-2025", RENT_DUE!$D$2:$D$10000, "<"&DATE(2025,4,22)), 0) - IFERROR(SUMIFS(RENT_RECEIVED!$O$2:$O$10000, RENT_RECEIVED!$B$2:$B$10000, "LEASE-BH-F4-2025", RENT_RECEIVED!$E$2:$E$10000, "<"&DATE(2025,4,22)), 0) -> 0 | K5: =G5 - H5 -> 0 | L5: =J5 + K5 -> 0 | M5: =H5 * 0.1500 -> 0 | N5: =H5 * 0.0000 -> 0 | O5: =ABS(M5 + N5) -> 0 | Q5: =SUMIFS(EXPENSES!E:E, EXPENSES!B:B, "LEASE-BH-F4-2025", EXPENSES!D:D, ">="&DATE(2025,4,22), EXPENSES!D:D, "<="&DATE(2025,5,21)) -> 0 | S5: =H5 - O5 - Q5 -> 0 | Y5: 6390.75 | Z5: =S5-Y5 -> 0 | AA5: PAID | AB5: MULTIPLE | AC5: 45982
A6: LEASE-BH-F5-2025 | B6: Flat 5 - 3 West Gate | C6: Achal (Delegated for Udayan) | D6: Mr Amos Blyth | E6: 45698 | F6: 10 | G6: =IFERROR(SUMPRODUCT((RENT_DUE!$B$2:$B$1000="LEASE-BH-F5-2025")*(RENT_DUE!$D$2:$D$1000>=DATE(2025,4,22))*(RENT_DUE!$D$2:$D$1000<=DATE(2025,5,21))*RENT_DUE!$L$2:$L$1000), 0) -> 0 | H6: =IFERROR(SUMPRODUCT((RENT_RECEIVED!$B$2:$B$1000="LEASE-BH-F5-2025")*(RENT_RECEIVED!$E$2:$E$1000>=DATE(2025,4,22))*(RENT_RECEIVED!$E$2:$E$1000<=DATE(2025,5,21))*RENT_RECEIVED!$O$2:$O$1000), 0) -> 0 | I6: HIST-2025-05-1564 | J6: =IFERROR(SUMIFS(RENT_DUE!$L$2:$L$10000, RENT_DUE!$B$2:$B$10000, "LEASE-BH-F5-2025", RENT_DUE!$D$2:$D$10000, "<"&DATE(2025,4,22)), 0) - IFERROR(SUMIFS(RENT_RECEIVED!$O$2:$O$10000, RENT_RECEIVED!$B$2:$B$10000, "LEASE-BH-F5-2025", RENT_RECEIVED!$E$2:$E$10000, "<"&DATE(2025,4,22)), 0) -> 0 | K6: =G6 - H6 -> 0 | L6: =J6 + K6 -> 0 | M6: =H6 * 0.1500 -> 0 | N6: =H6 * 0.0000 -> 0 | O6: =ABS(M6 + N6) -> 0 | Q6: =SUMIFS(EXPENSES!E:E, EXPENSES!B:B, "LEASE-BH-F5-2025", EXPENSES!D:D, ">="&DATE(2025,4,22), EXPENSES!D:D, "<="&DATE(2025,5,21)) -> 0 | S6: =H6 - O6 - Q6 -> 0 | Y6: 6140 | Z6: =S6-Y6 -> 0 | AA6: PAID | AB6: MULTIPLE | AC6: 45982
A7: LEASE-BH-F6-2025 | B7: Flat 6 - 3 West Gate | C7: Achal (Delegated for Udayan) | D7: Miss Shelley Lees | E7: 45744 | F7: 28 | G7: =IFERROR(SUMPRODUCT((RENT_DUE!$B$2:$B$1000="LEASE-BH-F6-2025")*(RENT_DUE!$D$2:$D$1000>=DATE(2025,4,22))*(RENT_DUE!$D$2:$D$1000<=DATE(2025,5,21))*RENT_DUE!$L$2:$L$1000), 0) -> 0 | H7: =IFERROR(SUMPRODUCT((RENT_RECEIVED!$B$2:$B$1000="LEASE-BH-F6-2025")*(RENT_RECEIVED!$E$2:$E$1000>=DATE(2025,4,22))*(RENT_RECEIVED!$E$2:$E$1000<=DATE(2025,5,21))*RENT_RECEIVED!$O$2:$O$1000), 0) -> 0 | I7: HIST-2025-04-1532 | J7: =IFERROR(SUMIFS(RENT_DUE!$L$2:$L$10000, RENT_DUE!$B$2:$B$10000, "LEASE-BH-F6-2025", RENT_DUE!$D$2:$D$10000, "<"&DATE(2025,4,22)), 0) - IFERROR(SUMIFS(RENT_RECEIVED!$O$2:$O$10000, RENT_RECEIVED!$B$2:$B$10000, "LEASE-BH-F6-2025", RENT_RECEIVED!$E$2:$E$10000, "<"&DATE(2025,4,22)), 0) -> 0 | K7: =G7 - H7 -> 0 | L7: =J7 + K7 -> 0 | M7: =H7 * 0.1500 -> 0 | N7: =H7 * 0.0000 -> 0 | O7: =ABS(M7 + N7) -> 0 | Q7: =SUMIFS(EXPENSES!E:E, EXPENSES!B:B, "LEASE-BH-F6-2025", EXPENSES!D:D, ">="&DATE(2025,4,22), EXPENSES!D:D, "<="&DATE(2025,5,21)) -> 0 | S7: =H7 - O7 - Q7 -> 0 | Y7: 4882 | Z7: =S7-Y7 -> 0 | AA7: PAID | AB7: MULTIPLE | AC7: 45982
A8: LEASE-BH-F7-2025 | B8: Flat 7 - 3 West Gate | C8: Achal (Delegated for Udayan) | D8: Mr Chun Hung Tang | E8: 45707 | F8: 19 | G8: =IFERROR(SUMPRODUCT((RENT_DUE!$B$2:$B$1000="LEASE-BH-F7-2025")*(RENT_DUE!$D$2:$D$1000>=DATE(2025,4,22))*(RENT_DUE!$D$2:$D$1000<=DATE(2025,5,21))*RENT_DUE!$L$2:$L$1000), 0) -> 0 | H8: =IFERROR(SUMPRODUCT((RENT_RECEIVED!$B$2:$B$1000="LEASE-BH-F7-2025")*(RENT_RECEIVED!$E$2:$E$1000>=DATE(2025,4,22))*(RENT_RECEIVED!$E$2:$E$1000<=DATE(2025,5,21))*RENT_RECEIVED!$O$2:$O$1000), 0) -> 0 | I8: HIST-2025-05-1564 | J8: =IFERROR(SUMIFS(RENT_DUE!$L$2:$L$10000, RENT_DUE!$B$2:$B$10000, "LEASE-BH-F7-2025", RENT_DUE!$D$2:$D$10000, "<"&DATE(2025,4,22)), 0) - IFERROR(SUMIFS(RENT_RECEIVED!$O$2:$O$10000, RENT_RECEIVED!$B$2:$B$10000, "LEASE-BH-F7-2025", RENT_RECEIVED!$E$2:$E$10000, "<"&DATE(2025,4,22)), 0) -> 0 | K8: =G8 - H8 -> 0 | L8: =J8 + K8 -> 0 | M8: =H8 * 0.1500 -> 0 | N8: =H8 * 0.0000 -> 0 | O8: =ABS(M8 + N8) -> 0 | Q8: =SUMIFS(EXPENSES!E:E, EXPENSES!B:B, "LEASE-BH-F7-2025", EXPENSES!D:D, ">="&DATE(2025,4,22), EXPENSES!D:D, "<="&DATE(2025,5,21)) -> 0 | S8: =H8 - O8 - Q8 -> 0 | Y8: 3570 | Z8: =S8-Y8 -> 0 | AA8: PAID | AB8: MULTIPLE | AC8: 45861
A9: LEASE-BH-F8-2025 | B9: Flat 8 - 3 West Gate | C9: Achal (Delegated for Udayan) | D9: Mr Shermal Wijesinghage, Mrs Udeshika Dona | E9: 45712 | F9: 24 | G9: =IFERROR(SUMPRODUCT((RENT_DUE!$B$2:$B$1000="LEASE-BH-F8-2025")*(RENT_DUE!$D$2:$D$1000>=DATE(2025,4,22))*(RENT_DUE!$D$2:$D$1000<=DATE(2025,5,21))*RENT_DUE!$L$2:$L$1000), 0) -> 0 | H9: =IFERROR(SUMPRODUCT((RENT_RECEIVED!$B$2:$B$1000="LEASE-BH-F8-2025")*(RENT_RECEIVED!$E$2:$E$1000>=DATE(2025,4,22))*(RENT_RECEIVED!$E$2:$E$1000<=DATE(2025,5,21))*RENT_RECEIVED!$O$2:$O$1000), 0) -> 0 | I9: HIST-2025-05-1564 | J9: =IFERROR(SUMIFS(RENT_DUE!$L$2:$L$10000, RENT_DUE!$B$2:$B$10000, "LEASE-BH-F8-2025", RENT_DUE!$D$2:$D$10000, "<"&DATE(2025,4,22)), 0) - IFERROR(SUMIFS(RENT_RECEIVED!$O$2:$O$10000, RENT_RECEIVED!$B$2:$B$10000, "LEASE-BH-F8-2025", RENT_RECEIVED!$E$2:$E$10000, "<"&DATE(2025,4,22)), 0) -> 0 | K9: =G9 - H9 -> 0 | L9: =J9 + K9 -> 0 | M9: =H9 * 0.1500 -> 0 | N9: =H9 * 0.0000 -> 0 | O9: =ABS(M9 + N9) -> 0 | Q9: =SUMIFS(EXPENSES!E:E, EXPENSES!B:B, "LEASE-BH-F8-2025", EXPENSES!D:D, ">="&DATE(2025,4,22), EXPENSES!D:D, "<="&DATE(2025,5,21)) -> 0 | S9: =H9 - O9 - Q9 -> 0 | Y9: 5318.75 | Z9: =S9-Y9 -> 0 | AA9: PAID | AB9: MULTIPLE | AC9: 45982
A10: LEASE-BH-F9-2025 | B10: Flat 9 - 3 West Gate | C10: Achal (Delegated for Udayan) | D10: Mr Scott Warner | E10: 45736 | F10: 20 | G10: =IFERROR(SUMPRODUCT((RENT_DUE!$B$2:$B$1000="LEASE-BH-F9-2025")*(RENT_DUE!$D$2:$D$1000>=DATE(2025,4,22))*(RENT_DUE!$D$2:$D$1000<=DATE(2025,5,21))*RENT_DUE!$L$2:$L$1000), 0) -> 0 | H10: =IFERROR(SUMPRODUCT((RENT_RECEIVED!$B$2:$B$1000="LEASE-BH-F9-2025")*(RENT_RECEIVED!$E$2:$E$1000>=DATE(2025,4,22))*(RENT_RECEIVED!$E$2:$E$1000<=DATE(2025,5,21))*RENT_RECEIVED!$O$2:$O$1000), 0) -> 0 | I10: HIST-2025-05-1564 | J10: =IFERROR(SUMIFS(RENT_DUE!$L$2:$L$10000, RENT_DUE!$B$2:$B$10000, "LEASE-BH-F9-2025", RENT_DUE!$D$2:$D$10000, "<"&DATE(2025,4,22)), 0) - IFERROR(SUMIFS(RENT_RECEIVED!$O$2:$O$10000, RENT_RECEIVED!$B$2:$B$10000, "LEASE-BH-F9-2025", RENT_RECEIVED!$E$2:$E$10000, "<"&DATE(2025,4,22)), 0) -> 0 | K10: =G10 - H10 -> 0 | L10: =J10 + K10 -> 0 | M10: =H10 * 0.1500 -> 0 | N10: =H10 * 0.0000 -> 0 | O10: =ABS(M10 + N10) -> 0 | Q10: =SUMIFS(EXPENSES!E:E, EXPENSES!B:B, "LEASE-BH-F9-2025", EXPENSES!D:D, ">="&DATE(2025,4,22), EXPENSES!D:D, "<="&DATE(2025,5,21)) -> 0 | S10: =H10 - O10 - Q10 -> 0 | Y10: 5255 | Z10: =S10-Y10 -> 0 | AA10: PAID | AB10: MULTIPLE | AC10: 45982
A11: LEASE-BH-F10-2025 | B11: Flat 10 - 3 West Gate | C11: Achal (Delegated for Udayan) | D11: Mr Ferenc Peter | E11: 45722 | F11: 6 | G11: =IFERROR(SUMPRODUCT((RENT_DUE!$B$2:$B$1000="LEASE-BH-F10-2025")*(RENT_DUE!$D$2:$D$1000>=DATE(2025,4,22))*(RENT_DUE!$D$2:$D$1000<=DATE(2025,5,21))*RENT_DUE!$L$2:$L$1000), 0) -> 0 | H11: =IFERROR(SUMPRODUCT((RENT_RECEIVED!$B$2:$B$1000="LEASE-BH-F10-2025")*(RENT_RECEIVED!$E$2:$E$1000>=DATE(2025,4,22))*(RENT_RECEIVED!$E$2:$E$1000<=DATE(2025,5,21))*RENT_RECEIVED!$O$2:$O$1000), 0) -> 0 | I11: HIST-2025-05-1564 | J11: =IFERROR(SUMIFS(RENT_DUE!$L$2:$L$10000, RENT_DUE!$B$2:$B$10000, "LEASE-BH-F10-2025", RENT_DUE!$D$2:$D$10000, "<"&DATE(2025,4,22)), 0) - IFERROR(SUMIFS(RENT_RECEIVED!$O$2:$O$10000, RENT_RECEIVED!$B$2:$B$10000, "LEASE-BH-F10-2025", RENT_RECEIVED!$E$2:$E$10000, "<"&DATE(2025,4,22)), 0) -> 0 | K11: =G11 - H11 -> 0 | L11: =J11 + K11 -> 0 | M11: =H11 * 0.1500 -> 0 | N11: =H11 * 0.0000 -> 0 | O11: =ABS(M11 + N11) -> 0 | Q11: =SUMIFS(EXPENSES!E:E, EXPENSES!B:B, "LEASE-BH-F10-2025", EXPENSES!D:D, ">="&DATE(2025,4,22), EXPENSES!D:D, "<="&DATE(2025,5,21)) -> 0 | S11: =H11 - O11 - Q11 -> 0 | Y11: 3534.47 | Z11: =S11-Y11 -> 0 | AA11: PAID | AB11: MULTIPLE | AC11: 45920
A12: LEASE-BH-F11-2025 | B12: Flat 11 - 3 West Gate | C12: Achal (Delegated for Udayan) | D12: Mr Richard Perrotta | E12: 45722 | F12: 26 | G12: =IFERROR(SUMPRODUCT((RENT_DUE!$B$2:$B$1000="LEASE-BH-F11-2025")*(RENT_DUE!$D$2:$D$1000>=DATE(2025,4,22))*(RENT_DUE!$D$2:$D$1000<=DATE(2025,5,21))*RENT_DUE!$L$2:$L$1000), 0) -> 0 | H12: =IFERROR(SUMPRODUCT((RENT_RECEIVED!$B$2:$B$1000="LEASE-BH-F11-2025")*(RENT_RECEIVED!$E$2:$E$1000>=DATE(2025,4,22))*(RENT_RECEIVED!$E$2:$E$1000<=DATE(2025,5,21))*RENT_RECEIVED!$O$2:$O$1000), 0) -> 0 | I12: HIST-2025-05-1564 | J12: =IFERROR(SUMIFS(RENT_DUE!$L$2:$L$10000, RENT_DUE!$B$2:$B$10000, "LEASE-BH-F11-2025", RENT_DUE!$D$2:$D$10000, "<"&DATE(2025,4,22)), 0) - IFERROR(SUMIFS(RENT_RECEIVED!$O$2:$O$10000, RENT_RECEIVED!$B$2:$B$10000, "LEASE-BH-F11-2025", RENT_RECEIVED!$E$2:$E$10000, "<"&DATE(2025,4,22)), 0) -> 0 | K12: =G12 - H12 -> 0 | L12: =J12 + K12 -> 0 | M12: =H12 * 0.1500 -> 0 | N12: =H12 * 0.0000 -> 0 | O12: =ABS(M12 + N12) -> 0 | Q12: =SUMIFS(EXPENSES!E:E, EXPENSES!B:B, "LEASE-BH-F11-2025", EXPENSES!D:D, ">="&DATE(2025,4,22), EXPENSES!D:D, "<="&DATE(2025,5,21)) -> 0 | S12: =H12 - O12 - Q12 -> 0 | Y12: 5979.75 | Z12: =S12-Y12 -> 0 | AA12: PAID | AB12: MULTIPLE | AC12: 45981
A13: LEASE-BH-F12-2025 | B13: Flat 12 - 3 West Gate | C13: Achal (Delegated for Udayan) | D13: MR J SOOPIYADAKATH THEKKE PURAYIL & MS S | E13: 45754 | F13: 7 | G13: =IFERROR(SUMPRODUCT((RENT_DUE!$B$2:$B$1000="LEASE-BH-F12-2025")*(RENT_DUE!$D$2:$D$1000>=DATE(2025,4,22))*(RENT_DUE!$D$2:$D$1000<=DATE(2025,5,21))*RENT_DUE!$L$2:$L$1000), 0) -> 0 | H13: =IFERROR(SUMPRODUCT((RENT_RECEIVED!$B$2:$B$1000="LEASE-BH-F12-2025")*(RENT_RECEIVED!$E$2:$E$1000>=DATE(2025,4,22))*(RENT_RECEIVED!$E$2:$E$1000<=DATE(2025,5,21))*RENT_RECEIVED!$O$2:$O$1000), 0) -> 0 | I13: HIST-2025-05-1564 | J13: =IFERROR(SUMIFS(RENT_DUE!$L$2:$L$10000, RENT_DUE!$B$2:$B$10000, "LEASE-BH-F12-2025", RENT_DUE!$D$2:$D$10000, "<"&DATE(2025,4,22)), 0) - IFERROR(SUMIFS(RENT_RECEIVED!$O$2:$O$10000, RENT_RECEIVED!$B$2:$B$10000, "LEASE-BH-F12-2025", RENT_RECEIVED!$E$2:$E$10000, "<"&DATE(2025,4,22)), 0) -> 0 | K13: =G13 - H13 -> 0 | L13: =J13 + K13 -> 0 | M13: =H13 * 0.1500 -> 0 | N13: =H13 * 0.0000 -> 0 | O13: =ABS(M13 + N13) -> 0 | Q13: =SUMIFS(EXPENSES!E:E, EXPENSES!B:B, "LEASE-BH-F12-2025", EXPENSES!D:D, ">="&DATE(2025,4,22), EXPENSES!D:D, "<="&DATE(2025,5,21)) -> 0 | S13: =H13 - O13 - Q13 -> 0 | Y13: 1147.5 | Z13: =S13-Y13 -> 0 | AA13: PAID | AB13: MULTIPLE | AC13: 45804
A14: LEASE-BH-F13-2025 | B14: Flat 13 - 3 West Gate | C14: Achal (Delegated for Udayan) | D14: Mr Nathan Holland | E14: 45719 | F14: 3 | G14: =IFERROR(SUMPRODUCT((RENT_DUE!$B$2:$B$1000="LEASE-BH-F13-2025")*(RENT_DUE!$D$2:$D$1000>=DATE(2025,4,22))*(RENT_DUE!$D$2:$D$1000<=DATE(2025,5,21))*RENT_DUE!$L$2:$L$1000), 0) -> 0 | H14: =IFERROR(SUMPRODUCT((RENT_RECEIVED!$B$2:$B$1000="LEASE-BH-F13-2025")*(RENT_RECEIVED!$E$2:$E$1000>=DATE(2025,4,22))*(RENT_RECEIVED!$E$2:$E$1000<=DATE(2025,5,21))*RENT_RECEIVED!$O$2:$O$1000), 0) -> 0 | I14: HIST-2025-05-1564 | J14: =IFERROR(SUMIFS(RENT_DUE!$L$2:$L$10000, RENT_DUE!$B$2:$B$10000, "LEASE-BH-F13-2025", RENT_DUE!$D$2:$D$10000, "<"&DATE(2025,4,22)), 0) - IFERROR(SUMIFS(RENT_RECEIVED!$O$2:$O$10000, RENT_RECEIVED!$B$2:$B$10000, "LEASE-BH-F13-2025", RENT_RECEIVED!$E$2:$E$10000, "<"&DATE(2025,4,22)), 0) -> 0 | K14: =G14 - H14 -> 0 | L14: =J14 + K14 -> 0 | M14: =H14 * 0.1500 -> 0 | N14: =H14 * 0.0000 -> 0 | O14: =ABS(M14 + N14) -> 0 | Q14: =SUMIFS(EXPENSES!E:E, EXPENSES!B:B, "LEASE-BH-F13-2025", EXPENSES!D:D, ">="&DATE(2025,4,22), EXPENSES!D:D, "<="&DATE(2025,5,21)) -> 0 | S14: =H14 - O14 - Q14 -> 0 | Y14: 5440 | Z14: =S14-Y14 -> 0 | AA14: PAID | AB14: MULTIPLE | AC14: 45936
A15: LEASE-BH-F14-2025 | B15: Flat 14 - 3 West Gate | C15: Achal (Delegated for Udayan) | D15: Ms Sarah Buckle, Mr Matthew Lewsley | E15: 45744 | F15: 28 | G15: =IFERROR(SUMPRODUCT((RENT_DUE!$B$2:$B$1000="LEASE-BH-F14-2025")*(RENT_DUE!$D$2:$D$1000>=DATE(2025,4,22))*(RENT_DUE!$D$2:$D$1000<=DATE(2025,5,21))*RENT_DUE!$L$2:$L$1000), 0) -> 0 | H15: =IFERROR(SUMPRODUCT((RENT_RECEIVED!$B$2:$B$1000="LEASE-BH-F14-2025")*(RENT_RECEIVED!$E$2:$E$1000>=DATE(2025,4,22))*(RENT_RECEIVED!$E$2:$E$1000<=DATE(2025,5,21))*RENT_RECEIVED!$O$2:$O$1000), 0) -> 0 | I15: HIST-2025-04-1532 | J15: =IFERROR(SUMIFS(RENT_DUE!$L$2:$L$10000, RENT_DUE!$B$2:$B$10000, "LEASE-BH-F14-2025", RENT_DUE!$D$2:$D$10000, "<"&DATE(2025,4,22)), 0) - IFERROR(SUMIFS(RENT_RECEIVED!$O$2:$O$10000, RENT_RECEIVED!$B$2:$B$10000, "LEASE-BH-F14-2025", RENT_RECEIVED!$E$2:$E$10000, "<"&DATE(2025,4,22)), 0) -> 0 | K15: =G15 - H15 -> 0 | L15: =J15 + K15 -> 0 | M15: =H15 * 0.1500 -> 0 | N15: =H15 * 0.0000 -> 0 | O15: =ABS(M15 + N15) -> 0 | Q15: =SUMIFS(EXPENSES!E:E, EXPENSES!B:B, "LEASE-BH-F14-2025", EXPENSES!D:D, ">="&DATE(2025,4,22), EXPENSES!D:D, "<="&DATE(2025,5,21)) -> 0 | S15: =H15 - O15 - Q15 -> 0 | Y15: 5410.25 | Z15: =S15-Y15 -> 0 | AA15: PAID | AB15: MULTIPLE | AC15: 45992
A16: LEASE-BH-F15-2025 | B16: Flat 15 - 3 West Gate | C16: Achal (Delegated for Udayan) | D16: Ms Lucy Cassell | E16: 45703 | F16: 15 | G16: =IFERROR(SUMPRODUCT((RENT_DUE!$B$2:$B$1000="LEASE-BH-F15-2025")*(RENT_DUE!$D$2:$D$1000>=DATE(2025,4,22))*(RENT_DUE!$D$2:$D$1000<=DATE(2025,5,21))*RENT_DUE!$L$2:$L$1000), 0) -> 0 | H16: =IFERROR(SUMPRODUCT((RENT_RECEIVED!$B$2:$B$1000="LEASE-BH-F15-2025")*(RENT_RECEIVED!$E$2:$E$1000>=DATE(2025,4,22))*(RENT_RECEIVED!$E$2:$E$1000<=DATE(2025,5,21))*RENT_RECEIVED!$O$2:$O$1000), 0) -> 0 | I16: HIST-2025-05-1564 | J16: =IFERROR(SUMIFS(RENT_DUE!$L$2:$L$10000, RENT_DUE!$B$2:$B$10000, "LEASE-BH-F15-2025", RENT_DUE!$D$2:$D$10000, "<"&DATE(2025,4,22)), 0) - IFERROR(SUMIFS(RENT_RECEIVED!$O$2:$O$10000, RENT_RECEIVED!$B$2:$B$10000, "LEASE-BH-F15-2025", RENT_RECEIVED!$E$2:$E$10000, "<"&DATE(2025,4,22)), 0) -> 0 | K16: =G16 - H16 -> 0 | L16: =J16 + K16 -> 0 | M16: =H16 * 0.1500 -> 0 | N16: =H16 * 0.0000 -> 0 | O16: =ABS(M16 + N16) -> 0 | Q16: =SUMIFS(EXPENSES!E:E, EXPENSES!B:B, "LEASE-BH-F15-2025", EXPENSES!D:D, ">="&DATE(2025,4,22), EXPENSES!D:D, "<="&DATE(2025,5,21)) -> 0 | S16: =H16 - O16 - Q16 -> 0 | Y16: 6170 | Z16: =S16-Y16 -> 0 | AA16: PAID | AB16: MULTIPLE | AC16: 45982
A17: LEASE-BH-F16-2025 | B17: Flat 16 - 3 West Gate | C17: Achal (Delegated for Udayan) | D17: Mr Riley Paul Beresford, Ms Gina Louise Judge | E17: 45726 | F17: 10 | G17: =IFERROR(SUMPRODUCT((RENT_DUE!$B$2:$B$1000="LEASE-BH-F16-2025")*(RENT_DUE!$D$2:$D$1000>=DATE(2025,4,22))*(RENT_DUE!$D$2:$D$1000<=DATE(2025,5,21))*RENT_DUE!$L$2:$L$1000), 0) -> 0 | H17: =IFERROR(SUMPRODUCT((RENT_RECEIVED!$B$2:$B$1000="LEASE-BH-F16-2025")*(RENT_RECEIVED!$E$2:$E$1000>=DATE(2025,4,22))*(RENT_RECEIVED!$E$2:$E$1000<=DATE(2025,5,21))*RENT_RECEIVED!$O$2:$O$1000), 0) -> 0 | I17: HIST-2025-05-1564 | J17: =IFERROR(SUMIFS(RENT_DUE!$L$2:$L$10000, RENT_DUE!$B$2:$B$10000, "LEASE-BH-F16-2025", RENT_DUE!$D$2:$D$10000, "<"&DATE(2025,4,22)), 0) - IFERROR(SUMIFS(RENT_RECEIVED!$O$2:$O$10000, RENT_RECEIVED!$B$2:$B$10000, "LEASE-BH-F16-2025", RENT_RECEIVED!$E$2:$E$10000, "<"&DATE(2025,4,22)), 0) -> 0 | K17: =G17 - H17 -> 0 | L17: =J17 + K17 -> 0 | M17: =H17 * 0.1500 -> 0 | N17: =H17 * 0.0000 -> 0 | O17: =ABS(M17 + N17) -> 0 | Q17: =SUMIFS(EXPENSES!E:E, EXPENSES!B:B, "LEASE-BH-F16-2025", EXPENSES!D:D, ">="&DATE(2025,4,22), EXPENSES!D:D, "<="&DATE(2025,5,21)) -> 0 | S17: =H17 - O17 - Q17 -> 0 | Y17: 3641.31 | Z17: =S17-Y17 -> 0 | AA17: PAID | AB17: MULTIPLE | AC17: 45891
A18: LEASE-BH-F17-2025 | B18: Flat 17 - 3 West Gate | C18: Achal (Delegated for Udayan) | D18: Mr Harsh Patel | E18: 45705 | F18: 17 | G18: =IFERROR(SUMPRODUCT((RENT_DUE!$B$2:$B$1000="LEASE-BH-F17-2025")*(RENT_DUE!$D$2:$D$1000>=DATE(2025,4,22))*(RENT_DUE!$D$2:$D$1000<=DATE(2025,5,21))*RENT_DUE!$L$2:$L$1000), 0) -> 0 | H18: =IFERROR(SUMPRODUCT((RENT_RECEIVED!$B$2:$B$1000="LEASE-BH-F17-2025")*(RENT_RECEIVED!$E$2:$E$1000>=DATE(2025,4,22))*(RENT_RECEIVED!$E$2:$E$1000<=DATE(2025,5,21))*RENT_RECEIVED!$O$2:$O$1000), 0) -> 0 | I18: HIST-2025-05-1564 | J18: =IFERROR(SUMIFS(RENT_DUE!$L$2:$L$10000, RENT_DUE!$B$2:$B$10000, "LEASE-BH-F17-2025", RENT_DUE!$D$2:$D$10000, "<"&DATE(2025,4,22)), 0) - IFERROR(SUMIFS(RENT_RECEIVED!$O$2:$O$10000, RENT_RECEIVED!$B$2:$B$10000, "LEASE-BH-F17-2025", RENT_RECEIVED!$E$2:$E$10000, "<"&DATE(2025,4,22)), 0) -> 0 | K18: =G18 - H18 -> 0 | L18: =J18 + K18 -> 0 | M18: =H18 * 0.1500 -> 0 | N18: =H18 * 0.0000 -> 0 | O18: =ABS(M18 + N18) -> 0 | Q18: =SUMIFS(EXPENSES!E:E, EXPENSES!B:B, "LEASE-BH-F17-2025", EXPENSES!D:D, ">="&DATE(2025,4,22), EXPENSES!D:D, "<="&DATE(2025,5,21)) -> 0 | S18: =H18 - O18 - Q18 -> 0 | Y18: 5800 | Z18: =S18-Y18 -> 0 | AA18: PAID | AB18: MULTIPLE | AC18: 45982
A19: LEASE-BH-F18-2025 | B19: Flat 18 - 3 West Gate | C19: Achal (Delegated for Udayan) | D19: Marie Dinko | E19: 45687 | F19: 30 | G19: =IFERROR(SUMPRODUCT((RENT_DUE!$B$2:$B$1000="LEASE-BH-F18-2025")*(RENT_DUE!$D$2:$D$1000>=DATE(2025,4,22))*(RENT_DUE!$D$2:$D$1000<=DATE(2025,5,21))*RENT_DUE!$L$2:$L$1000), 0) -> 0 | H19: =IFERROR(SUMPRODUCT((RENT_RECEIVED!$B$2:$B$1000="LEASE-BH-F18-2025")*(RENT_RECEIVED!$E$2:$E$1000>=DATE(2025,4,22))*(RENT_RECEIVED!$E$2:$E$1000<=DATE(2025,5,21))*RENT_RECEIVED!$O$2:$O$1000), 0) -> 0 | I19: HIST-2025-05-1564 | J19: =IFERROR(SUMIFS(RENT_DUE!$L$2:$L$10000, RENT_DUE!$B$2:$B$10000, "LEASE-BH-F18-2025", RENT_DUE!$D$2:$D$10000, "<"&DATE(2025,4,22)), 0) - IFERROR(SUMIFS(RENT_RECEIVED!$O$2:$O$10000, RENT_RECEIVED!$B$2:$B$10000, "LEASE-BH-F18-2025", RENT_RECEIVED!$E$2:$E$10000, "<"&DATE(2025,4,22)), 0) -> 0 | K19: =G19 - H19 -> 0 | L19: =J19 + K19 -> 0 | M19: =H19 * 0.1500 -> 0 | N19: =H19 * 0.0000 -> 0 | O19: =ABS(M19 + N19) -> 0 | Q19: =SUMIFS(EXPENSES!E:E, EXPENSES!B:B, "LEASE-BH-F18-2025", EXPENSES!D:D, ">="&DATE(2025,4,22), EXPENSES!D:D, "<="&DATE(2025,5,21)) -> 0 | S19: =H19 - O19 - Q19 -> 0 | Y19: 2044.25 | Z19: =S19-Y19 -> 0 | AA19: PAID | AB19: MULTIPLE | AC19: 45804
A20: LEASE-BH-F19-2025 | B20: Flat 19 - 3 West Gate | C20: Achal (Delegated for Udayan) | D20: Mr Joshua Banks, Miss Layla Middlemass | E20: 45730 | F20: 14 | G20: =IFERROR(SUMPRODUCT((RENT_DUE!$B$2:$B$1000="LEASE-BH-F19-2025")*(RENT_DUE!$D$2:$D$1000>=DATE(2025,4,22))*(RENT_DUE!$D$2:$D$1000<=DATE(2025,5,21))*RENT_DUE!$L$2:$L$1000), 0) -> 0 | H20: =IFERROR(SUMPRODUCT((RENT_RECEIVED!$B$2:$B$1000="LEASE-BH-F19-2025")*(RENT_RECEIVED!$E$2:$E$1000>=DATE(2025,4,22))*(RENT_RECEIVED!$E$2:$E$1000<=DATE(2025,5,21))*RENT_RECEIVED!$O$2:$O$1000), 0) -> 0 | I20: HIST-2025-05-1564 | J20: =IFERROR(SUMIFS(RENT_DUE!$L$2:$L$10000, RENT_DUE!$B$2:$B$10000, "LEASE-BH-F19-2025", RENT_DUE!$D$2:$D$10000, "<"&DATE(2025,4,22)), 0) - IFERROR(SUMIFS(RENT_RECEIVED!$O$2:$O$10000, RENT_RECEIVED!$B$2:$B$10000, "LEASE-BH-F19-2025", RENT_RECEIVED!$E$2:$E$10000, "<"&DATE(2025,4,22)), 0) -> 0 | K20: =G20 - H20 -> 0 | L20: =J20 + K20 -> 0 | M20: =H20 * 0.1500 -> 0 | N20: =H20 * 0.0000 -> 0 | O20: =ABS(M20 + N20) -> 0 | Q20: =SUMIFS(EXPENSES!E:E, EXPENSES!B:B, "LEASE-BH-F19-2025", EXPENSES!D:D, ">="&DATE(2025,4,22), EXPENSES!D:D, "<="&DATE(2025,5,21)) -> 0 | S20: =H20 - O20 - Q20 -> 0 | Y20: 2888.3 | Z20: =S20-Y20 -> 0 | AA20: PAID | AB20: MULTIPLE | AC20: 45846
A21: LEASE-BH-F20-2025 | B21: Flat 20 - 3 West Gate | C21: Achal (Delegated for Udayan) | D21: Mr James Kay | E21: 45732 | F21: 16 | G21: =IFERROR(SUMPRODUCT((RENT_DUE!$B$2:$B$1000="LEASE-BH-F20-2025")*(RENT_DUE!$D$2:$D$1000>=DATE(2025,4,22))*(RENT_DUE!$D$2:$D$1000<=DATE(2025,5,21))*RENT_DUE!$L$2:$L$1000), 0) -> 0 | H21: =IFERROR(SUMPRODUCT((RENT_RECEIVED!$B$2:$B$1000="LEASE-BH-F20-2025")*(RENT_RECEIVED!$E$2:$E$1000>=DATE(2025,4,22))*(RENT_RECEIVED!$E$2:$E$1000<=DATE(2025,5,21))*RENT_RECEIVED!$O$2:$O$1000), 0) -> 0 | I21: HIST-2025-05-1564 | J21: =IFERROR(SUMIFS(RENT_DUE!$L$2:$L$10000, RENT_DUE!$B$2:$B$10000, "LEASE-BH-F20-2025", RENT_DUE!$D$2:$D$10000, "<"&DATE(2025,4,22)), 0) - IFERROR(SUMIFS(RENT_RECEIVED!$O$2:$O$10000, RENT_RECEIVED!$B$2:$B$10000, "LEASE-BH-F20-2025", RENT_RECEIVED!$E$2:$E$10000, "<"&DATE(2025,4,22)), 0) -> 0 | K21: =G21 - H21 -> 0 | L21: =J21 + K21 -> 0 | M21: =H21 * 0.1500 -> 0 | N21: =H21 * 0.0000 -> 0 | O21: =ABS(M21 + N21) -> 0 | Q21: =SUMIFS(EXPENSES!E:E, EXPENSES!B:B, "LEASE-BH-F20-2025", EXPENSES!D:D, ">="&DATE(2025,4,22), EXPENSES!D:D, "<="&DATE(2025,5,21)) -> 0 | S21: =H21 - O21 - Q21 -> 0 | Y21: 5255 | Z21: =S21-Y21 -> 0 | AA21: PAID | AB21: MULTIPLE | AC21: 45982
A22: LEASE-BH-F21-2025 | B22: Flat 21 - 3 West Gate | C22: Achal (Delegated for Udayan) | D22: Mr Felwin Francis | E22: 45687 | F22: 30 | G22: =IFERROR(SUMPRODUCT((RENT_DUE!$B$2:$B$1000="LEASE-BH-F21-2025")*(RENT_DUE!$D$2:$D$1000>=DATE(2025,4,22))*(RENT_DUE!$D$2:$D$1000<=DATE(2025,5,21))*RENT_DUE!$L$2:$L$1000), 0) -> 0 | H22: =IFERROR(SUMPRODUCT((RENT_RECEIVED!$B$2:$B$1000="LEASE-BH-F21-2025")*(RENT_RECEIVED!$E$2:$E$1000>=DATE(2025,4,22))*(RENT_RECEIVED!$E$2:$E$1000<=DATE(2025,5,21))*RENT_RECEIVED!$O$2:$O$1000), 0) -> 0 | I22: HIST-2025-05-1564 | J22: =IFERROR(SUMIFS(RENT_DUE!$L$2:$L$10000, RENT_DUE!$B$2:$B$10000, "LEASE-BH-F21-2025", RENT_DUE!$D$2:$D$10000, "<"&DATE(2025,4,22)), 0) - IFERROR(SUMIFS(RENT_RECEIVED!$O$2:$O$10000, RENT_RECEIVED!$B$2:$B$10000, "LEASE-BH-F21-2025", RENT_RECEIVED!$E$2:$E$10000, "<"&DATE(2025,4,22)), 0) -> 0 | K22: =G22 - H22 -> 0 | L22: =J22 + K22 -> 0 | M22: =H22 * 0.1500 -> 0 | N22: =H22 * 0.0000 -> 0 | O22: =ABS(M22 + N22) -> 0 | Q22: =SUMIFS(EXPENSES!E:E, EXPENSES!B:B, "LEASE-BH-F21-2025", EXPENSES!D:D, ">="&DATE(2025,4,22), EXPENSES!D:D, "<="&DATE(2025,5,21)) -> 0 | S22: =H22 - O22 - Q22 -> 0 | Y22: 6637.5 | Z22: =S22-Y22 -> 0 | AA22: PAID | AB22: MULTIPLE | AC22: 45982
A23: LEASE-BH-F22-2025 | B23: Flat 22 - 3 West Gate | C23: Achal (Delegated for Udayan) | D23: Mr Brian Lowe | E23: 45717 | F23: 1 | G23: =IFERROR(SUMPRODUCT((RENT_DUE!$B$2:$B$1000="LEASE-BH-F22-2025")*(RENT_DUE!$D$2:$D$1000>=DATE(2025,4,22))*(RENT_DUE!$D$2:$D$1000<=DATE(2025,5,21))*RENT_DUE!$L$2:$L$1000), 0) -> 0 | H23: =IFERROR(SUMPRODUCT((RENT_RECEIVED!$B$2:$B$1000="LEASE-BH-F22-2025")*(RENT_RECEIVED!$E$2:$E$1000>=DATE(2025,4,22))*(RENT_RECEIVED!$E$2:$E$1000<=DATE(2025,5,21))*RENT_RECEIVED!$O$2:$O$1000), 0) -> 0 | I23: HIST-2025-04-1532, HIST-2025-05-1564 | J23: =IFERROR(SUMIFS(RENT_DUE!$L$2:$L$10000, RENT_DUE!$B$2:$B$10000, "LEASE-BH-F22-2025", RENT_DUE!$D$2:$D$10000, "<"&DATE(2025,4,22)), 0) - IFERROR(SUMIFS(RENT_RECEIVED!$O$2:$O$10000, RENT_RECEIVED!$B$2:$B$10000, "LEASE-BH-F22-2025", RENT_RECEIVED!$E$2:$E$10000, "<"&DATE(2025,4,22)), 0) -> 0 | K23: =G23 - H23 -> 0 | L23: =J23 + K23 -> 0 | M23: =H23 * 0.1500 -> 0 | N23: =H23 * 0.0000 -> 0 | O23: =ABS(M23 + N23) -> 0 | Q23: =SUMIFS(EXPENSES!E:E, EXPENSES!B:B, "LEASE-BH-F22-2025", EXPENSES!D:D, ">="&DATE(2025,4,22), EXPENSES!D:D, "<="&DATE(2025,5,21)) -> 0 | S23: =H23 - O23 - Q23 -> 0 | Y23: 5661 | Z23: =S23-Y23 -> 0 | AA23: PAID | AB23: MULTIPLE | AC23: 45982
A24: LEASE-BH-F24-2025 | B24: Flat 24 - 3 West Gate | C24: Achal (Delegated for Udayan) | D24: Mr Ethan Maloney, Miss Soraya Fearon | E24: 45700 | F24: 12 | G24: =IFERROR(SUMPRODUCT((RENT_DUE!$B$2:$B$1000="LEASE-BH-F24-2025")*(RENT_DUE!$D$2:$D$1000>=DATE(2025,4,22))*(RENT_DUE!$D$2:$D$1000<=DATE(2025,5,21))*RENT_DUE!$L$2:$L$1000), 0) -> 0 | H24: =IFERROR(SUMPRODUCT((RENT_RECEIVED!$B$2:$B$1000="LEASE-BH-F24-2025")*(RENT_RECEIVED!$E$2:$E$1000>=DATE(2025,4,22))*(RENT_RECEIVED!$E$2:$E$1000<=DATE(2025,5,21))*RENT_RECEIVED!$O$2:$O$1000), 0) -> 0 | I24: HIST-2025-05-1564 | J24: =IFERROR(SUMIFS(RENT_DUE!$L$2:$L$10000, RENT_DUE!$B$2:$B$10000, "LEASE-BH-F24-2025", RENT_DUE!$D$2:$D$10000, "<"&DATE(2025,4,22)), 0) - IFERROR(SUMIFS(RENT_RECEIVED!$O$2:$O$10000, RENT_RECEIVED!$B$2:$B$10000, "LEASE-BH-F24-2025", RENT_RECEIVED!$E$2:$E$10000, "<"&DATE(2025,4,22)), 0) -> 0 | K24: =G24 - H24 -> 0 | L24: =J24 + K24 -> 0 | M24: =H24 * 0.1500 -> 0 | N24: =H24 * 0.0000 -> 0 | O24: =ABS(M24 + N24) -> 0 | Q24: =SUMIFS(EXPENSES!E:E, EXPENSES!B:B, "LEASE-BH-F24-2025", EXPENSES!D:D, ">="&DATE(2025,4,22), EXPENSES!D:D, "<="&DATE(2025,5,21)) -> 0 | S24: =H24 - O24 - Q24 -> 0 | Y24: 6765 | Z24: =S24-Y24 -> 0 | AA24: PAID | AB24: MULTIPLE | AC24: 45982
A25: LEASE-BH-F26-2025 | B25: Flat 26 - 3 West Gate | C25: Achal (Delegated for Udayan) | D25: Mr Louis Scotting | E25: 45730 | F25: 14 | G25: =IFERROR(SUMPRODUCT((RENT_DUE!$B$2:$B$1000="LEASE-BH-F26-2025")*(RENT_DUE!$D$2:$D$1000>=DATE(2025,4,22))*(RENT_DUE!$D$2:$D$1000<=DATE(2025,5,21))*RENT_DUE!$L$2:$L$1000), 0) -> 0 | H25: =IFERROR(SUMPRODUCT((RENT_RECEIVED!$B$2:$B$1000="LEASE-BH-F26-2025")*(RENT_RECEIVED!$E$2:$E$1000>=DATE(2025,4,22))*(RENT_RECEIVED!$E$2:$E$1000<=DATE(2025,5,21))*RENT_RECEIVED!$O$2:$O$1000), 0) -> 0 | I25: HIST-2025-05-1564 | J25: =IFERROR(SUMIFS(RENT_DUE!$L$2:$L$10000, RENT_DUE!$B$2:$B$10000, "LEASE-BH-F26-2025", RENT_DUE!$D$2:$D$10000, "<"&DATE(2025,4,22)), 0) - IFERROR(SUMIFS(RENT_RECEIVED!$O$2:$O$10000, RENT_RECEIVED!$B$2:$B$10000, "LEASE-BH-F26-2025", RENT_RECEIVED!$E$2:$E$10000, "<"&DATE(2025,4,22)), 0) -> 0 | K25: =G25 - H25 -> 0 | L25: =J25 + K25 -> 0 | M25: =H25 * 0.1500 -> 0 | N25: =H25 * 0.0000 -> 0 | O25: =ABS(M25 + N25) -> 0 | Q25: =SUMIFS(EXPENSES!E:E, EXPENSES!B:B, "LEASE-BH-F26-2025", EXPENSES!D:D, ">="&DATE(2025,4,22), EXPENSES!D:D, "<="&DATE(2025,5,21)) -> 0 | S25: =H25 - O25 - Q25 -> 0 | Y25: 5163.75 | Z25: =S25-Y25 -> 0 | AA25: PAID | AB25: MULTIPLE | AC25: 45992
A26: LEASE-BH-F27-2025 | B26: Flat 27 - 3 West Gate | C26: Achal (Delegated for Udayan) | D26: Miss Sophie Murray | E26: 45716 | F26: 30 | G26: =IFERROR(SUMPRODUCT((RENT_DUE!$B$2:$B$1000="LEASE-BH-F27-2025")*(RENT_DUE!$D$2:$D$1000>=DATE(2025,4,22))*(RENT_DUE!$D$2:$D$1000<=DATE(2025,5,21))*RENT_DUE!$L$2:$L$1000), 0) -> 0 | H26: =IFERROR(SUMPRODUCT((RENT_RECEIVED!$B$2:$B$1000="LEASE-BH-F27-2025")*(RENT_RECEIVED!$E$2:$E$1000>=DATE(2025,4,22))*(RENT_RECEIVED!$E$2:$E$1000<=DATE(2025,5,21))*RENT_RECEIVED!$O$2:$O$1000), 0) -> 0 | I26: HIST-2025-05-1564 | J26: =IFERROR(SUMIFS(RENT_DUE!$L$2:$L$10000, RENT_DUE!$B$2:$B$10000, "LEASE-BH-F27-2025", RENT_DUE!$D$2:$D$10000, "<"&DATE(2025,4,22)), 0) - IFERROR(SUMIFS(RENT_RECEIVED!$O$2:$O$10000, RENT_RECEIVED!$B$2:$B$10000, "LEASE-BH-F27-2025", RENT_RECEIVED!$E$2:$E$10000, "<"&DATE(2025,4,22)), 0) -> 0 | K26: =G26 - H26 -> 0 | L26: =J26 + K26 -> 0 | M26: =H26 * 0.1500 -> 0 | N26: =H26 * 0.0000 -> 0 | O26: =ABS(M26 + N26) -> 0 | Q26: =SUMIFS(EXPENSES!E:E, EXPENSES!B:B, "LEASE-BH-F27-2025", EXPENSES!D:D, ">="&DATE(2025,4,22), EXPENSES!D:D, "<="&DATE(2025,5,21)) -> 0 | S26: =H26 - O26 - Q26 -> 0 | Y26: 5355 | Z26: =S26-Y26 -> 0 | AA26: PAID | AB26: MULTIPLE | AC26: 45982
A27: LEASE-BH-F28-2025 | B27: Flat 28 - 3 West Gate | C27: Achal (Delegated for Udayan) | D27: Ms Shiu Lun Cheung, Mr Chi Man Poon | E27: 45744 | F27: 18 | G27: =IFERROR(SUMPRODUCT((RENT_DUE!$B$2:$B$1000="LEASE-BH-F28-2025")*(RENT_DUE!$D$2:$D$1000>=DATE(2025,4,22))*(RENT_DUE!$D$2:$D$1000<=DATE(2025,5,21))*RENT_DUE!$L$2:$L$1000), 0) -> 0 | H27: =IFERROR(SUMPRODUCT((RENT_RECEIVED!$B$2:$B$1000="LEASE-BH-F28-2025")*(RENT_RECEIVED!$E$2:$E$1000>=DATE(2025,4,22))*(RENT_RECEIVED!$E$2:$E$1000<=DATE(2025,5,21))*RENT_RECEIVED!$O$2:$O$1000), 0) -> 0 | I27: HIST-2025-05-1564 | J27: =IFERROR(SUMIFS(RENT_DUE!$L$2:$L$10000, RENT_DUE!$B$2:$B$10000, "LEASE-BH-F28-2025", RENT_DUE!$D$2:$D$10000, "<"&DATE(2025,4,22)), 0) - IFERROR(SUMIFS(RENT_RECEIVED!$O$2:$O$10000, RENT_RECEIVED!$B$2:$B$10000, "LEASE-BH-F28-2025", RENT_RECEIVED!$E$2:$E$10000, "<"&DATE(2025,4,22)), 0) -> 0 | K27: =G27 - H27 -> 0 | L27: =J27 + K27 -> 0 | M27: =H27 * 0.1500 -> 0 | N27: =H27 * 0.0000 -> 0 | O27: =ABS(M27 + N27) -> 0 | Q27: =SUMIFS(EXPENSES!E:E, EXPENSES!B:B, "LEASE-BH-F28-2025", EXPENSES!D:D, ">="&DATE(2025,4,22), EXPENSES!D:D, "<="&DATE(2025,5,21)) -> 0 | S27: =H27 - O27 - Q27 -> 0 | Y27: 0 | Z27: =S27-Y27 -> 0 | AA27: PAID | AB27: HIST-2025-10-1650 | AC27: 45951
A28: LEASE-BH-F29-2025 | B28: Flat 29 - 3 West Gate | C28: Achal (Delegated for Udayan) | D28: Mrs Margaret Fritchley | E28: 45715 | F28: 27 | G28: =IFERROR(SUMPRODUCT((RENT_DUE!$B$2:$B$1000="LEASE-BH-F29-2025")*(RENT_DUE!$D$2:$D$1000>=DATE(2025,4,22))*(RENT_DUE!$D$2:$D$1000<=DATE(2025,5,21))*RENT_DUE!$L$2:$L$1000), 0) -> 0 | H28: =IFERROR(SUMPRODUCT((RENT_RECEIVED!$B$2:$B$1000="LEASE-BH-F29-2025")*(RENT_RECEIVED!$E$2:$E$1000>=DATE(2025,4,22))*(RENT_RECEIVED!$E$2:$E$1000<=DATE(2025,5,21))*RENT_RECEIVED!$O$2:$O$1000), 0) -> 0 | I28: HIST-2025-05-1564 | J28: =IFERROR(SUMIFS(RENT_DUE!$L$2:$L$10000, RENT_DUE!$B$2:$B$10000, "LEASE-BH-F29-2025", RENT_DUE!$D$2:$D$10000, "<"&DATE(2025,4,22)), 0) - IFERROR(SUMIFS(RENT_RECEIVED!$O$2:$O$10000, RENT_RECEIVED!$B$2:$B$10000, "LEASE-BH-F29-2025", RENT_RECEIVED!$E$2:$E$10000, "<"&DATE(2025,4,22)), 0) -> 0 | K28: =G28 - H28 -> 0 | L28: =J28 + K28 -> 0 | M28: =H28 * 0.1500 -> 0 | N28: =H28 * 0.0000 -> 0 | O28: =ABS(M28 + N28) -> 0 | Q28: =SUMIFS(EXPENSES!E:E, EXPENSES!B:B, "LEASE-BH-F29-2025", EXPENSES!D:D, ">="&DATE(2025,4,22), EXPENSES!D:D, "<="&DATE(2025,5,21)) -> 0 | S28: =H28 - O28 - Q28 -> 0 | Y28: 5541 | Z28: =S28-Y28 -> 0 | AA28: PAID | AB28: MULTIPLE | AC28: 45982
A29: LEASE-BH-F30-2025 | B29: Flat 30 - 3 West Gate | C29: Achal (Delegated for Udayan) | D29: Mr Joel Bryan | E29: 45722 | F29: 6 | G29: =IFERROR(SUMPRODUCT((RENT_DUE!$B$2:$B$1000="LEASE-BH-F30-2025")*(RENT_DUE!$D$2:$D$1000>=DATE(2025,4,22))*(RENT_DUE!$D$2:$D$1000<=DATE(2025,5,21))*RENT_DUE!$L$2:$L$1000), 0) -> 0 | H29: =IFERROR(SUMPRODUCT((RENT_RECEIVED!$B$2:$B$1000="LEASE-BH-F30-2025")*(RENT_RECEIVED!$E$2:$E$1000>=DATE(2025,4,22))*(RENT_RECEIVED!$E$2:$E$1000<=DATE(2025,5,21))*RENT_RECEIVED!$O$2:$O$1000), 0) -> 0 | I29: HIST-2025-05-1564 | J29: =IFERROR(SUMIFS(RENT_DUE!$L$2:$L$10000, RENT_DUE!$B$2:$B$10000, "LEASE-BH-F30-2025", RENT_DUE!$D$2:$D$10000, "<"&DATE(2025,4,22)), 0) - IFERROR(SUMIFS(RENT_RECEIVED!$O$2:$O$10000, RENT_RECEIVED!$B$2:$B$10000, "LEASE-BH-F30-2025", RENT_RECEIVED!$E$2:$E$10000, "<"&DATE(2025,4,22)), 0) -> 0 | K29: =G29 - H29 -> 0 | L29: =J29 + K29 -> 0 | M29: =H29 * 0.1500 -> 0 | N29: =H29 * 0.0000 -> 0 | O29: =ABS(M29 + N29) -> 0 | Q29: =SUMIFS(EXPENSES!E:E, EXPENSES!B:B, "LEASE-BH-F30-2025", EXPENSES!D:D, ">="&DATE(2025,4,22), EXPENSES!D:D, "<="&DATE(2025,5,21)) -> 0 | S29: =H29 - O29 - Q29 -> 0 | Y29: 5032 | Z29: =S29-Y29 -> 0 | AA29: PAID | AB29: MULTIPLE | AC29: 45992
A30: LEASE-KH-F-2024 | B30: Apartment F - Knighton Hayes Manor | C30: Achal (Delegated for Udayan) | D30: Mr Riaz Hamid, Ismat Tarr-Hamid | E30: 45648 | F30: 22 | G30: =IFERROR(SUMPRODUCT((RENT_DUE!$B$2:$B$1000="LEASE-KH-F-2024")*(RENT_DUE!$D$2:$D$1000>=DATE(2025,4,22))*(RENT_DUE!$D$2:$D$1000<=DATE(2025,5,21))*RENT_DUE!$L$2:$L$1000), 0) -> 0 | H30: =IFERROR(SUMPRODUCT((RENT_RECEIVED!$B$2:$B$1000="LEASE-KH-F-2024")*(RENT_RECEIVED!$E$2:$E$1000>=DATE(2025,4,22))*(RENT_RECEIVED!$E$2:$E$1000<=DATE(2025,5,21))*RENT_RECEIVED!$O$2:$O$1000), 0) -> 0 | I30: HIST-2025-07-1604 | J30: =IFERROR(SUMIFS(RENT_DUE!$L$2:$L$10000, RENT_DUE!$B$2:$B$10000, "LEASE-KH-F-2024", RENT_DUE!$D$2:$D$10000, "<"&DATE(2025,4,22)), 0) - IFERROR(SUMIFS(RENT_RECEIVED!$O$2:$O$10000, RENT_RECEIVED!$B$2:$B$10000, "LEASE-KH-F-2024", RENT_RECEIVED!$E$2:$E$10000, "<"&DATE(2025,4,22)), 0) -> 0 | K30: =G30 - H30 -> 0 | L30: =J30 + K30 -> 0 | M30: =H30 * 0.1000 -> 0 | N30: =H30 * 0.0000 -> 0 | O30: =ABS(M30 + N30) -> 0 | Q30: =SUMIFS(EXPENSES!E:E, EXPENSES!B:B, "LEASE-KH-F-2024", EXPENSES!D:D, ">="&DATE(2025,4,22), EXPENSES!D:D, "<="&DATE(2025,5,21)) -> 0 | S30: =H30 - O30 - Q30 -> 0 | Y30: 12150 | Z30: =S30-Y30 -> 0 | AA30: PAID | AB30: MULTIPLE | AC30: 45982
A31: BODEN-BLOCK-2025 | B31: Boden House Block - Block Property | C31: Achal (Delegated for Udayan) | D31: Prestvale Properties Limited | E31: 45717 | F31: 1 | G31: =IFERROR(SUMPRODUCT((RENT_DUE!$B$2:$B$1000="BODEN-BLOCK-2025")*(RENT_DUE!$D$2:$D$1000>=DATE(2025,4,22))*(RENT_DUE!$D$2:$D$1000<=DATE(2025,5,21))*RENT_DUE!$L$2:$L$1000), 0) -> 0 | H31: =IFERROR(SUMPRODUCT((RENT_RECEIVED!$B$2:$B$1000="BODEN-BLOCK-2025")*(RENT_RECEIVED!$E$2:$E$1000>=DATE(2025,4,22))*(RENT_RECEIVED!$E$2:$E$1000<=DATE(2025,5,21))*RENT_RECEIVED!$O$2:$O$1000), 0) -> 0 | J31: =IFERROR(SUMIFS(RENT_DUE!$L$2:$L$10000, RENT_DUE!$B$2:$B$10000, "BODEN-BLOCK-2025", RENT_DUE!$D$2:$D$10000, "<"&DATE(2025,4,22)), 0) - IFERROR(SUMIFS(RENT_RECEIVED!$O$2:$O$10000, RENT_RECEIVED!$B$2:$B$10000, "BODEN-BLOCK-2025", RENT_RECEIVED!$E$2:$E$10000, "<"&DATE(2025,4,22)), 0) -> 0 | K31: =G31 - H31 -> 0 | L31: =J31 + K31 -> 0 | M31: =H31 * 0.0000 -> 0 | N31: =H31 * 0.0500 -> 0 | O31: =ABS(M31 + N31) -> 0 | Q31: =SUMIFS(EXPENSES!E:E, EXPENSES!B:B, "BODEN-BLOCK-2025", EXPENSES!D:D, ">="&DATE(2025,4,22), EXPENSES!D:D, "<="&DATE(2025,5,21)) -> 0 | R31: HIST-2025-04-1532 | S31: =H31 - O31 - Q31 -> 0 | T31: Boden House NG10 | U31: =IFERROR(SUMIFS(PROPERTY_ACCOUNT!D:D, PROPERTY_ACCOUNT!A:A, T31, PROPERTY_ACCOUNT!B:B, "opening"), 0) -> 0 | V31: =IFERROR(SUMIFS(PROPERTY_ACCOUNT!D:D, PROPERTY_ACCOUNT!A:A, T31, PROPERTY_ACCOUNT!B:B, "in"), 0) -> 0 | W31: =IFERROR(SUMIFS(PROPERTY_ACCOUNT!D:D, PROPERTY_ACCOUNT!A:A, T31, PROPERTY_ACCOUNT!B:B, "out"), 0) -> 0 | X31: =U31 + V31 - W31 -> 0 | Y31: 0 | Z31: =S31-Y31 -> 0 | AA31: PAID | AB31: MULTIPLE | AC31: 45993
A32: TOTALS | G32: =SUM(G2:G31) -> 0 | H32: =SUM(H2:H31) -> 0 | J32: =SUM(J2:J31) -> 0 | K32: =SUM(K2:K31) -> 0 | L32: =SUM(L2:L31) -> 0 | M32: =SUM(M2:M31) -> 0 | N32: =SUM(N2:N31) -> 0 | O32: =SUM(O2:O31) -> 0 | Q32: =SUM(Q2:Q31) -> 0 | S32: =SUM(S2:S31) -> 0 | U32: =SUM(U2:U31) -> 0 | V32: =SUM(V2:V31) -> 0 | W32: =SUM(W2:W31) -> 0 | X32: =SUM(X2:X31) -> 0
A34: PAYMENT RECONCILIATION
A35: Period: 2025-04-22 to 2025-05-21
A37: BROUGHT FORWARD (items from prior periods paid this period)
A38: Prior Period Income:
A39: 2025-03-28 | Flat 22 - 3 West Gate | rent | B39: 629
A40: 2025-03-28 | Flat 26 - 3 West Gate | rent | B40: 403
A41: 2025-03-30 | Flat 6 - 3 West Gate | rent | B41: 629
A42: 2025-03-31 | Flat 28 - 3 West Gate | rent | B42: 629
A43: 2025-04-01 | Flat 11 - 3 West Gate | rent | B43: 675.75
A44: 2025-04-01 | Flat 20 - 3 West Gate | rent | B44: 595
A45: 2025-04-01 | Flat 9 - 3 West Gate | rent | B45: 595
A46: 2025-04-02 | Flat 2 - 3 West Gate | rent | B46: 629
A47: 2025-04-02 | Flat 27 - 3 West Gate | rent | B47: 595
A48: 2025-04-02 | Flat 29 - 3 West Gate | rent | B48: 629
A49: 2025-04-03 | Flat 19 - 3 West Gate | rent | B49: 629
A50: 2025-04-03 | Flat 4 - 3 West Gate | rent | B50: 726.75
... A65: Prior Period Income Total (26 items): | B65: 16609.25
A66: Prior Period Expenses: None
A67: NET B/F (Income - Expenses): | B67: 16609.25
A69: THIS PERIOD ACTIVITY (see transactions above for details)
A70: Period Income (3 transactions) | B70: 1887
A71: Period Expenses (1 transactions) | B71: 200
A72: Net Activity (Income - Expenses): | B72: 1687
A74: PAYMENTS MADE THIS PERIOD
A75: HIST-2025-04-1532 (2025-04-25) | B75: 18296.25
A76: Covers: 29 income (£18496.25) - 1 expenses (£200.00) = £18296.25
A77: Total Payments Made: | B77: 18296.25
A78: (See PAYMENT_ALLOCATIONS sheet for full details)
A80: SUMMARY
A81: Total Allocated (Income - Expenses): | B81: 18296.25
A82: Total Payments Made: | B82: 18296.25
A83: Unallocated Payment Amounts: | B83: 0
A85: Check: Allocated 18296.25 + Unallocated 0.00 = 18296.25 vs Payments 18296.25

Sheet May 22 - Jun 21, 2025
A1: lease_reference | B1: property_name | C1: customer_name | D1: tenant_name | E1: lease_start_date | F1: rent_due_day | G1: rent_due | H1: rent_received | I1: rent_batch | J1: opening_balance | K1: period_arrears | L1: closing_balance | M1: management_fee | N1: service_fee | O1: total_commission | P1: commission_batch | Q1: total_expenses | R1: expenses_batch | S1: net_to_owner | T1: block_name | U1: property_account_opening | V1: property_account_in | W1: property_account_out | X1: property_account_closing | Y1: allocated_amount | Z1: variance | AA1: allocation_status | AB1: batch_id | AC1: paid_date
A2: LEASE-BH-F1-2025 | B2: Flat 1 - 3 West Gate | C2: Achal (Delegated for Udayan) | D2: Ms Oleksandra Smoliarenko, Mr Illia Halii | E2: 45715 | F2: 27 | G2: =IFERROR(SUMPRODUCT((RENT_DUE!$B$2:$B$1000="LEASE-BH-F1-2025")*(RENT_DUE!$D$2:$D$1000>=DATE(2025,5,22))*(RENT_DUE!$D$2:$D$1000<=DATE(2025,6,21))*RENT_DUE!$L$2:$L$1000), 0) -> 0 | H2: =IFERROR(SUMPRODUCT((RENT_RECEIVED!$B$2:$B$1000="LEASE-BH-F1-2025")*(RENT_RECEIVED!$E$2:$E$1000>=DATE(2025,5,22))*(RENT_RECEIVED!$E$2:$E$1000<=DATE(2025,6,21))*RENT_RECEIVED!$O$2:$O$1000), 0) -> 0 | I2: HIST-2025-07-1591, HIST-2025-07-1603 | J2: =IFERROR(SUMIFS(RENT_DUE!$L$2:$L$10000, RENT_DUE!$B$2:$B$10000, "LEASE-BH-F1-2025", RENT_DUE!$D$2:$D$10000, "<"&DATE(2025,5,22)), 0) - IFERROR(SUMIFS(RENT_RECEIVED!$O$2:$O$10000, RENT_RECEIVED!$B$2:$B$10000, "LEASE-BH-F1-2025", RENT_RECEIVED!$E$2:$E$10000, "<"&DATE(2025,5,22)), 0) -> 0 | K2: =G2 - H2 -> 0 | L2: =J2 + K2 -> 0 | M2: =H2 * 0.1500 -> 0 | N2: =H2 * 0.0000 -> 0 | O2: =ABS(M2 + N2) -> 0 | Q2: =SUMIFS(EXPENSES!E:E, EXPENSES!B:B, "LEASE-BH-F1-2025", EXPENSES!D:D, ">="&DATE(2025,5,22), EXPENSES!D:D, "<="&DATE(2025,6,21)) -> 0 | S2: =H2 - O2 - Q2 -> 0 | Y2: 5985.52 | Z2: =S2-Y2 -> 0 | AA2: PAID | AB2: MULTIPLE | AC2: 45992
A3: LEASE-BH-F2-2025 | B3: Flat 2 - 3 West Gate | C3: Achal (Delegated for Udayan) | D3: Mr Mustafa Al Bayat, Mrs Gulala Al - Zangana | E3: 45715 | F3: 27 | G3: =IFERROR(SUMPRODUCT((RENT_DUE!$B$2:$B$1000="LEASE-BH-F2-2025")*(RENT_DUE!$D$2:$D$1000>=DATE(2025,5,22))*(RENT_DUE!$D$2:$D$1000<=DATE(2025,6,21))*RENT_DUE!$L$2:$L$1000), 0) -> 0 | H3: =IFERROR(SUMPRODUCT((RENT_RECEIVED!$B$2:$B$1000="LEASE-BH-F2-2025")*(RENT_RECEIVED!$E$2:$E$1000>=DATE(2025,5,22))*(RENT_RECEIVED!$E$2:$E$1000<=DATE(2025,6,21))*RENT_RECEIVED!$O$2:$O$1000), 0) -> 0 | I3: HIST-2025-07-1603 | J3: =IFERROR(SUMIFS(RENT_DUE!$L$2:$L$10000, RENT_DUE!$B$2:$B$10000, "LEASE-BH-F2-2025", RENT_DUE!$D$2:$D$10000, "<"&DATE(2025,5,22)), 0) - IFERROR(SUMIFS(RENT_RECEIVED!$O$2:$O$10000, RENT_RECEIVED!$B$2:$B$10000, "LEASE-BH-F2-2025", RENT_RECEIVED!$E$2:$E$10000, "<"&DATE(2025,5,22)), 0) -> 0 | K3: =G3 - H3 -> 0 | L3: =J3 + K3 -> 0 | M3: =H3 * 0.1500 -> 0 | N3: =H3 * 0.0000 -> 0 | O3: =ABS(M3 + N3) -> 0 | Q3: =SUMIFS(EXPENSES!E:E, EXPENSES!B:B, "LEASE-BH-F2-2025", EXPENSES!D:D, ">="&DATE(2025,5,22), EXPENSES!D:D, "<="&DATE(2025,6,21)) -> 0 | S3: =H3 - O3 - Q3 -> 0 | Y3: 5661 | Z3: =S3-Y3 -> 0 | AA3: PAID | AB3: MULTIPLE | AC3: 45992
A4: LEASE-BH-F3-2025 | B4: Flat 3 - 3 West Gate | C4: Achal (Delegated for Udayan) | D4: Mr Tracy Whyte | E4: 45727 | F4: 11 | G4: =IFERROR(SUMPRODUCT((RENT_DUE!$B$2:$B$1000="LEASE-BH-F3-2025")*(RENT_DUE!$D$2:$D$1000>=DATE(2025,5,22))*(RENT_DUE!$D$2:$D$1000<=DATE(2025,6,21))*RENT_DUE!$L$2:$L$1000), 0) -> 0 | H4: =IFERROR(SUMPRODUCT((RENT_RECEIVED!$B$2:$B$1000="LEASE-BH-F3-2025")*(RENT_RECEIVED!$E$2:$E$1000>=DATE(2025,5,22))*(RENT_RECEIVED!$E$2:$E$1000<=DATE(2025,6,21))*RENT_RECEIVED!$O$2:$O$1000), 0) -> 0 | I4: HIST-2025-07-1591 | J4: =IFERROR(SUMIFS(RENT_DUE!$L$2:$L$10000, RENT_DUE!$B$2:$B$10000, "LEASE-BH-F3-2025", RENT_DUE!$D$2:$D$10000, "<"&DATE(2025,5,22)), 0) - IFERROR(SUMIFS(RENT_RECEIVED!$O$2:$O$10000, RENT_RECEIVED!$B$2:$B$10000, "LEASE-BH-F3-2025", RENT_RECEIVED!$E$2:$E$10000, "<"&DATE(2025,5,22)), 0) -> 0 | K4: =G4 - H4 -> 0 | L4: =J4 + K4 -> 0 | M4: =H4 * 0.1500 -> 0 | N4: =H4 * 0.0000 -> 0 | O4: =ABS(M4 + N4) -> 0 | Q4: =SUMIFS(EXPENSES!E:E, EXPENSES!B:B, "LEASE-BH-F3-2025", EXPENSES!D:D, ">="&DATE(2025,5,22), EXPENSES!D:D, "<="&DATE(2025,6,21)) -> 0 | S4: =H4 - O4 - Q4 -> 0 | Y4: 5661 | Z4: =S4-Y4 -> 0 | AA4: PAID | AB4: MULTIPLE | AC4: 45992
A5: LEASE-BH-F4-2025 | B5: Flat 4 - 3 West Gate | C5: Achal (Delegated for Udayan) | D5: Miss Megan Delaney, Mr Joseph Williams | E5: 45713 | F5: 25 | G5: =IFERROR(SUMPRODUCT((RENT_DUE!$B$2:$B$1000="LEASE-BH-F4-2025")*(RENT_DUE!$D$2:$D$1000>=DATE(2025,5,22))*(RENT_DUE!$D$2:$D$1000<=DATE(2025,6,21))*RENT_DUE!$L$2:$L$1000), 0) -> 0 | H5: =IFERROR(SUMPRODUCT((RENT_RECEIVED!$B$2:$B$1000="LEASE-BH-F4-2025")*(RENT_RECEIVED!$E$2:$E$1000>=DATE(2025,5,22))*(RENT_RECEIVED!$E$2:$E$1000<=DATE(2025,6,21))*RENT_RECEIVED!$O$2:$O$1000), 0) -> 0 | I5: HIST-2025-07-1603 | J5: =IFERROR(SUMIFS(RENT_DUE!$L$2:$L$10000, RENT_DUE!$B$2:$B$10000, "LEASE-BH-F4-2025", RENT_DUE!$D$2:$D$10000, "<"&DATE(2025,5,22)), 0) - IFERROR(SUMIFS(RENT_RECEIVED!$O$2:$O$10000, RENT_RECEIVED!$B$2:$B$10000, "LEASE-BH-F4-2025", RENT_RECEIVED!$E$2:$E$10000, "<"&DATE(2025,5,22)), 0) -> 0 | K5: =G5 - H5 -> 0 | L5: =J5 + K5 -> 0 | M5: =H5 * 0.1500 -> 0 | N5: =H5 * 0.0000 -> 0 | O5: =ABS(M5 + N5) -> 0 | Q5: =SUMIFS(EXPENSES!E:E, EXPENSES!B:B, "LEASE-BH-F4-2025", EXPENSES!D:D, ">="&DATE(2025,5,22), EXPENSES!D:D, "<="&DATE(2025,6,21)) -> 0 | S5: =H5 - O5 - Q5 -> 0 | Y5: 6390.75 | Z5: =S5-Y5 -> 0 | AA5: PAID | AB5: MULTIPLE | AC5: 45982
A6: LEASE-BH-F5-2025 | B6: Flat 5 - 3 West Gate | C6: Achal (Delegated for Udayan) | D6: Mr Amos Blyth | E6: 45698 | F6: 10 | G6: =IFERROR(SUMPRODUCT((RENT_DUE!$B$2:$B$1000="LEASE-BH-F5-2025")*(RENT_DUE!$D$2:$D$1000>=DATE(2025,5,22))*(RENT_DUE!$D$2:$D$1000<=DATE(2025,6,21))*RENT_DUE!$L$2:$L$1000), 0) -> 0 | H6: =IFERROR(SUMPRODUCT((RENT_RECEIVED!$B$2:$B$1000="LEASE-BH-F5-2025")*(RENT_RECEIVED!$E$2:$E$1000>=DATE(2025,5,22))*(RENT_RECEIVED!$E$2:$E$1000<=DATE(2025,6,21))*RENT_RECEIVED!$O$2:$O$1000), 0) -> 0 | J6: =IFERROR(SUMIFS(RENT_DUE!$L$2:$L$10000, RENT_DUE!$B$2:$B$10000, "LEASE-BH-F5-2025", RENT_DUE!$D$2:$D$10000, "<"&DATE(2025,5,22)), 0) - IFERROR(SUMIFS(RENT_RECEIVED!$O$2:$O$10000, RENT_RECEIVED!$B$2:$B$10000, "LEASE-BH-F5-2025", RENT_RECEIVED!$E$2:$E$10000, "<"&DATE(2025,5,22)), 0) -> 0 | K6: =G6 - H6 -> 0 | L6: =J6 + K6 -> 0 | M6: =H6 * 0.1500 -> 0 | N6: =H6 * 0.0000 -> 0 | O6: =ABS(M6 + N6) -> 0 | Q6: =SUMIFS(EXPENSES!E:E, EXPENSES!B:B, "LEASE-BH-F5-2025", EXPENSES!D:D, ">="&DATE(2025,5,22), EXPENSES!D:D, "<="&DATE(2025,6,21)) -> 0 | S6: =H6 - O6 - Q6 -> 0 | Y6: 6140 | Z6: =S6-Y6 -> 0 | AA6: PAID | AB6: MULTIPLE | AC6: 45982
A7: LEASE-BH-F6-2025 | B7: Flat 6 - 3 West Gate | C7: Achal (Delegated for Udayan) | D7: Miss Shelley Lees | E7: 45744 | F7: 28 | G7: =IFERROR(SUMPRODUCT((RENT_DUE!$B$2:$B$1000="LEASE-BH-F6-2025")*(RENT_DUE!$D$2:$D$1000>=DATE(2025,5,22))*(RENT_DUE!$D$2:$D$1000<=DATE(2025,6,21))*RENT_DUE!$L$2:$L$1000), 0) -> 0 | H7: =IFERROR(SUMPRODUCT((RENT_RECEIVED!$B$2:$B$1000="LEASE-BH-F6-2025")*(RENT_RECEIVED!$E$2:$E$1000>=DATE(2025,5,22))*(RENT_RECEIVED!$E$2:$E$1000<=DATE(2025,6,21))*RENT_RECEIVED!$O$2:$O$1000), 0) -> 0 | I7: HIST-2025-05-1565 | J7: =IFERROR(SUMIFS(RENT_DUE!$L$2:$L$10000, RENT_DUE!$B$2:$B$10000, "LEASE-BH-F6-2025", RENT_DUE!$D$2:$D$10000, "<"&DATE(2025,5,22)), 0) - IFERROR(SUMIFS(RENT_RECEIVED!$O$2:$O$10000, RENT_RECEIVED!$B$2:$B$10000, "LEASE-BH-F6-2025", RENT_RECEIVED!$E$2:$E$10000, "<"&DATE(2025,5,22)), 0) -> 0 | K7: =G7 - H7 -> 0 | L7: =J7 + K7 -> 0 | M7: =H7 * 0.1500 -> 0 | N7: =H7 * 0.0000 -> 0 | O7: =ABS(M7 + N7) -> 0 | Q7: =SUMIFS(EXPENSES!E:E, EXPENSES!B:B, "LEASE-BH-F6-2025", EXPENSES!D:D, ">="&DATE(2025,5,22), EXPENSES!D:D, "<="&DATE(2025,6,21)) -> 0 | S7: =H7 - O7 - Q7 -> 0 | Y7: 4882 | Z7: =S7-Y7 -> 0 | AA7: PAID | AB7: MULTIPLE | AC7: 45982
A8: LEASE-BH-F7-2025 | B8: Flat 7 - 3 West Gate | C8: Achal (Delegated for Udayan) | D8: Mr Chun Hung Tang | E8: 45707 | F8: 19 | G8: =IFERROR(SUMPRODUCT((RENT_DUE!$B$2:$B$1000="LEASE-BH-F7-2025")*(RENT_DUE!$D$2:$D$1000>=DATE(2025,5,22))*(RENT_DUE!$D$2:$D$1000<=DATE(2025,6,21))*RENT_DUE!$L$2:$L$1000), 0) -> 0 | H8: =IFERROR(SUMPRODUCT((RENT_RECEIVED!$B$2:$B$1000="LEASE-BH-F7-2025")*(RENT_RECEIVED!$E$2:$E$1000>=DATE(2025,5,22))*(RENT_RECEIVED!$E$2:$E$1000<=DATE(2025,6,21))*RENT_RECEIVED!$O$2:$O$1000), 0) -> 0 | J8: =IFERROR(SUMIFS(RENT_DUE!$L$2:$L$10000, RENT_DUE!$B$2:$B$10000, "LEASE-BH-F7-2025", RENT_DUE!$D$2:$D$10000, "<"&DATE(2025,5,22)), 0) - IFERROR(SUMIFS(RENT_RECEIVED!$O$2:$O$10000, RENT_RECEIVED!$B$2:$B$10000, "LEASE-BH-F7-2025", RENT_RECEIVED!$E$2:$E$10000, "<"&DATE(2025,5,22)), 0) -> 0 | K8: =G8 - H8 -> 0 | L8: =J8 + K8 -> 0 | M8: =H8 * 0.1500 -> 0 | N8: =H8 * 0.0000 -> 0 | O8: =ABS(M8 + N8) -> 0 | Q8: =SUMIFS(EXPENSES!E:E, EXPENSES!B:B, "LEASE-BH-F7-2025", EXPENSES!D:D, ">="&DATE(2025,5,22), EXPENSES!D:D, "<="&DATE(2025,6,21)) -> 0 | S8: =H8 - O8 - Q8 -> 0 | Y8: 3570 | Z8: =S8-Y8 -> 0 | AA8: PAID | AB8: MULTIPLE | AC8: 45861
A9: LEASE-BH-F8-2025 | B9: Flat 8 - 3 West Gate | C9: Achal (Delegated for Udayan) | D9: Mr Shermal Wijesinghage, Mrs Udeshika Dona | E9: 45712 | F9: 24 | G9: =IFERROR(SUMPRODUCT((RENT_DUE!$B$2:$B$1000="LEASE-BH-F8-2025")*(RENT_DUE!$D$2:$D$1000>=DATE(2025,5,22))*(RENT_DUE!$D$2:$D$1000<=DATE(2025,6,21))*RENT_DUE!$L$2:$L$1000), 0) -> 0 | H9: =IFERROR(SUMPRODUCT((RENT_RECEIVED!$B$2:$B$1000="LEASE-BH-F8-2025")*(RENT_RECEIVED!$E$2:$E$1000>=DATE(2025,5,22))*(RENT_RECEIVED!$E$2:$E$1000<=DATE(2025,6,21))*RENT_RECEIVED!$O$2:$O$1000), 0) -> 0 | I9: HIST-2025-07-1591 | J9: =IFERROR(SUMIFS(RENT_DUE!$L$2:$L$10000, RENT_DUE!$B$2:$B$10000, "LEASE-BH-F8-2025", RENT_DUE!$D$2:$D$10000, "<"&DATE(2025,5,22)), 0) - IFERROR(SUMIFS(RENT_RECEIVED!$O$2:$O$10000, RENT_RECEIVED!$B$2:$B$10000, "LEASE-BH-F8-2025", RENT_RECEIVED!$E$2:$E$10000, "<"&DATE(2025,5,22)), 0) -> 0 | K9: =G9 - H9 -> 0 | L9: =J9 + K9 -> 0 | M9: =H9 * 0.1500 -> 0 | N9: =H9 * 0.0000 -> 0 | O9: =ABS(M9 + N9) -> 0 | Q9: =SUMIFS(EXPENSES!E:E, EXPENSES!B:B, "LEASE-BH-F8-2025", EXPENSES!D:D, ">="&DATE(2025,5,22), EXPENSES!D:D, "<="&DATE(2025,6,21)) -> 0 | S9: =H9 - O9 - Q9 -> 0 | Y9: 5318.75 | Z9: =S9-Y9 -> 0 | AA9: PAID | AB9: MULTIPLE | AC9: 45982
